Workbook
Name Approach: 'CMSCore 2.8'!$O$3
Name Approach: 'ONESheet 2.8'!$O$3
Name BillingCountry: 'CMSCore 2.8'!$O$10
Name BillingCountry: 'ONESheet 2.8'!$O$10
Name BillingCountryCurrency: 'CMSCore 2.8'!$O$11
Name BillingCountryCurrency: 'ONESheet 2.8'!$O$11
Name BillingCurrencyTRM: 'CMSCore 2.8'!$X$21
Name BillingCurrencyTRM: 'ONESheet 2.8'!$X$21
Name BusinessCurrency: 'CMSCore 2.8'!$O$13
Name BusinessCurrency: 'ONESheet 2.8'!$O$13
Name BusinessCurrencyTRM: 'CMSCore 2.8'!$O$14
Name BusinessCurrencyTRM: 'ONESheet 2.8'!$O$14
Name CustomerCountry: 'CMSCore 2.8'!$C$3
Name CustomerCountry: 'ONESheet 2.8'!$C$3
Name HoursPerDayTeamBased: 'CMSCore 2.8'!$O$4
Name HoursPerDayTeamBased: 'ONESheet 2.8'!$O$4

Sheet ONESheet 2.8
A1: Scope | N1: Delivery Cost - Internal Use | AC1: Price - Internal Use | AT1: Año 1 Ingreso Mensual | BA1: Año 2 Ingreso Mensual | BH1: Año 3 Ingreso Mensual | BO1: Año 4 Ingreso Mensual | BV1: Año 5 Ingreso Mensual
B2: Fields with * are mandatory for both DealReview and HandOff; ** denotes HandOff-only requirements | N2: Fields with * are mandatory for both DealReview and HandOff; ** denotes HandOff-only requirements
B3: Customer Country * | C3: Noram | N3: Approach * | O3: By Hours | U3: HOURS | V3: =_xlfn.CONCAT("DELIVERY COST (",BillingCountryCurrency,")") -> DELIVERY COST (USD) | W3: =_xlfn.CONCAT("DELIVERY COST (",IF(ISBLANK(BusinessCurrency),"N/A",BusinessCurrency),")") -> DELIVERY COST (N/A) | AD3: =_xlfn.CONCAT("PRICING (",BillingCountryCurrency,")") -> PRICING (USD) | AE3: =_xlfn.CONCAT("PRICING (",IF(ISBLANK(BusinessCurrency),"N/A",BusinessCurrency),")") -> PRICING (N/A) | AF3: + | AG3: =_xlfn.CONCAT("Intercompany (",BillingCountryCurrency,")") -> Intercompany (USD) | AH3: =_xlfn.CONCAT("Intercompany (",IF(ISBLANK(BusinessCurrency),"N/A",BusinessCurrency),")") -> Intercompany (N/A) | AI3: + | AJ3: =_xlfn.CONCAT("WHT (",BillingCountryCurrency,")") -> WHT (USD) | AK3: =_xlfn.CONCAT("WHT (",IF(ISBLANK(BusinessCurrency),"N/A",BusinessCurrency),")") -> WHT (N/A) | AM3: = | AN3: =_xlfn.CONCAT("BUSINESS VOLUME (",BillingCountryCurrency,")") -> BUSINESS VOLUME (USD) | AO3: =_xlfn.CONCAT("BUSINESS VOLUME (",IF(ISBLANK(BusinessCurrency),"N/A",BusinessCurrency),")") -> BUSINESS VOLUME (N/A) | AS3: MILESTONES | AV3: =BillingCountryCurrency -> USD | AW3: =IF(ISBLANK(BusinessCurrency),"N/A",BusinessCurrency) -> N/A | BA3: MILESTONES | BC3: =BillingCountryCurrency -> USD | BD3: =IF(ISBLANK(BusinessCurrency),"N/A",BusinessCurrency) -> N/A | BH3: MILESTONES | BJ3: =BillingCountryCurrency -> USD | BK3: =IF(ISBLANK(BusinessCurrency),"N/A",BusinessCurrency) -> N/A | BO3: MILESTONES | BQ3: =BillingCountryCurrency -> USD | BR3: =IF(ISBLANK(BusinessCurrency),"N/A",BusinessCurrency) -> N/A | BV3: MILESTONES | BX3: =BillingCountryCurrency -> USD | BY3: =IF(ISBLANK(BusinessCurrency),"N/A",BusinessCurrency) -> N/A
B4: Customer Name * | C4: Gama Mobility | N4: =IF(Approach="By Hours", "N/A for ByHours", "Hours/Day") -> N/A for ByHours | O4: 8.1 | T4: SERVICE COSTS | AC4: SERVICE PRICE | AS4: Hito 1 | AU4: 0 | AV4: 0 | AW4: =IFERROR(AV4/BusinessCurrencyTRM,"N/A") -> N/A | BA4: Hito 1 | BB4: 0 | BC4: 0 | BD4: =IFERROR(BC4/BusinessCurrencyTRM,"N/A") -> N/A | BH4: Hito 1 | BI4: 0 | BJ4: 0 | BK4: =IFERROR(BJ4/BusinessCurrencyTRM,"N/A") -> N/A | BO4: Hito 1 | BP4: 0 | BQ4: 0 | BR4: =IFERROR(BQ4/BusinessCurrencyTRM,"N/A") -> N/A | BV4: Hito 1 | BW4: 0 | BX4: 0 | BY4: =IFERROR(BX4/BusinessCurrencyTRM,"N/A") -> N/A
B5: Project Name * | C5: Modern SecOps Envisioning Workshop (Sentinel) | T5: Consultant Team | U5: =IFERROR(SUMIFS(O:O,Y:Y,"varTotalConsultant"),0) -> 91.12 | V5: =IFERROR(SUMIFS(V:V,Y:Y,"varTotalConsultant"),0) -> 3336.8144 | W5: =IFERROR(V5/BusinessCurrencyTRM,"N/A") -> N/A | AC5: Consultant Team | AD5: =IFERROR(SUMIF(Y:Y,"varTotalConsultant",AD:AD),0) -> 5213.8864 | AE5: =IFERROR(AD5/BusinessCurrencyTRM,"N/A") -> N/A | AG5: =IFERROR(SUMIF(Y:Y,"varTotalConsultant",AG:AG),0) -> 0 | AH5: =IFERROR(AG5/BusinessCurrencyTRM,"N/A") -> N/A | AJ5: =IFERROR(SUMIF(Y:Y,"varTotalConsultant",AJ:AJ),0) -> 0 | AK5: =IFERROR(AJ5/BusinessCurrencyTRM,"N/A") -> N/A | AN5: =SUM(AD5,AG5,AJ5) -> 5213.8864 | AO5: =IFERROR(AN5/BusinessCurrencyTRM,"N/A") -> N/A | AS5: Hito 2 | AU5: 0 | AV5: 0 | AW5: =IFERROR(AV5/BusinessCurrencyTRM,"N/A") -> N/A | BA5: Hito 2 | BB5: 0 | BC5: 0 | BD5: =IFERROR(BC5/BusinessCurrencyTRM,"N/A") -> N/A | BH5: Hito 2 | BI5: 0 | BJ5: 0 | BK5: =IFERROR(BJ5/BusinessCurrencyTRM,"N/A") -> N/A | BO5: Hito 2 | BP5: 0 | BQ5: 0 | BR5: =IFERROR(BQ5/BusinessCurrencyTRM,"N/A") -> N/A | BV5: Hito 2 | BW5: 0 | BX5: 0 | BY5: =IFERROR(BX5/BusinessCurrencyTRM,"N/A") -> N/A
B6: Opp ID * | C6: OPP-2026-713922 | N6: Account Manager * | O6: jose.jalabert@softwareone.com | T6: Project Managment | U6: =IFERROR(SUMIFS(O:O,Y:Y,"varTotalPM"),0) -> 18.224 | V6: =IFERROR(SUMIFS(V:V,Y:Y,"varTotalPM"),0) -> 863.8176 | W6: =IFERROR(V6/BusinessCurrencyTRM,"N/A") -> N/A | AC6: Project Managment | AD6: =IFERROR(SUMIF(Y:Y,"varTotalPM",AD:AD),0) -> 1349.8517 | AE6: =IFERROR(AD6/BusinessCurrencyTRM,"N/A") -> N/A | AG6: =IFERROR(SUMIF(Y:Y,"varTotalPM",AG:AG),0) -> 0 | AH6: =IFERROR(AG6/BusinessCurrencyTRM,"N/A") -> N/A | AJ6: =IFERROR(SUMIF(Y:Y,"varTotalPM",AJ:AJ),0) -> 0 | AK6: =IFERROR(AJ6/BusinessCurrencyTRM,"N/A") -> N/A | AN6: =SUM(AD6,AG6,AJ6) -> 1349.8517 | AO6: =IFERROR(AN6/BusinessCurrencyTRM,"N/A") -> N/A | AS6: Hito 3 | AU6: 0 | AV6: 0 | AW6: =IFERROR(AV6/BusinessCurrencyTRM,"N/A") -> N/A | BA6: Hito 3 | BB6: 0 | BC6: 0 | BD6: =IFERROR(BC6/BusinessCurrencyTRM,"N/A") -> N/A | BH6: Hito 3 | BI6: 0 | BJ6: 0 | BK6: =IFERROR(BJ6/BusinessCurrencyTRM,"N/A") -> N/A | BO6: Hito 3 | BP6: 0 | BQ6: 0 | BR6: =IFERROR(BQ6/BusinessCurrencyTRM,"N/A") -> N/A | BV6: Hito 3 | BW6: 0 | BX6: 0 | BY6: =IFERROR(BX6/BusinessCurrencyTRM,"N/A") -> N/A
B7: SWO Job ID / PRJ | N7: Pre-sale in Sale * | O7: claudio.toledo@softwareone.com | T7: Subtotal | U7: =IFERROR(SUM(U5:U6),0) -> 109.344 | V7: =IFERROR(SUM($V$5:$V$6),0) -> 4200.632 | W7: =IFERROR(V7/BusinessCurrencyTRM,"N/A") -> N/A | AC7: Subtotal | AD7: =IFERROR(SUM(AD5:AD6),0) -> 6563.7381 | AE7: =IFERROR(AD7/BusinessCurrencyTRM,"N/A") -> N/A | AG7: =IFERROR(SUM(AG5:AG6),0) -> 0 | AH7: =IFERROR(AG7/BusinessCurrencyTRM,"N/A") -> N/A | AJ7: =IFERROR(SUM(AJ5:AJ6),0) -> 0 | AK7: =IFERROR(AJ7/BusinessCurrencyTRM,"N/A") -> N/A | AN7: =IFERROR(SUM(AN5:AN6),0) -> 6563.7381 | AO7: =IFERROR(AN7/BusinessCurrencyTRM,"N/A") -> N/A | AS7: Hito 4 | AU7: 0 | AV7: 0 | AW7: =IFERROR(AV7/BusinessCurrencyTRM,"N/A") -> N/A | BA7: Hito 4 | BB7: 0 | BC7: 0 | BD7: =IFERROR(BC7/BusinessCurrencyTRM,"N/A") -> N/A | BH7: Hito 4 | BI7: 0 | BJ7: 0 | BK7: =IFERROR(BJ7/BusinessCurrencyTRM,"N/A") -> N/A | BO7: Hito 4 | BP7: 0 | BQ7: 0 | BR7: =IFERROR(BQ7/BusinessCurrencyTRM,"N/A") -> N/A | BV7: Hito 4 | BW7: 0 | BX7: 0 | BY7: =IFERROR(BX7/BusinessCurrencyTRM,"N/A") -> N/A
B8: Main Business Line * | C8: Cibersecurity | N8: Pre-sale in Delivery * | AS8: Hito 5 | AU8: 0 | AV8: 0 | AW8: =IFERROR(AV8/BusinessCurrencyTRM,"N/A") -> N/A | BA8: Hito 5 | BB8: 0 | BC8: 0 | BD8: =IFERROR(BC8/BusinessCurrencyTRM,"N/A") -> N/A | BH8: Hito 5 | BI8: 0 | BJ8: 0 | BK8: =IFERROR(BJ8/BusinessCurrencyTRM,"N/A") -> N/A | BO8: Hito 5 | BP8: 0 | BQ8: 0 | BR8: =IFERROR(BQ8/BusinessCurrencyTRM,"N/A") -> N/A | BV8: Hito 5 | BW8: 0 | BX8: 0 | BY8: =IFERROR(BX8/BusinessCurrencyTRM,"N/A") -> N/A
B9: Funding * | T9: OTHER COSTS | AC9: OTHER PRICES | AS9: Hito 6 | AU9: 0 | AV9: 0 | AW9: =IFERROR(AV9/BusinessCurrencyTRM,"N/A") -> N/A | BA9: Hito 6 | BB9: 0 | BC9: 0 | BD9: =IFERROR(BC9/BusinessCurrencyTRM,"N/A") -> N/A | BH9: Hito 6 | BI9: 0 | BJ9: 0 | BK9: =IFERROR(BJ9/BusinessCurrencyTRM,"N/A") -> N/A | BO9: Hito 6 | BP9: 0 | BQ9: 0 | BR9: =IFERROR(BQ9/BusinessCurrencyTRM,"N/A") -> N/A | BV9: Hito 6 | BW9: 0 | BX9: 0 | BY9: =IFERROR(BX9/BusinessCurrencyTRM,"N/A") -> N/A
B10: OPP Type * | N10: Billing Country * | O10: =CustomerCountry -> Noram | T10: Risks | V10: =IFERROR(SUMIF(Y:Y,"varTotalRisks",V:V),0) -> 0 | W10: =IFERROR(V10/BusinessCurrencyTRM,"N/A") -> N/A | AC10: Risks | AD10: =IFERROR(SUMIF(Y:Y,"varTotalRisks",AD:AD),0) -> 0 | AE10: =IFERROR(AD10/BusinessCurrencyTRM,"N/A") -> N/A | AG10: =IFERROR(SUMIF(Y:Y,"varTotalRisks",AG:AG),0) -> 0 | AH10: =IFERROR(AG10/BusinessCurrencyTRM,"N/A") -> N/A | AJ10: =IFERROR(SUMIF(Y:Y,"varTotalRisks",AJ:AJ),0) -> 0 | AK10: =IFERROR(AJ10/BusinessCurrencyTRM,"N/A") -> N/A | AN10: =SUM(AD10,AG10,AJ10) -> 0 | AO10: =IFERROR(AN10/BusinessCurrencyTRM,"N/A") -> N/A | AS10: Hito 7 | AU10: 0 | AV10: 0 | AW10: =IFERROR(AV10/BusinessCurrencyTRM,"N/A") -> N/A | BA10: Hito 7 | BB10: 0 | BC10: 0 | BD10: =IFERROR(BC10/BusinessCurrencyTRM,"N/A") -> N/A | BH10: Hito 7 | BI10: 0 | BJ10: 0 | BK10: =IFERROR(BJ10/BusinessCurrencyTRM,"N/A") -> N/A | BO10: Hito 7 | BP10: 0 | BQ10: 0 | BR10: =IFERROR(BQ10/BusinessCurrencyTRM,"N/A") -> N/A | BV10: Hito 7 | BW10: 0 | BX10: 0 | BY10: =IFERROR(BX10/BusinessCurrencyTRM,"N/A") -> N/A
N11: Billing Country Currency * | O11: =INDEX(Paramenters!$C$28:$C$85,MATCH(BillingCountry,Paramenters!$A$28:$A$85,0)) -> USD | T11: Pay Rise | V11: =IFERROR(SUMIF(Y:Y,"varTotalPayRise",V:V),0) -> 0 | W11: =IFERROR(V11/BusinessCurrencyTRM,"N/A") -> N/A | AC11: Salary Increase | AD11: =IFERROR(SUMIF(Y:Y,"varTotalPayRise",AD:AD),0) -> 0 | AE11: =IFERROR(AD11/BusinessCurrencyTRM,"N/A") -> N/A | AG11: =IFERROR(SUMIF(Y:Y,"varTotalPayRise",AG:AG),0) -> 0 | AH11: =IFERROR(AG11/BusinessCurrencyTRM,"N/A") -> N/A | AJ11: =IFERROR(SUMIF(Y:Y,"varTotalPayRise",AJ:AJ),0) -> 0 | AK11: =IFERROR(AJ11/BusinessCurrencyTRM,"N/A") -> N/A | AN11: =SUM(AD11,AG11,AJ11) -> 0 | AO11: =IFERROR(AN11/BusinessCurrencyTRM,"N/A") -> N/A | AS11: Hito 8 | AU11: 0 | AV11: 0 | AW11: =IFERROR(AV11/BusinessCurrencyTRM,"N/A") -> N/A | BA11: Hito 8 | BB11: 0 | BC11: 0 | BD11: =IFERROR(BC11/BusinessCurrencyTRM,"N/A") -> N/A | BH11: Hito 8 | BI11: 0 | BJ11: 0 | BK11: =IFERROR(BJ11/BusinessCurrencyTRM,"N/A") -> N/A | BO11: Hito 8 | BP11: 0 | BQ11: 0 | BR11: =IFERROR(BQ11/BusinessCurrencyTRM,"N/A") -> N/A | BV11: Hito 8 | BW11: 0 | BX11: 0 | BY11: =IFERROR(BX11/BusinessCurrencyTRM,"N/A") -> N/A
B12: SKUs Business Line SWO * | C12: SKUs OneSales Descripcion * | T12: Products | V12: =IFERROR(SUMIF(Y:Y,"varTotalProducts",V:V),0) -> 0 | W12: =IFERROR(V12/BusinessCurrencyTRM,"N/A") -> N/A | AC12: Products | AD12: =IFERROR(SUMIF(Y:Y,"varTotalProducts",AD:AD),0) -> 0 | AE12: =IFERROR(AD12/BusinessCurrencyTRM,"N/A") -> N/A | AG12: =IFERROR(SUMIF(Y:Y,"varTotalProducts",AG:AG),0) -> 0 | AH12: =IFERROR(AG12/BusinessCurrencyTRM,"N/A") -> N/A | AJ12: =IFERROR(SUMIF(Y:Y,"varTotalProducts",AJ:AJ),0) -> 0 | AK12: =IFERROR(AJ12/BusinessCurrencyTRM,"N/A") -> N/A | AN12: =SUM(AD12,AG12,AJ12) -> 0 | AO12: =IFERROR(AN12/BusinessCurrencyTRM,"N/A") -> N/A | AS12: Hito 9 | AU12: 0 | AV12: 0 | AW12: =IFERROR(AV12/BusinessCurrencyTRM,"N/A") -> N/A | BA12: Hito 9 | BB12: 0 | BC12: 0 | BD12: =IFERROR(BC12/BusinessCurrencyTRM,"N/A") -> N/A | BH12: Hito 9 | BI12: 0 | BJ12: 0 | BK12: =IFERROR(BJ12/BusinessCurrencyTRM,"N/A") -> N/A | BO12: Hito 9 | BP12: 0 | BQ12: 0 | BR12: =IFERROR(BQ12/BusinessCurrencyTRM,"N/A") -> N/A | BV12: Hito 9 | BW12: 0 | BX12: 0 | BY12: =IFERROR(BX12/BusinessCurrencyTRM,"N/A") -> N/A
N13: Business Currency | T13: Vendors | V13: =IFERROR(SUMIF(Y:Y,"varTotalVAR",V:V),0) -> 0 | W13: =IFERROR(V13/BusinessCurrencyTRM,"N/A") -> N/A | AC13: Vendors | AD13: =IFERROR(SUMIF(Y:Y,"varTotalVAR",AD:AD),0) -> 0 | AE13: =IFERROR(AD13/BusinessCurrencyTRM,"N/A") -> N/A | AG13: =IFERROR(SUMIF(Y:Y,"varTotalVAR",AG:AG),0) -> 0 | AH13: =IFERROR(AG13/BusinessCurrencyTRM,"N/A") -> N/A | AJ13: =IFERROR(SUMIF(Y:Y,"varTotalVAR",AJ:AJ),0) -> 0 | AK13: =IFERROR(AJ13/BusinessCurrencyTRM,"N/A") -> N/A | AN13: =SUM(AD13,AG13,AJ13) -> 0 | AO13: =IFERROR(AN13/BusinessCurrencyTRM,"N/A") -> N/A | AS13: Hito 10 | AU13: 0 | AV13: 0 | AW13: =IFERROR(AV13/BusinessCurrencyTRM,"N/A") -> N/A | BA13: Hito 10 | BB13: 0 | BC13: 0 | BD13: =IFERROR(BC13/BusinessCurrencyTRM,"N/A") -> N/A | BH13: Hito 10 | BI13: 0 | BJ13: 0 | BK13: =IFERROR(BJ13/BusinessCurrencyTRM,"N/A") -> N/A | BO13: Hito 10 | BP13: 0 | BQ13: 0 | BR13: =IFERROR(BQ13/BusinessCurrencyTRM,"N/A") -> N/A | BV13: Hito 10 | BW13: 0 | BX13: 0 | BY13: =IFERROR(BX13/BusinessCurrencyTRM,"N/A") -> N/A
N14: Currency Exchange Rate | T14: Insurances | V14: =IFERROR(SUMIF(Y:Y,"varTotalInsurances",V:V),0) -> 0 | W14: =IFERROR(V14/BusinessCurrencyTRM,"N/A") -> N/A | AC14: Insurances | AD14: =IFERROR(SUMIF(Y:Y,"varTotalInsurances",AD:AD),0) -> 0 | AE14: =IFERROR(AD14/BusinessCurrencyTRM,"N/A") -> N/A | AG14: =IFERROR(SUMIF(Y:Y,"varTotalInsurances",AG:AG),0) -> 0 | AH14: =IFERROR(AG14/BusinessCurrencyTRM,"N/A") -> N/A | AJ14: =IFERROR(SUMIF(Y:Y,"varTotalInsurances",AJ:AJ),0) -> 0 | AK14: =IFERROR(AJ14/BusinessCurrencyTRM,"N/A") -> N/A | AN14: =SUM(AD14,AG14,AJ14) -> 0 | AO14: =IFERROR(AN14/BusinessCurrencyTRM,"N/A") -> N/A | AS14: Hito 11 | AU14: 0 | AV14: 0 | AW14: =IFERROR(AV14/BusinessCurrencyTRM,"N/A") -> N/A | BA14: Hito 11 | BB14: 0 | BC14: 0 | BD14: =IFERROR(BC14/BusinessCurrencyTRM,"N/A") -> N/A | BH14: Hito 11 | BI14: 0 | BJ14: 0 | BK14: =IFERROR(BJ14/BusinessCurrencyTRM,"N/A") -> N/A | BO14: Hito 11 | BP14: 0 | BQ14: 0 | BR14: =IFERROR(BQ14/BusinessCurrencyTRM,"N/A") -> N/A | BV14: Hito 11 | BW14: 0 | BX14: 0 | BY14: =IFERROR(BX14/BusinessCurrencyTRM,"N/A") -> N/A
N15: Exchange Rate Request Date | T15: Others | V15: =IFERROR(SUMIF(Y:Y,"varTotalOthers",V:V),0) -> 0 | W15: =IFERROR(V15/BusinessCurrencyTRM,"N/A") -> N/A | AC15: Others | AD15: =IFERROR(SUMIF(Y:Y,"varTotalOthers",AD:AD),0) -> 0 | AE15: =IFERROR(AD15/BusinessCurrencyTRM,"N/A") -> N/A | AG15: =IFERROR(SUMIF(Y:Y,"varTotalOthers",AG:AG),0) -> 0 | AH15: =IFERROR(AG15/BusinessCurrencyTRM,"N/A") -> N/A | AJ15: =IFERROR(SUMIF(Y:Y,"varTotalOthers",AJ:AJ),0) -> 0 | AK15: =IFERROR(AJ15/BusinessCurrencyTRM,"N/A") -> N/A | AN15: =SUM(AD15,AG15,AJ15) -> 0 | AO15: =IFERROR(AN15/BusinessCurrencyTRM,"N/A") -> N/A | AS15: Hito 12 | AU15: 0 | AV15: 0 | AW15: =IFERROR(AV15/BusinessCurrencyTRM,"N/A") -> N/A | BA15: Hito 12 | BB15: 0 | BC15: 0 | BD15: =IFERROR(BC15/BusinessCurrencyTRM,"N/A") -> N/A | BH15: Hito 12 | BI15: 0 | BJ15: 0 | BK15: =IFERROR(BJ15/BusinessCurrencyTRM,"N/A") -> N/A | BO15: Hito 12 | BP15: 0 | BQ15: 0 | BR15: =IFERROR(BQ15/BusinessCurrencyTRM,"N/A") -> N/A | BV15: Hito 12 | BW15: 0 | BX15: 0 | BY15: =IFERROR(BX15/BusinessCurrencyTRM,"N/A") -> N/A
O16: =IF(ISBLANK(BusinessCurrency),"","* Request the official TRM/RMR from the financial area and/or official url in each billing country") | T16: Subtotal | V16: =IFERROR(SUM(V10:V15),0) -> 0 | W16: =IFERROR(V16/BusinessCurrencyTRM,"N/A") -> N/A | AC16: Subtotal | AD16: =IFERROR(SUM(AD10:AD15),0) -> 0 | AE16: =IFERROR(AD16/BusinessCurrencyTRM,"N/A") -> N/A | AG16: =IFERROR(SUM(AG10:AG15),0) -> 0 | AH16: =IFERROR(AG16/BusinessCurrencyTRM,"N/A") -> N/A | AJ16: =IFERROR(SUM(AJ10:AJ15),0) -> 0 | AK16: =IFERROR(AJ16/BusinessCurrencyTRM,"N/A") -> N/A | AN16: =IFERROR(SUM(AN10:AN15),0) -> 0 | AO16: =IFERROR(AN16/BusinessCurrencyTRM,"N/A") -> N/A | AU16: =SUM(AU4:AU15) -> 0 | AV16: =SUM(AV4:AV15) -> 0 | AW16: =SUM(AW4:AW15) -> 0 | BB16: =SUM(BB4:BB15) -> 0 | BC16: =SUM(BC4:BC15) -> 0 | BD16: =SUM(BD4:BD15) -> 0 | BI16: =SUM(BI4:BI15) -> 0 | BJ16: =SUM(BJ4:BJ15) -> 0 | BK16: =SUM(BK4:BK15) -> 0 | BP16: =SUM(BP4:BP15) -> 0 | BQ16: =SUM(BQ4:BQ15) -> 0 | BR16: =SUM(BR4:BR15) -> 0 | BW16: =SUM(BW4:BW15) -> 0 | BX16: =SUM(BX4:BX15) -> 0 | BY16: =SUM(BY4:BY15) -> 0
B17: Deal Comments
B18: Market B | AV18: =BillingCountryCurrency -> USD | AW18: =IF(ISBLANK(BusinessCurrency),"N/A",BusinessCurrency) -> N/A
AC19: SUBTOTAL | AD19: =SUM(AD7,AD16) -> 6563.7381 | AE19: =IFERROR(AD19/BusinessCurrencyTRM,"N/A") -> N/A | AG19: =SUM(AG7,AG16) -> 0 | AH19: =IFERROR(AG19/BusinessCurrencyTRM,"N/A") -> N/A | AJ19: =SUM(AJ7,AJ16) -> 0 | AK19: =IFERROR(AJ19/BusinessCurrencyTRM,"N/A") -> N/A | AN19: =SUM(AN7,AN16) -> 6563.7381 | AO19: =IFERROR(AN19/BusinessCurrencyTRM,"N/A") -> N/A | AS19: BUSINESS PRICE | AV19: =AN21 -> 6499.9981 | AW19: =IFERROR(AV19/BusinessCurrencyTRM,"N/A") -> N/A
AC20: ADDITIONAL GP | AD20: -63.74 | AE20: =IFERROR(AD20/BusinessCurrencyTRM,"N/A") -> N/A | AG20: 0 | AH20: =IFERROR(AG20/BusinessCurrencyTRM,"N/A") -> N/A | AJ20: 0 | AK20: =IFERROR(AJ20/BusinessCurrencyTRM,"N/A") -> N/A | AN20: =SUM(AD20,AG20,AJ20) -> -63.74 | AO20: =IFERROR(AN20/BusinessCurrencyTRM,"N/A") -> N/A | AS20: DELIVERY COST | AV20: =SUM($V$21,$AG$21,$AJ$21) -> 4200.632 | AW20: =IFERROR(AV20/BusinessCurrencyTRM,"N/A") -> N/A
N21: =IF(CustomerCountry="Colombia","Impuesto de Timbre","") | O21: =IF(CustomerCountry="Colombia","Aplica a nuevos contratos donde la cuantia supera los 6.000 UVT (COP 298.794.000)","") | T21: TOTAL COSTS | V21: =V7+V16 -> 4200.632 | W21: =IFERROR(V21/BusinessCurrencyTRM,"N/A") -> N/A | X21: =INDEX(Paramenters!$D$28:$D$85,MATCH(BillingCountryCurrency,Paramenters!$C$28:$C$85,0)) -> 1.2788018 | Y21: BillingCurrencyTRM | AC21: TOTAL PRICE | AD21: =SUM(AD19:AD20) -> 6499.9981 | AE21: =IFERROR(AD21/BusinessCurrencyTRM,"N/A") -> N/A | AG21: =SUM(AG19:AG20) -> 0 | AH21: =IFERROR(AG21/BusinessCurrencyTRM,"N/A") -> N/A | AJ21: =SUM(AJ19:AJ20) -> 0 | AK21: =IFERROR(AJ21/BusinessCurrencyTRM,"N/A") -> N/A | AN21: =SUM(AN19:AN20) -> 6499.9981 | AO21: =IFERROR(AN21/BusinessCurrencyTRM,"N/A") -> N/A | AS21: % CONTRIBUTION MARGIN | AV21: =IFERROR(1-AV20/AV19,0) -> 0.35374873
B24: (Note 1) To add new phases/stages/blocks, it is recommended to use the phase/stage/block called "Phase_Name_7" which does not have fixed references and allows maintaining cell relationships.
B26: MCI/EA(CSI) PROGRAM: Modern SecOps Envisioning Workshop (Sentinel)
N27: PROJECT WEIGHT BY PHASE | O27: Hours | P27: Percentage (%) | U27: COSTS BY PHASE | V27: =_xlfn.CONCAT("DELIVERY COST (",BillingCountryCurrency,")") -> DELIVERY COST (USD) | W27: =_xlfn.CONCAT("DELIVERY COST (",IF(ISBLANK(BusinessCurrency),"N/A",BusinessCurrency),")") -> DELIVERY COST (N/A) | AC27: PRICE BY PHASE | AD27: =_xlfn.CONCAT("PRICING (",BillingCountryCurrency,")") -> PRICING (USD) | AE27: =_xlfn.CONCAT("PRICING (",IF(ISBLANK(BusinessCurrency),"N/A",BusinessCurrency),")") -> PRICING (N/A) | AF27: + | AG27: =_xlfn.CONCAT("Intercompany (",BillingCountryCurrency,")") -> Intercompany (USD) | AH27: =_xlfn.CONCAT("Intercompany (",IF(ISBLANK(BusinessCurrency),"N/A",BusinessCurrency),")") -> Intercompany (N/A) | AI27: + | AJ27: =_xlfn.CONCAT("WHT (",BillingCountryCurrency,")") -> WHT (USD) | AK27: =_xlfn.CONCAT("WHT (",IF(ISBLANK(BusinessCurrency),"N/A",BusinessCurrency),")") -> WHT (N/A) | AM27: = | AN27: =_xlfn.CONCAT("SUBTOTAL PRICE (",BillingCountryCurrency,")") -> SUBTOTAL PRICE (USD) | AO27: =_xlfn.CONCAT("SUBTOTAL PRICE (",IF(ISBLANK(BusinessCurrency),"N/A",BusinessCurrency),")") -> SUBTOTAL PRICE (N/A) | AS27: SUMMARY BY PHASE
N28: Consultant Team: | O28: =SUMIF($P42:$P71,"<>*Project Management*",$T42:$T71) -> 91.12 | P28: =IFERROR(O28/O31,0) -> 0.76917882 | U28: Consultant Team | V28: =SUMIF(P42:P71,"<>*Project Management*",W42:W71) -> 3336.8144 | W28: =IFERROR(V28/BusinessCurrencyTRM,"N/A") -> N/A | Y28: varTotalConsultant | AC28: Consultant Team | AD28: =SUMIF(P42:P71,"<>*Project Management*",AD42:AD71) -> 5213.8864 | AE28: =IFERROR(AD28/BusinessCurrencyTRM,"N/A") -> N/A | AG28: =SUMIF(P42:P71,"<>*Project Management*",AH42:AH71) -> 0 | AH28: =IFERROR(AG28/BusinessCurrencyTRM,"N/A") -> N/A | AJ28: =SUMIF(P42:P71,"<>*Project Management*",AK42:AK71) -> 0 | AK28: =IFERROR(AJ28/BusinessCurrencyTRM,"N/A") -> N/A | AN28: =SUM(AD28,AG28,AJ28) -> 5213.8864 | AO28: =IFERROR(AN28/BusinessCurrencyTRM,"N/A") -> N/A | AS28: % Margin a Sold * | AV28: 0.36
N29: Project Managment: | O29: =SUMIF($P42:$P71,"=*Project Management*",$T42:T71) -> 18.224 | P29: =IFERROR(O29/O31,0) -> 0.15383576 | U29: Project Managment | V29: =SUMIF(P42:P71,"=*Project Management*",W42:W71) -> 863.8176 | W29: =IFERROR(V29/BusinessCurrencyTRM,"N/A") -> N/A | Y29: varTotalPM | AC29: Project Managment | AD29: =SUMIF(P42:P71,"=*Project Management*",AD42:AD71) -> 1349.8517 | AE29: =IFERROR(AD29/BusinessCurrencyTRM,"N/A") -> N/A | AG29: =SUMIF(P42:P71,"=*Project Management*",AH42:AH71) -> 0 | AH29: =IFERROR(AG29/BusinessCurrencyTRM,"N/A") -> N/A | AJ29: =SUMIF(P42:P71,"=*Project Management*",AK42:AK71) -> 0 | AK29: =IFERROR(AJ29/BusinessCurrencyTRM,"N/A") -> N/A | AN29: =SUM(AD29,AG29,AJ29) -> 1349.8517 | AO29: =IFERROR(AN29/BusinessCurrencyTRM,"N/A") -> N/A | AS29: % Contribution Margin | AV29: =IFERROR(1-AV31/AV32,0) -> 0.36002443
N30: Risk / Extra Effort: | O30: =IF(Approach="Team-Based",SUM(O28:O29)*$O33,$J40-$G40) -> 9.12 | P30: =IFERROR(O30/O31,0) -> 0.076985413 | U30: Subtotal | V30: =SUM(V28:V29) -> 4200.632 | W30: =IFERROR(V30/BusinessCurrencyTRM,"N/A") -> N/A | AC30: Subtotal | AD30: =SUM(AD28:AD29) -> 6563.7381 | AE30: =IFERROR(AD30/BusinessCurrencyTRM,"N/A") -> N/A | AG30: =SUM(AG28:AG29) -> 0 | AH30: =IFERROR(AG30/BusinessCurrencyTRM,"N/A") -> N/A | AJ30: =SUM(AJ28:AJ29) -> 0 | AK30: =IFERROR(AJ30/BusinessCurrencyTRM,"N/A") -> N/A | AN30: =SUM(AD30,AG30,AJ30) -> 6563.7381 | AO30: =IFERROR(AN30/BusinessCurrencyTRM,"N/A") -> N/A | AV30: =BillingCountryCurrency -> USD | AW30: =IF(ISBLANK(BusinessCurrency),"N/A",BusinessCurrency) -> N/A
N31: Total | O31: =SUM(O28:O30) -> 118.464 | P31: =SUM(P28:P30) -> 1 | U31: Risks | V31: =ROUNDUP(V30*O33,2) -> 0 | W31: =IFERROR(V31/BusinessCurrencyTRM,"N/A") -> N/A | Y31: varTotalRisks | AC31: Risks | AD31: =ROUNDUP(V31/(1-$AV$28),2) -> 0 | AE31: =IFERROR(AD31/BusinessCurrencyTRM,"N/A") -> N/A | AG31: =IFERROR(V31*MAX(AG42:AG71),0) -> 0 | AH31: =IFERROR(AG31/BusinessCurrencyTRM,"N/A") -> N/A | AJ31: =IFERROR(SUM(V31,AG31)*MAX(AJ42:AJ71),0) -> 0 | AK31: =IFERROR(AJ31/BusinessCurrencyTRM,"N/A") -> N/A | AN31: =SUM(AD31,AG31,AJ31) -> 0 | AO31: =IFERROR(AN31/BusinessCurrencyTRM,"N/A") -> N/A | AS31: Phase Cost | AV31: =SUM(V37,AG37,AJ37) -> 4200.632 | AW31: =IFERROR(AV31/BusinessCurrencyTRM,"N/A") -> N/A
U32: Pay Rise | V32: =IFERROR(SUMIF(PayRise!A:A,B26,PayRise!J:J),0) -> 0 | W32: =IFERROR(V32/BusinessCurrencyTRM,"N/A") -> N/A | Y32: varTotalPayRise | AC32: Pay Rise | AD32: =IFERROR(SUMIF(PayRise!A:A,B26,PayRise!K:K),0) -> 0 | AE32: =IFERROR(AD32/BusinessCurrencyTRM,"N/A") -> N/A | AG32: =IFERROR(SUMIF(PayRise!A:A,B26,PayRise!L:L),0) -> 0 | AH32: =IFERROR(AG32/BusinessCurrencyTRM,"N/A") -> N/A | AJ32: =IFERROR(SUMIF(PayRise!A:A,B26,PayRise!M:M),0) -> 0 | AK32: =IFERROR(AJ32/BusinessCurrencyTRM,"N/A") -> N/A | AN32: =SUM(AD32,AG32,AJ32) -> 0 | AO32: =IFERROR(AN32/BusinessCurrencyTRM,"N/A") -> N/A | AS32: Phase Price | AV32: =AN37 -> 6563.7381 | AW32: =IFERROR(AV32/BusinessCurrencyTRM,"N/A") -> N/A
N33: =IF(Approach="By Hours", "N/A for ByHours", "% Risks") -> N/A for ByHours | O33: 0 | U33: Products | V33: =IFERROR(SUMIFS(OtherCosts!Q:Q,OtherCosts!A:A,B26,OtherCosts!B:B,"Hardware/Software"),0) -> 0 | W33: =IFERROR(V33/BusinessCurrencyTRM,"N/A") -> N/A | Y33: varTotalProducts | AC33: Products | AD33: =IFERROR(SUMIFS(OtherCosts!R:R,OtherCosts!A:A,B26,OtherCosts!B:B,"Hardware/Software"),0) -> 0 | AE33: =IFERROR(AD33/BusinessCurrencyTRM,"N/A") -> N/A | AG33: =IFERROR(SUMIFS(OtherCosts!S:S,OtherCosts!A:A,B26,OtherCosts!B:B,"Hardware/Software"),0) -> 0 | AH33: =IFERROR(AG33/BusinessCurrencyTRM,"N/A") -> N/A | AJ33: =IFERROR(SUMIFS(OtherCosts!T:T,OtherCosts!A:A,B26,OtherCosts!B:B,"Hardware/Software"),0) -> 0 | AK33: =IFERROR(AJ33/BusinessCurrencyTRM,"N/A") -> N/A | AN33: =SUM(AD33,AG33,AJ33) -> 0 | AO33: =IFERROR(AN33/BusinessCurrencyTRM,"N/A") -> N/A | AS33: Monthly Price | AV33: =IFERROR(IF(O34<1,AN37,AN37/O34),0) -> 6563.7381 | AW33: =IFERROR(AV33/BusinessCurrencyTRM,"N/A") -> N/A
N34: =IF(Approach="By Hours", "N/A for ByHours", "Duration (Months) *") -> N/A for ByHours | O34: 0 | U34: Vendors | V34: =IFERROR(SUMIFS(OtherCosts!Q:Q,OtherCosts!A:A,B26,OtherCosts!B:B,"Vendor"),0) -> 0 | W34: =IFERROR(V34/BusinessCurrencyTRM,"N/A") -> N/A | Y34: varTotalVAR | AC34: Vendors | AD34: =IFERROR(SUMIFS(OtherCosts!R:R,OtherCosts!A:A,B26,OtherCosts!B:B,"Vendor"),0) -> 0 | AE34: =IFERROR(AD34/BusinessCurrencyTRM,"N/A") -> N/A | AG34: =IFERROR(SUMIFS(OtherCosts!S:S,OtherCosts!A:A,B26,OtherCosts!B:B,"Vendor"),0) -> 0 | AH34: =IFERROR(AG34/BusinessCurrencyTRM,"N/A") -> N/A | AJ34: =IFERROR(SUMIFS(OtherCosts!T:T,OtherCosts!A:A,B26,OtherCosts!B:B,"Vendor"),0) -> 0 | AK34: =IFERROR(AJ34/BusinessCurrencyTRM,"N/A") -> N/A | AN34: =SUM(AD34,AG34,AJ34) -> 0 | AO34: =IFERROR(AN34/BusinessCurrencyTRM,"N/A") -> N/A | AS34: Hour Price | AV34: =IFERROR(AN37/T40,0) -> 60.02504 | AW34: =IFERROR(AV34/BusinessCurrencyTRM,"N/A") -> N/A
U35: Insurances | V35: =IFERROR(SUMIFS(OtherCosts!Q:Q,OtherCosts!A:A,B26,OtherCosts!B:B,"Insurance"),0) -> 0 | W35: =IFERROR(V35/BusinessCurrencyTRM,"N/A") -> N/A | Y35: varTotalInsurances | AC35: Insurances | AD35: =IFERROR(SUMIFS(OtherCosts!R:R,OtherCosts!A:A,B26,OtherCosts!B:B,"Insurance"),0) -> 0 | AE35: =IFERROR(AD35/BusinessCurrencyTRM,"N/A") -> N/A | AG35: =IFERROR(SUMIFS(OtherCosts!S:S,OtherCosts!A:A,B26,OtherCosts!B:B,"Insurance"),0) -> 0 | AH35: =IFERROR(AG35/BusinessCurrencyTRM,"N/A") -> N/A | AJ35: =IFERROR(SUMIFS(OtherCosts!T:T,OtherCosts!A:A,B26,OtherCosts!B:B,"Insurance"),0) -> 0 | AK35: =IFERROR(AJ35/BusinessCurrencyTRM,"N/A") -> N/A | AN35: =SUM(AD35,AG35,AJ35) -> 0 | AO35: =IFERROR(AN35/BusinessCurrencyTRM,"N/A") -> N/A
U36: Others | V36: =IFERROR(SUMIFS(OtherCosts!Q:Q,OtherCosts!A:A,B26,OtherCosts!B:B,"Other"),0) -> 0 | W36: =IFERROR(V36/BusinessCurrencyTRM,"N/A") -> N/A | Y36: varTotalOthers | AC36: Others | AD36: =IFERROR(SUMIFS(OtherCosts!R:R,OtherCosts!A:A,B26,OtherCosts!B:B,"Other"),0) -> 0 | AE36: =IFERROR(AD36/BusinessCurrencyTRM,"N/A") -> N/A | AG36: =IFERROR(SUMIFS(OtherCosts!S:S,OtherCosts!A:A,B26,OtherCosts!B:B,"Other"),0) -> 0 | AH36: =IFERROR(AG36/BusinessCurrencyTRM,"N/A") -> N/A | AJ36: =IFERROR(SUMIFS(OtherCosts!T:T,OtherCosts!A:A,B26,OtherCosts!B:B,"Other"),0) -> 0 | AK36: =IFERROR(AJ36/BusinessCurrencyTRM,"N/A") -> N/A | AN36: =SUM(AD36,AG36,AJ36) -> 0 | AO36: =IFERROR(AN36/BusinessCurrencyTRM,"N/A") -> N/A
U37: Subtotal | V37: =SUM(V30:V36) -> 4200.632 | W37: =IFERROR(V37/BusinessCurrencyTRM,"N/A") -> N/A | AC37: Subtotal | AD37: =SUM(AD30:AD36) -> 6563.7381 | AE37: =IFERROR(AD37/BusinessCurrencyTRM,"N/A") -> N/A | AG37: =SUM(AG30:AG36) -> 0 | AH37: =IFERROR(AG37/BusinessCurrencyTRM,"N/A") -> N/A | AJ37: =SUM(AJ30:AJ36) -> 0 | AK37: =IFERROR(AJ37/BusinessCurrencyTRM,"N/A") -> N/A | AN37: =SUM(AD37,AG37,AJ37) -> 6563.7381 | AO37: =IFERROR(AN37/BusinessCurrencyTRM,"N/A") -> N/A
G40: =ROUNDUP(SUM(G42:G71),2) -> 82 | J40: =ROUNDUP(SUM(J42:J71),2) -> 91.12 | T40: =ROUNDUP(SUM(T42:T71),2) -> 109.35 | W40: =SUM(W42:W69) -> 4200.632 | Y40: varTotalFase | AD40: =SUM(AD42:AD71) -> 6563.7381 | AE40: =IFERROR(1-($W40/$AD40),0) -> 0.36002443 | AH40: =SUM(AH42:AH71) -> 0 | AK40: =ROUNDUP(SUM(AK42:AK71),2) -> 0 | AM40: =SUM(AM42:AM71) -> 6563.7381 | AN40: =SUM(AN42:AN71) -> 6563.7381 | AO40: =BillingCountryCurrency -> USD | AT40: =SUM(AT42:AU71) -> 6563.7381 | AV40: =BillingCountryCurrency -> USD | AW40: =IF(ISBLANK(BusinessCurrency),"N/A",BusinessCurrency) -> N/A
G41: Hours | H41: Risk | I41: EE | J41: Total | N41: Delivery Country | O41: Services Line | P41: Job Profile | Q41: Qty | R41: % Allocation | S41: Days | T41: Total Hours | U41: % Surcharge Hours | V41: Unit Cost Base | W41: Subtotal Cost | X41: FilterSL | Y41: FilterJP | AC41: Unit Price Base | AD41: Subtotal Price | AE41: % MaS | AG41: % Intercomp | AH41: $ Intercompany | AJ41: % WHT | AK41: $ WHT | AM41: Subtotal Price | AN41: Subtotal Price + Costs | AO41: Unit Price + Costs | AS41: Fact | AT41: Subtotal Price + Costs | AV41: Unit Price + Cost | AW41: Unit Price + Cost
B42: Observaciones / Incluido: | C42: • Pre-engagement | G42: 82 | H42: 0.1 | I42: 0 | J42: =IFERROR(G42/(1-(H42+I42)),0) -> 91.111111 | N42: xDC Medellin | O42: Cybersecurity | P42: Sr Expert Technology Implementation & Consulting (General) | S42: =IF(ISBLANK(P42),0,$O$34*20) -> 0 | T42: =J40 -> 91.12 | U42: 0 | V42: =ROUNDUP(IFERROR(INDEX(CostRateTbl[Cost Rate],MATCH(_xlfn.CONCAT(N42,O42,P42,"NA"),CostRateTbl[KeyCostRate],0)),0)*BillingCurrencyTRM*(1+U42),2) -> 36.62 | W42: =T42*V42 -> 3336.8144 | X42: {=_xlfn.LET( _xlpm.valor, INDEX(CostRate!H:H, MATCH(1, (CostRate!A:A=N42)*1, 0)), _xlpm.posicion, MATCH(_xlpm.valor, FilterSL!$F$1:$Z$1, 0), _xlpm.direccionCompleta, ADDRESS(1, _xlpm.posicion + 5, 4), _xlpm.letraColumna, SUBSTITUTE(_xlpm.direccionCompleta, "1", ""), _xlpm.letraColumna )} -> R | Y42: {=_xlfn.LET( _xlpm.valor, INDEX(CostRate!I:I, MATCH(1, (CostRate!A:A=N42)*(CostRate!B:B=O42), 0)), _xlpm.posicion, MATCH(_xlpm.valor, FilterJP!$E$1:$FZ$1, 0), _xlpm.direccionCompleta, ADDRESS(1, _xlpm.posicion + 4, 4), _xlpm.letraColumna, SUBSTITUTE(_xlpm.direccionCompleta, "1", ""), _xlpm.letraColumna )} -> BJ | AC42: =ROUNDUP($V42/(1-$AV$28),2) -> 57.22 | AD42: =$T42*$AC42 -> 5213.8864 | AE42: =IFERROR(1-($W42/$AD42),0) -> 0.36001398 | AG42: =IFERROR(IF(OR(ISBLANK(N42),N42=CustomerCountry,COUNTIF($N42,"*xDC*")),0,10%),0) -> 0 | AH42: =W42*AG42 -> 0 | AJ42: {=IFERROR(INDEX(WHT!$C$7:$W$18,MATCH( _xlfn.SWITCH(N42,"xDC Medellin","Colombia","xDC Belo Horizonte","Brazil","xDC Guadalajara","Mexico","xDC Gurugram","India","xDC Leon","Spain","xDC San Jose","Costa Rica","xDC Warsaw","Poland",N42), WHT!$B$7:$B$18,0),MATCH(CustomerCountry,WHT!$C$5:$W$5,0)),0)} -> 0 | AK42: =(W42+AH42)*AJ42 -> 0 | AM42: =SUM($AD42,$AH42,$AK42) -> 5213.8864 | AN42: =AM42+IFERROR(SUM($AN$31:$AN$36)*AM42/$AM$40,0) -> 5213.8864 | AO42: =IFERROR($AN42/$T42,0) -> 57.22 | AS42: X | AT42: =IF(AS42="x",AM42+((SUM($AN$31:$AN$36)+SUMIF($AS$42:$AS$71,"<>x",$AM$42:$AM$71))*IFERROR(AM42/SUMIF($AS$42:$AS$71,"x",$AM$42:$AM$71),0)),0) -> 5213.8864 | AV42: =IFERROR(AT42/T42,0) -> 57.22 | AW42: =IFERROR(AV42/BusinessCurrencyTRM,"N/A") -> N/A
C43: o Pre-engagement Call | H43: 0.1 | I43: 0 | J43: =IFERROR(G43/(1-(H43+I43)),0) -> 0
C44: o Prepare, Send and Review the Modern SecOps Envisioning Workshop Customer Questionnaire | G44: 0 | H44: 0.1 | I44: 0 | J44: =IFERROR(G44/(1-(H44+I44)),0) -> 0
C45: • Readiness (Optional) | G45: 0 | I45: 0 | J45: =IFERROR(G45/(1-(H45+I45)),0) -> 0
C46: • Microsoft Sentinel Overview Presentation | G46: 0 | H46: 0.1 | I46: 0 | J46: =IFERROR(G46/(1-(H46+I46)),0) -> 0
C47: • Engagement Setup | G47: 0 | H47: 0 | I47: 0 | J47: =IFERROR(G47/(1-(H47+I47)),0) -> 0
C48: o Kick-off Meeting | G48: 0 | H48: 0.1 | I48: 0 | J48: =IFERROR(G48/(1-(H48+I48)),0) -> 0
C49: o Define Scope | G49: 0 | H49: 0.1 | I49: 0 | J49: =IFERROR(G49/(1-(H49+I49)),0) -> 0
C50: o Change Management (Optional) | G50: 0 | H50: 0.1 | I50: 0 | J50: =IFERROR(G50/(1-(H50+I50)),0) -> 0
C51: o General Setup | G51: 0 | H51: 0 | I51: 0 | J51: =IFERROR(G51/(1-(H51+I51)),0) -> 0
C52: o Mandatory Modules Configuration | G52: 0 | H52: 0 | I52: 0 | J52: =IFERROR(G52/(1-(H52+I52)),0) -> 0
C53: o Selectable Modules Configuration | G53: 0 | H53: 0.1 | I53: 0 | J53: =IFERROR(G53/(1-(H53+I53)),0) -> 0
C54: • Data Collection | G54: 0 | H54: 0.1 | I54: 0 | J54: =IFERROR(G54/(1-(H54+I54)),0) -> 0
C55: o Data Collection | G55: 0 | H55: 0.1 | I55: 0 | J55: =IFERROR(G55/(1-(H55+I55)),0) -> 0
C56: o Remote Monitoring (optional) | G56: 0 | H56: 0 | I56: 0 | J56: =IFERROR(G56/(1-(H56+I56)),0) -> 0
C57: • Exploration | G57: 0 | H57: 0 | I57: 0 | J57: =IFERROR(G57/(1-(H57+I57)),0) -> 0
... C62: • Engagement Decommissioning | G62: 0 | H62: 0 | I62: 0 | J62: =IFERROR(G62/(1-(H62+I62)),0) -> 0
H63: 0 | I63: 0 | J63: =IFERROR(G63/(1-(H63+I63)),0) -> 0
H64: 0 | I64: 0 | J64: =IFERROR(G64/(1-(H64+I64)),0) -> 0 | N64: xDC Medellin | O64: Project Management | P64: Sr Expert Technology & Consulting Project Management | S64: =IF(ISBLANK(P64),0,$O$34*20) -> 0 | T64: =J40*20% -> 18.224 | U64: 0 | V64: =ROUNDUP(IFERROR(INDEX(CostRateTbl[Cost Rate],MATCH(_xlfn.CONCAT(N64,O64,P64,"NA"),CostRateTbl[KeyCostRate],0)),0)*BillingCurrencyTRM*(1+U64),2) -> 47.4 | W64: =T64*V64 -> 863.8176 | X64: {=_xlfn.LET( _xlpm.valor, INDEX(CostRate!H:H, MATCH(1, (CostRate!A:A=N64)*1, 0)), _xlpm.posicion, MATCH(_xlpm.valor, FilterSL!$F$1:$Z$1, 0), _xlpm.direccionCompleta, ADDRESS(1, _xlpm.posicion + 5, 4), _xlpm.letraColumna, SUBSTITUTE(_xlpm.direccionCompleta, "1", ""), _xlpm.letraColumna )} -> R | Y64: {=_xlfn.LET( _xlpm.valor, INDEX(CostRate!I:I, MATCH(1, (CostRate!A:A=N64)*(CostRate!B:B=O64), 0)), _xlpm.posicion, MATCH(_xlpm.valor, FilterJP!$E$1:$FZ$1, 0), _xlpm.direccionCompleta, ADDRESS(1, _xlpm.posicion + 4, 4), _xlpm.letraColumna, SUBSTITUTE(_xlpm.direccionCompleta, "1", ""), _xlpm.letraColumna )} -> BP | AC64: =ROUNDUP($V64/(1-$AV$28),2) -> 74.07 | AD64: =$T64*$AC64 -> 1349.8517 | AE64: =IFERROR(1-($W64/$AD64),0) -> 0.3600648 | AG64: =IFERROR(IF(OR(ISBLANK(N64),N64=CustomerCountry,COUNTIF($N64,"*xDC*")),0,10%),0) -> 0 | AH64: =W64*AG64 -> 0 | AJ64: {=IFERROR(INDEX(WHT!$C$7:$W$18,MATCH( _xlfn.SWITCH(N64,"xDC Medellin","Colombia","xDC Belo Horizonte","Brazil","xDC Guadalajara","Mexico","xDC Gurugram","India","xDC Leon","Spain","xDC San Jose","Costa Rica","xDC Warsaw","Poland",N64), WHT!$B$7:$B$18,0),MATCH(CustomerCountry,WHT!$C$5:$W$5,0)),0)} -> 0 | AK64: =(W64+AH64)*AJ64 -> 0 | AM64: =SUM($AD64,$AH64,$AK64) -> 1349.8517 | AN64: =AM64+IFERROR(SUM($AN$31:$AN$36)*AM64/$AM$40,0) -> 1349.8517 | AO64: =IFERROR($AN64/$T64,0) -> 74.07 | AS64: X | AT64: =IF(AS64="x",AM64+((SUM($AN$31:$AN$36)+SUMIF($AS$42:$AS$71,"<>x",$AM$42:$AM$71))*IFERROR(AM64/SUMIF($AS$42:$AS$71,"x",$AM$42:$AM$71),0)),0) -> 1349.8517 | AV64: =IFERROR(AT64/T64,0) -> 74.07 | AW64: =IFERROR(AV64/BusinessCurrencyTRM,"N/A") -> N/A
H65: 0 | I65: 0 | J65: =IFERROR(G65/(1-(H65+I65)),0) -> 0 | S65: =IF(ISBLANK(P65),0,$O$34*20) -> 0 | T65: =IF(ISBLANK($P65),0,IF(Approach="Team-Based",$Q65*$R65*$S65*HoursPerDayTeamBased,$J65)) -> 0 | U65: 0 | V65: =ROUNDUP(IFERROR(INDEX(CostRateTbl[Cost Rate],MATCH(_xlfn.CONCAT(N65,O65,P65,"NA"),CostRateTbl[KeyCostRate],0)),0)*BillingCurrencyTRM*(1+U65),2) -> 0 | W65: =T65*V65 -> 0 | X65: {=_xlfn.LET( _xlpm.valor, INDEX(CostRate!H:H, MATCH(1, (CostRate!A:A=N65)*1, 0)), _xlpm.posicion, MATCH(_xlpm.valor, FilterSL!$F$1:$Z$1, 0), _xlpm.direccionCompleta, ADDRESS(1, _xlpm.posicion + 5, 4), _xlpm.letraColumna, SUBSTITUTE(_xlpm.direccionCompleta, "1", ""), _xlpm.letraColumna )} -> #N/A | Y65: {=_xlfn.LET( _xlpm.valor, INDEX(CostRate!I:I, MATCH(1, (CostRate!A:A=N65)*(CostRate!B:B=O65), 0)), _xlpm.posicion, MATCH(_xlpm.valor, FilterJP!$E$1:$FZ$1, 0), _xlpm.direccionCompleta, ADDRESS(1, _xlpm.posicion + 4, 4), _xlpm.letraColumna, SUBSTITUTE(_xlpm.direccionCompleta, "1", ""), _xlpm.letraColumna )} -> #N/A | AC65: =ROUNDUP($V65/(1-$AV$28),2) -> 0 | AD65: =$T65*$AC65 -> 0 | AE65: =IFERROR(1-($W65/$AD65),0) -> 0 | AG65: =IFERROR(IF(OR(ISBLANK(N65),N65=CustomerCountry,COUNTIF($N65,"*xDC*")),0,10%),0) -> 0 | AH65: =W65*AG65 -> 0 | AJ65: {=IFERROR(INDEX(WHT!$C$7:$W$18,MATCH( _xlfn.SWITCH(N65,"xDC Medellin","Colombia","xDC Belo Horizonte","Brazil","xDC Guadalajara","Mexico","xDC Gurugram","India","xDC Leon","Spain","xDC San Jose","Costa Rica","xDC Warsaw","Poland",N65), WHT!$B$7:$B$18,0),MATCH(CustomerCountry,WHT!$C$5:$W$5,0)),0)} -> 0 | AK65: =(W65+AH65)*AJ65 -> 0 | AM65: =SUM($AD65,$AH65,$AK65) -> 0 | AN65: =AM65+IFERROR(SUM($AN$31:$AN$36)*AM65/$AM$40,0) -> 0 | AO65: =IFERROR($AN65/$T65,0) -> 0 | AS65: X | AT65: =IF(AS65="x",AM65+((SUM($AN$31:$AN$36)+SUMIF($AS$42:$AS$71,"<>x",$AM$42:$AM$71))*IFERROR(AM65/SUMIF($AS$42:$AS$71,"x",$AM$42:$AM$71),0)),0) -> 0 | AV65: =IFERROR(AT65/T65,0) -> 0 | AW65: =IFERROR(AV65/BusinessCurrencyTRM,"N/A") -> N/A
H66: 0 | I66: 0 | J66: =IFERROR(G66/(1-(H66+I66)),0) -> 0 | S66: =IF(ISBLANK(P66),0,$O$34*20) -> 0 | T66: =IF(ISBLANK($P66),0,IF(Approach="Team-Based",$Q66*$R66*$S66*HoursPerDayTeamBased,$J66)) -> 0 | U66: 0 | V66: =ROUNDUP(IFERROR(INDEX(CostRateTbl[Cost Rate],MATCH(_xlfn.CONCAT(N66,O66,P66,"NA"),CostRateTbl[KeyCostRate],0)),0)*BillingCurrencyTRM*(1+U66),2) -> 0 | W66: =T66*V66 -> 0 | X66: {=_xlfn.LET( _xlpm.valor, INDEX(CostRate!H:H, MATCH(1, (CostRate!A:A=N66)*1, 0)), _xlpm.posicion, MATCH(_xlpm.valor, FilterSL!$F$1:$Z$1, 0), _xlpm.direccionCompleta, ADDRESS(1, _xlpm.posicion + 5, 4), _xlpm.letraColumna, SUBSTITUTE(_xlpm.direccionCompleta, "1", ""), _xlpm.letraColumna )} -> #N/A | Y66: {=_xlfn.LET( _xlpm.valor, INDEX(CostRate!I:I, MATCH(1, (CostRate!A:A=N66)*(CostRate!B:B=O66), 0)), _xlpm.posicion, MATCH(_xlpm.valor, FilterJP!$E$1:$FZ$1, 0), _xlpm.direccionCompleta, ADDRESS(1, _xlpm.posicion + 4, 4), _xlpm.letraColumna, SUBSTITUTE(_xlpm.direccionCompleta, "1", ""), _xlpm.letraColumna )} -> #N/A | AC66: =ROUNDUP($V66/(1-$AV$28),2) -> 0 | AD66: =$T66*$AC66 -> 0 | AE66: =IFERROR(1-($W66/$AD66),0) -> 0 | AG66: =IFERROR(IF(OR(ISBLANK(N66),N66=CustomerCountry,COUNTIF($N66,"*xDC*")),0,10%),0) -> 0 | AH66: =W66*AG66 -> 0 | AJ66: {=IFERROR(INDEX(WHT!$C$7:$W$18,MATCH( _xlfn.SWITCH(N66,"xDC Medellin","Colombia","xDC Belo Horizonte","Brazil","xDC Guadalajara","Mexico","xDC Gurugram","India","xDC Leon","Spain","xDC San Jose","Costa Rica","xDC Warsaw","Poland",N66), WHT!$B$7:$B$18,0),MATCH(CustomerCountry,WHT!$C$5:$W$5,0)),0)} -> 0 | AK66: =(W66+AH66)*AJ66 -> 0 | AM66: =SUM($AD66,$AH66,$AK66) -> 0 | AN66: =AM66+IFERROR(SUM($AN$31:$AN$36)*AM66/$AM$40,0) -> 0 | AO66: =IFERROR($AN66/$T66,0) -> 0 | AS66: X | AT66: =IF(AS66="x",AM66+((SUM($AN$31:$AN$36)+SUMIF($AS$42:$AS$71,"<>x",$AM$42:$AM$71))*IFERROR(AM66/SUMIF($AS$42:$AS$71,"x",$AM$42:$AM$71),0)),0) -> 0 | AV66: =IFERROR(AT66/T66,0) -> 0 | AW66: =IFERROR(AV66/BusinessCurrencyTRM,"N/A") -> N/A
H67: 0 | I67: 0 | J67: =IFERROR(G67/(1-(H67+I67)),0) -> 0 | S67: =IF(ISBLANK(P67),0,$O$34*20) -> 0 | T67: =IF(ISBLANK($P67),0,IF(Approach="Team-Based",$Q67*$R67*$S67*HoursPerDayTeamBased,$J67)) -> 0 | U67: 0 | V67: =ROUNDUP(IFERROR(INDEX(CostRateTbl[Cost Rate],MATCH(_xlfn.CONCAT(N67,O67,P67,"NA"),CostRateTbl[KeyCostRate],0)),0)*BillingCurrencyTRM*(1+U67),2) -> 0 | W67: =T67*V67 -> 0 | X67: {=_xlfn.LET( _xlpm.valor, INDEX(CostRate!H:H, MATCH(1, (CostRate!A:A=N67)*1, 0)), _xlpm.posicion, MATCH(_xlpm.valor, FilterSL!$F$1:$Z$1, 0), _xlpm.direccionCompleta, ADDRESS(1, _xlpm.posicion + 5, 4), _xlpm.letraColumna, SUBSTITUTE(_xlpm.direccionCompleta, "1", ""), _xlpm.letraColumna )} -> #N/A | Y67: {=_xlfn.LET( _xlpm.valor, INDEX(CostRate!I:I, MATCH(1, (CostRate!A:A=N67)*(CostRate!B:B=O67), 0)), _xlpm.posicion, MATCH(_xlpm.valor, FilterJP!$E$1:$FZ$1, 0), _xlpm.direccionCompleta, ADDRESS(1, _xlpm.posicion + 4, 4), _xlpm.letraColumna, SUBSTITUTE(_xlpm.direccionCompleta, "1", ""), _xlpm.letraColumna )} -> #N/A | AC67: =ROUNDUP($V67/(1-$AV$28),2) -> 0 | AD67: =$T67*$AC67 -> 0 | AE67: =IFERROR(1-($W67/$AD67),0) -> 0 | AG67: =IFERROR(IF(OR(ISBLANK(N67),N67=CustomerCountry,COUNTIF($N67,"*xDC*")),0,10%),0) -> 0 | AH67: =W67*AG67 -> 0 | AJ67: {=IFERROR(INDEX(WHT!$C$7:$W$18,MATCH( _xlfn.SWITCH(N67,"xDC Medellin","Colombia","xDC Belo Horizonte","Brazil","xDC Guadalajara","Mexico","xDC Gurugram","India","xDC Leon","Spain","xDC San Jose","Costa Rica","xDC Warsaw","Poland",N67), WHT!$B$7:$B$18,0),MATCH(CustomerCountry,WHT!$C$5:$W$5,0)),0)} -> 0 | AK67: =(W67+AH67)*AJ67 -> 0 | AM67: =SUM($AD67,$AH67,$AK67) -> 0 | AN67: =AM67+IFERROR(SUM($AN$31:$AN$36)*AM67/$AM$40,0) -> 0 | AO67: =IFERROR($AN67/$T67,0) -> 0 | AS67: X | AT67: =IF(AS67="x",AM67+((SUM($AN$31:$AN$36)+SUMIF($AS$42:$AS$71,"<>x",$AM$42:$AM$71))*IFERROR(AM67/SUMIF($AS$42:$AS$71,"x",$AM$42:$AM$71),0)),0) -> 0 | AV67: =IFERROR(AT67/T67,0) -> 0 | AW67: =IFERROR(AV67/BusinessCurrencyTRM,"N/A") -> N/A
H68: 0 | I68: 0 | J68: =IFERROR(G68/(1-(H68+I68)),0) -> 0 | S68: =IF(ISBLANK(P68),0,$O$34*20) -> 0 | T68: =IF(ISBLANK($P68),0,IF(Approach="Team-Based",$Q68*$R68*$S68*HoursPerDayTeamBased,$J68)) -> 0 | U68: 0 | V68: =ROUNDUP(IFERROR(INDEX(CostRateTbl[Cost Rate],MATCH(_xlfn.CONCAT(N68,O68,P68,"NA"),CostRateTbl[KeyCostRate],0)),0)*BillingCurrencyTRM*(1+U68),2) -> 0 | W68: =T68*V68 -> 0 | X68: {=_xlfn.LET( _xlpm.valor, INDEX(CostRate!H:H, MATCH(1, (CostRate!A:A=N68)*1, 0)), _xlpm.posicion, MATCH(_xlpm.valor, FilterSL!$F$1:$Z$1, 0), _xlpm.direccionCompleta, ADDRESS(1, _xlpm.posicion + 5, 4), _xlpm.letraColumna, SUBSTITUTE(_xlpm.direccionCompleta, "1", ""), _xlpm.letraColumna )} -> #N/A | Y68: {=_xlfn.LET( _xlpm.valor, INDEX(CostRate!I:I, MATCH(1, (CostRate!A:A=N68)*(CostRate!B:B=O68), 0)), _xlpm.posicion, MATCH(_xlpm.valor, FilterJP!$E$1:$FZ$1, 0), _xlpm.direccionCompleta, ADDRESS(1, _xlpm.posicion + 4, 4), _xlpm.letraColumna, SUBSTITUTE(_xlpm.direccionCompleta, "1", ""), _xlpm.letraColumna )} -> #N/A | AC68: =ROUNDUP($V68/(1-$AV$28),2) -> 0 | AD68: =$T68*$AC68 -> 0 | AE68: =IFERROR(1-($W68/$AD68),0) -> 0 | AG68: =IFERROR(IF(OR(ISBLANK(N68),N68=CustomerCountry,COUNTIF($N68,"*xDC*")),0,10%),0) -> 0 | AH68: =W68*AG68 -> 0 | AJ68: {=IFERROR(INDEX(WHT!$C$7:$W$18,MATCH( _xlfn.SWITCH(N68,"xDC Medellin","Colombia","xDC Belo Horizonte","Brazil","xDC Guadalajara","Mexico","xDC Gurugram","India","xDC Leon","Spain","xDC San Jose","Costa Rica","xDC Warsaw","Poland",N68), WHT!$B$7:$B$18,0),MATCH(CustomerCountry,WHT!$C$5:$W$5,0)),0)} -> 0 | AK68: =(W68+AH68)*AJ68 -> 0 | AM68: =SUM($AD68,$AH68,$AK68) -> 0 | AN68: =AM68+IFERROR(SUM($AN$31:$AN$36)*AM68/$AM$40,0) -> 0 | AO68: =IFERROR($AN68/$T68,0) -> 0 | AS68: X | AT68: =IF(AS68="x",AM68+((SUM($AN$31:$AN$36)+SUMIF($AS$42:$AS$71,"<>x",$AM$42:$AM$71))*IFERROR(AM68/SUMIF($AS$42:$AS$71,"x",$AM$42:$AM$71),0)),0) -> 0 | AV68: =IFERROR(AT68/T68,0) -> 0 | AW68: =IFERROR(AV68/BusinessCurrencyTRM,"N/A") -> N/A
H69: 0 | I69: 0 | J69: =IFERROR(G69/(1-(H69+I69)),0) -> 0 | S69: =IF(ISBLANK(P69),0,$O$34*20) -> 0 | T69: =IF(ISBLANK($P69),0,IF(Approach="Team-Based",$Q69*$R69*$S69*HoursPerDayTeamBased,$J69)) -> 0 | U69: 0 | V69: =ROUNDUP(IFERROR(INDEX(CostRateTbl[Cost Rate],MATCH(_xlfn.CONCAT(N69,O69,P69,"NA"),CostRateTbl[KeyCostRate],0)),0)*BillingCurrencyTRM*(1+U69),2) -> 0 | W69: =T69*V69 -> 0 | X69: {=_xlfn.LET( _xlpm.valor, INDEX(CostRate!H:H, MATCH(1, (CostRate!A:A=N69)*1, 0)), _xlpm.posicion, MATCH(_xlpm.valor, FilterSL!$F$1:$Z$1, 0), _xlpm.direccionCompleta, ADDRESS(1, _xlpm.posicion + 5, 4), _xlpm.letraColumna, SUBSTITUTE(_xlpm.direccionCompleta, "1", ""), _xlpm.letraColumna )} -> #N/A | Y69: {=_xlfn.LET( _xlpm.valor, INDEX(CostRate!I:I, MATCH(1, (CostRate!A:A=N69)*(CostRate!B:B=O69), 0)), _xlpm.posicion, MATCH(_xlpm.valor, FilterJP!$E$1:$FZ$1, 0), _xlpm.direccionCompleta, ADDRESS(1, _xlpm.posicion + 4, 4), _xlpm.letraColumna, SUBSTITUTE(_xlpm.direccionCompleta, "1", ""), _xlpm.letraColumna )} -> #N/A | AC69: =ROUNDUP($V69/(1-$AV$28),2) -> 0 | AD69: =$T69*$AC69 -> 0 | AE69: =IFERROR(1-($W69/$AD69),0) -> 0 | AG69: =IFERROR(IF(OR(ISBLANK(N69),N69=CustomerCountry,COUNTIF($N69,"*xDC*")),0,10%),0) -> 0 | AH69: =W69*AG69 -> 0 | AJ69: {=IFERROR(INDEX(WHT!$C$7:$W$18,MATCH( _xlfn.SWITCH(N69,"xDC Medellin","Colombia","xDC Belo Horizonte","Brazil","xDC Guadalajara","Mexico","xDC Gurugram","India","xDC Leon","Spain","xDC San Jose","Costa Rica","xDC Warsaw","Poland",N69), WHT!$B$7:$B$18,0),MATCH(CustomerCountry,WHT!$C$5:$W$5,0)),0)} -> 0 | AK69: =(W69+AH69)*AJ69 -> 0 | AM69: =SUM($AD69,$AH69,$AK69) -> 0 | AN69: =AM69+IFERROR(SUM($AN$31:$AN$36)*AM69/$AM$40,0) -> 0 | AO69: =IFERROR($AN69/$T69,0) -> 0 | AS69: X | AT69: =IF(AS69="x",AM69+((SUM($AN$31:$AN$36)+SUMIF($AS$42:$AS$71,"<>x",$AM$42:$AM$71))*IFERROR(AM69/SUMIF($AS$42:$AS$71,"x",$AM$42:$AM$71),0)),0) -> 0 | AV69: =IFERROR(AT69/T69,0) -> 0 | AW69: =IFERROR(AV69/BusinessCurrencyTRM,"N/A") -> N/A
G70: 0 | H70: 0 | I70: 0 | J70: =IFERROR(G70/(1-(H70+I70)),0) -> 0 | S70: =IF(ISBLANK(P70),0,$O$34*20) -> 0 | T70: =IF(ISBLANK($P70),0,IF(Approach="Team-Based",$Q70*$R70*$S70*HoursPerDayTeamBased,$J70)) -> 0 | U70: 0 | V70: =ROUNDUP(IFERROR(INDEX(CostRateTbl[Cost Rate],MATCH(_xlfn.CONCAT(N70,O70,P70,"NA"),CostRateTbl[KeyCostRate],0)),0)*BillingCurrencyTRM*(1+U70),2) -> 0 | W70: =T70*V70 -> 0 | X70: {=_xlfn.LET( _xlpm.valor, INDEX(CostRate!H:H, MATCH(1, (CostRate!A:A=N70)*1, 0)), _xlpm.posicion, MATCH(_xlpm.valor, FilterSL!$F$1:$Z$1, 0), _xlpm.direccionCompleta, ADDRESS(1, _xlpm.posicion + 5, 4), _xlpm.letraColumna, SUBSTITUTE(_xlpm.direccionCompleta, "1", ""), _xlpm.letraColumna )} -> #N/A | Y70: {=_xlfn.LET( _xlpm.valor, INDEX(CostRate!I:I, MATCH(1, (CostRate!A:A=N70)*(CostRate!B:B=O70), 0)), _xlpm.posicion, MATCH(_xlpm.valor, FilterJP!$E$1:$FZ$1, 0), _xlpm.direccionCompleta, ADDRESS(1, _xlpm.posicion + 4, 4), _xlpm.letraColumna, SUBSTITUTE(_xlpm.direccionCompleta, "1", ""), _xlpm.letraColumna )} -> #N/A | AC70: =ROUNDUP($V70/(1-$AV$28),2) -> 0 | AD70: =$T70*$AC70 -> 0 | AE70: =IFERROR(1-($W70/$AD70),0) -> 0 | AG70: =IFERROR(IF(OR(ISBLANK(N70),N70=CustomerCountry,COUNTIF($N70,"*xDC*")),0,10%),0) -> 0 | AH70: =W70*AG70 -> 0 | AJ70: {=IFERROR(INDEX(WHT!$C$7:$W$18,MATCH( _xlfn.SWITCH(N70,"xDC Medellin","Colombia","xDC Belo Horizonte","Brazil","xDC Guadalajara","Mexico","xDC Gurugram","India","xDC Leon","Spain","xDC San Jose","Costa Rica","xDC Warsaw","Poland",N70), WHT!$B$7:$B$18,0),MATCH(CustomerCountry,WHT!$C$5:$W$5,0)),0)} -> 0 | AK70: =(W70+AH70)*AJ70 -> 0 | AM70: =SUM($AD70,$AH70,$AK70) -> 0 | AN70: =AM70+IFERROR(SUM($AN$31:$AN$36)*AM70/$AM$40,0) -> 0 | AO70: =IFERROR($AN70/$T70,0) -> 0 | AS70: X | AT70: =IF(AS70="x",AM70+((SUM($AN$31:$AN$36)+SUMIF($AS$42:$AS$71,"<>x",$AM$42:$AM$71))*IFERROR(AM70/SUMIF($AS$42:$AS$71,"x",$AM$42:$AM$71),0)),0) -> 0 | AV70: =IFERROR(AT70/T70,0) -> 0 | AW70: =IFERROR(AV70/BusinessCurrencyTRM,"N/A") -> N/A
G71: 0 | H71: 0 | I71: 0 | J71: =IFERROR(G71/(1-(H71+I71)),0) -> 0 | S71: =IF(ISBLANK(P71),0,$O$34*20) -> 0 | T71: =IF(ISBLANK($P71),0,IF(Approach="Team-Based",$Q71*$R71*$S71*HoursPerDayTeamBased,$J71)) -> 0 | U71: 0 | V71: =ROUNDUP(IFERROR(INDEX(CostRateTbl[Cost Rate],MATCH(_xlfn.CONCAT(N71,O71,P71,"NA"),CostRateTbl[KeyCostRate],0)),0)*BillingCurrencyTRM*(1+U71),2) -> 0 | W71: =T71*V71 -> 0 | X71: {=_xlfn.LET( _xlpm.valor, INDEX(CostRate!H:H, MATCH(1, (CostRate!A:A=N71)*1, 0)), _xlpm.posicion, MATCH(_xlpm.valor, FilterSL!$F$1:$Z$1, 0), _xlpm.direccionCompleta, ADDRESS(1, _xlpm.posicion + 5, 4), _xlpm.letraColumna, SUBSTITUTE(_xlpm.direccionCompleta, "1", ""), _xlpm.letraColumna )} -> #N/A | Y71: {=_xlfn.LET( _xlpm.valor, INDEX(CostRate!I:I, MATCH(1, (CostRate!A:A=N71)*(CostRate!B:B=O71), 0)), _xlpm.posicion, MATCH(_xlpm.valor, FilterJP!$E$1:$FZ$1, 0), _xlpm.direccionCompleta, ADDRESS(1, _xlpm.posicion + 4, 4), _xlpm.letraColumna, SUBSTITUTE(_xlpm.direccionCompleta, "1", ""), _xlpm.letraColumna )} -> #N/A | AC71: =ROUNDUP($V71/(1-$AV$28),2) -> 0 | AD71: =$T71*$AC71 -> 0 | AE71: =IFERROR(1-($W71/$AD71),0) -> 0 | AG71: =IFERROR(IF(OR(ISBLANK(N71),N71=CustomerCountry,COUNTIF($N71,"*xDC*")),0,10%),0) -> 0 | AH71: =W71*AG71 -> 0 | AJ71: {=IFERROR(INDEX(WHT!$C$7:$W$18,MATCH( _xlfn.SWITCH(N71,"xDC Medellin","Colombia","xDC Belo Horizonte","Brazil","xDC Guadalajara","Mexico","xDC Gurugram","India","xDC Leon","Spain","xDC San Jose","Costa Rica","xDC Warsaw","Poland",N71), WHT!$B$7:$B$18,0),MATCH(CustomerCountry,WHT!$C$5:$W$5,0)),0)} -> 0 | AK71: =(W71+AH71)*AJ71 -> 0 | AM71: =SUM($AD71,$AH71,$AK71) -> 0 | AN71: =AM71+IFERROR(SUM($AN$31:$AN$36)*AM71/$AM$40,0) -> 0 | AO71: =IFERROR($AN71/$T71,0) -> 0 | AS71: X | AT71: =IF(AS71="x",AM71+((SUM($AN$31:$AN$36)+SUMIF($AS$42:$AS$71,"<>x",$AM$42:$AM$71))*IFERROR(AM71/SUMIF($AS$42:$AS$71,"x",$AM$42:$AM$71),0)),0) -> 0 | AV71: =IFERROR(AT71/T71,0) -> 0 | AW71: =IFERROR(AV71/BusinessCurrencyTRM,"N/A") -> N/A
B74: Fase 2
N75: PROJECT WEIGHT BY PHASE | O75: Hours | P75: Percentage (%) | U75: COSTS BY PHASE | V75: =_xlfn.CONCAT("DELIVERY COST (",BillingCountryCurrency,")") -> DELIVERY COST (USD) | W75: =_xlfn.CONCAT("DELIVERY COST (",IF(ISBLANK(BusinessCurrency),"N/A",BusinessCurrency),")") -> DELIVERY COST (N/A) | AC75: PRICE BY PHASE | AD75: =_xlfn.CONCAT("PRICING (",BillingCountryCurrency,")") -> PRICING (USD) | AE75: =_xlfn.CONCAT("PRICING (",IF(ISBLANK(BusinessCurrency),"N/A",BusinessCurrency),")") -> PRICING (N/A) | AF75: + | AG75: =_xlfn.CONCAT("Intercompany (",BillingCountryCurrency,")") -> Intercompany (USD) | AH75: =_xlfn.CONCAT("Intercompany (",IF(ISBLANK(BusinessCurrency),"N/A",BusinessCurrency),")") -> Intercompany (N/A) | AI75: + | AJ75: =_xlfn.CONCAT("WHT (",BillingCountryCurrency,")") -> WHT (USD) | AK75: =_xlfn.CONCAT("WHT (",IF(ISBLANK(BusinessCurrency),"N/A",BusinessCurrency),")") -> WHT (N/A) | AM75: = | AN75: =_xlfn.CONCAT("SUBTOTAL PRICE (",BillingCountryCurrency,")") -> SUBTOTAL PRICE (USD) | AO75: =_xlfn.CONCAT("SUBTOTAL PRICE (",IF(ISBLANK(BusinessCurrency),"N/A",BusinessCurrency),")") -> SUBTOTAL PRICE (N/A) | AS75: SUMMARY BY PHASE
N76: Consultant Team: | O76: =SUMIF($P90:$P121,"<>*Project Management*",$T90:$T121) -> 0 | P76: =IFERROR(O76/O79,0) -> 0 | U76: Consultant Team | V76: =SUMIF(P90:P121,"<>*Project Management*",W90:W121) -> 0 | W76: =IFERROR(V76/BusinessCurrencyTRM,"N/A") -> N/A | Y76: varTotalConsultant | AC76: Consultant Team | AD76: =SUMIF(P90:P121,"<>*Project Management*",AD90:AD121) -> 0 | AE76: =IFERROR(AD76/BusinessCurrencyTRM,"N/A") -> N/A | AG76: =SUMIF(P90:P121,"<>*Project Management*",AH90:AH121) -> 0 | AH76: =IFERROR(AG76/BusinessCurrencyTRM,"N/A") -> N/A | AJ76: =SUMIF(P90:P121,"<>*Project Management*",AK90:AK121) -> 0 | AK76: =IFERROR(AJ76/BusinessCurrencyTRM,"N/A") -> N/A | AN76: =SUM(AD76,AG76,AJ76) -> 0 | AO76: =IFERROR(AN76/BusinessCurrencyTRM,"N/A") -> N/A | AS76: % Margin a Sold * | AV76: 0.35
N77: Project Managment: | O77: =SUMIF($P90:$P121,"=*Project Management*",$T90:T121) -> 0 | P77: =IFERROR(O77/O79,0) -> 0 | U77: Project Managment | V77: =SUMIF(P90:P121,"=*Project Management*",W90:W121) -> 0 | W77: =IFERROR(V77/BusinessCurrencyTRM,"N/A") -> N/A | Y77: varTotalPM | AC77: Project Managment | AD77: =SUMIF(P90:P121,"=*Project Management*",AD90:AD121) -> 0 | AE77: =IFERROR(AD77/BusinessCurrencyTRM,"N/A") -> N/A | AG77: =SUMIF(P90:P121,"=*Project Management*",AH90:AH121) -> 0 | AH77: =IFERROR(AG77/BusinessCurrencyTRM,"N/A") -> N/A | AJ77: =SUMIF(P90:P121,"=*Project Management*",AK90:AK121) -> 0 | AK77: =IFERROR(AJ77/BusinessCurrencyTRM,"N/A") -> N/A | AN77: =SUM(AD77,AG77,AJ77) -> 0 | AO77: =IFERROR(AN77/BusinessCurrencyTRM,"N/A") -> N/A | AS77: % Contribution Margin | AV77: =IFERROR(1-AV79/AV80,0) -> 0
N78: Risk / Extra Effort: | O78: =IF(Approach="Team-Based",SUM(O76:O77)*$O81,$J88-$G88) -> 0 | P78: =IFERROR(O78/O79,0) -> 0 | U78: Subtotal | V78: =SUM(V76:V77) -> 0 | W78: =IFERROR(V78/BusinessCurrencyTRM,"N/A") -> N/A | AC78: Subtotal | AD78: =SUM(AD76:AD77) -> 0 | AE78: =IFERROR(AD78/BusinessCurrencyTRM,"N/A") -> N/A | AG78: =SUM(AG76:AG77) -> 0 | AH78: =IFERROR(AG78/BusinessCurrencyTRM,"N/A") -> N/A | AJ78: =SUM(AJ76:AJ77) -> 0 | AK78: =IFERROR(AJ78/BusinessCurrencyTRM,"N/A") -> N/A | AN78: =SUM(AD78,AG78,AJ78) -> 0 | AO78: =IFERROR(AN78/BusinessCurrencyTRM,"N/A") -> N/A | AV78: =BillingCountryCurrency -> USD | AW78: =IF(ISBLANK(BusinessCurrency),"N/A",BusinessCurrency) -> N/A
N79: Total | O79: =SUM(O76:O78) -> 0 | P79: =SUM(P76:P78) -> 0 | U79: Risks | V79: =ROUNDUP(V78*O81,2) -> 0 | W79: =IFERROR(V79/BusinessCurrencyTRM,"N/A") -> N/A | Y79: varTotalRisks | AC79: Risks | AD79: =ROUNDUP(V79/(1-$AV$76),2) -> 0 | AE79: =IFERROR(AD79/BusinessCurrencyTRM,"N/A") -> N/A | AG79: =IFERROR(V79*MAX(AG90:AG121),0) -> 0 | AH79: =IFERROR(AG79/BusinessCurrencyTRM,"N/A") -> N/A | AJ79: =IFERROR(SUM(V79,AG79)*MAX(AJ90:AJ121),0) -> 0 | AK79: =IFERROR(AJ79/BusinessCurrencyTRM,"N/A") -> N/A | AN79: =SUM(AD79,AG79,AJ79) -> 0 | AO79: =IFERROR(AN79/BusinessCurrencyTRM,"N/A") -> N/A | AS79: Phase Cost | AV79: =SUM(V85,AG85,AJ85) -> 0 | AW79: =IFERROR(AV79/BusinessCurrencyTRM,"N/A") -> N/A
U80: Pay Rise | V80: =IFERROR(SUMIF(PayRise!A:A,B74,PayRise!J:J),0) -> 0 | W80: =IFERROR(V80/BusinessCurrencyTRM,"N/A") -> N/A | Y80: varTotalPayRise | AC80: Pay Rise | AD80: =IFERROR(SUMIF(PayRise!A:A,B74,PayRise!K:K),0) -> 0 | AE80: =IFERROR(AD80/BusinessCurrencyTRM,"N/A") -> N/A | AG80: =IFERROR(SUMIF(PayRise!A:A,B74,PayRise!L:L),0) -> 0 | AH80: =IFERROR(AG80/BusinessCurrencyTRM,"N/A") -> N/A | AJ80: =IFERROR(SUMIF(PayRise!A:A,B74,PayRise!M:M),0) -> 0 | AK80: =IFERROR(AJ80/BusinessCurrencyTRM,"N/A") -> N/A | AN80: =SUM(AD80,AG80,AJ80) -> 0 | AO80: =IFERROR(AN80/BusinessCurrencyTRM,"N/A") -> N/A | AS80: Phase Price | AV80: =AN85 -> 0 | AW80: =IFERROR(AV80/BusinessCurrencyTRM,"N/A") -> N/A
N81: =IF(Approach="By Hours", "N/A for ByHours", "% Risks") -> N/A for ByHours | O81: 0 | U81: Products | V81: =IFERROR(SUMIFS(OtherCosts!Q:Q,OtherCosts!A:A,B74,OtherCosts!B:B,"Hardware/Software"),0) -> 0 | W81: =IFERROR(V81/BusinessCurrencyTRM,"N/A") -> N/A | Y81: varTotalProducts | AC81: Products | AD81: =IFERROR(SUMIFS(OtherCosts!R:R,OtherCosts!A:A,B74,OtherCosts!B:B,"Hardware/Software"),0) -> 0 | AE81: =IFERROR(AD81/BusinessCurrencyTRM,"N/A") -> N/A | AG81: =IFERROR(SUMIFS(OtherCosts!S:S,OtherCosts!A:A,B74,OtherCosts!B:B,"Hardware/Software"),0) -> 0 | AH81: =IFERROR(AG81/BusinessCurrencyTRM,"N/A") -> N/A | AJ81: =IFERROR(SUMIFS(OtherCosts!T:T,OtherCosts!A:A,B74,OtherCosts!B:B,"Hardware/Software"),0) -> 0 | AK81: =IFERROR(AJ81/BusinessCurrencyTRM,"N/A") -> N/A | AN81: =SUM(AD81,AG81,AJ81) -> 0 | AO81: =IFERROR(AN81/BusinessCurrencyTRM,"N/A") -> N/A | AS81: Monthly Price | AV81: =IFERROR(IF(O82<1,AN85,AN85/O82),0) -> 0 | AW81: =IFERROR(AV81/BusinessCurrencyTRM,"N/A") -> N/A
N82: =IF(Approach="By Hours", "N/A for ByHours", "Duration (Months) *") -> N/A for ByHours | O82: 0 | U82: Vendors | V82: =IFERROR(SUMIFS(OtherCosts!Q:Q,OtherCosts!A:A,B74,OtherCosts!B:B,"Vendor"),0) -> 0 | W82: =IFERROR(V82/BusinessCurrencyTRM,"N/A") -> N/A | Y82: varTotalVAR | AC82: Vendors | AD82: =IFERROR(SUMIFS(OtherCosts!R:R,OtherCosts!A:A,B74,OtherCosts!B:B,"Vendor"),0) -> 0 | AE82: =IFERROR(AD82/BusinessCurrencyTRM,"N/A") -> N/A | AG82: =IFERROR(SUMIFS(OtherCosts!S:S,OtherCosts!A:A,B74,OtherCosts!B:B,"Vendor"),0) -> 0 | AH82: =IFERROR(AG82/BusinessCurrencyTRM,"N/A") -> N/A | AJ82: =IFERROR(SUMIFS(OtherCosts!T:T,OtherCosts!A:A,B74,OtherCosts!B:B,"Vendor"),0) -> 0 | AK82: =IFERROR(AJ82/BusinessCurrencyTRM,"N/A") -> N/A | AN82: =SUM(AD82,AG82,AJ82) -> 0 | AO82: =IFERROR(AN82/BusinessCurrencyTRM,"N/A") -> N/A | AS82: Hour Price | AV82: =IFERROR(AN85/T88,0) -> 0 | AW82: =IFERROR(AV82/BusinessCurrencyTRM,"N/A") -> N/A
U83: Insurances | V83: =IFERROR(SUMIFS(OtherCosts!Q:Q,OtherCosts!A:A,B74,OtherCosts!B:B,"Insurance"),0) -> 0 | W83: =IFERROR(V83/BusinessCurrencyTRM,"N/A") -> N/A | Y83: varTotalInsurances | AC83: Insurances | AD83: =IFERROR(SUMIFS(OtherCosts!R:R,OtherCosts!A:A,B74,OtherCosts!B:B,"Insurance"),0) -> 0 | AE83: =IFERROR(AD83/BusinessCurrencyTRM,"N/A") -> N/A | AG83: =IFERROR(SUMIFS(OtherCosts!S:S,OtherCosts!A:A,B74,OtherCosts!B:B,"Insurance"),0) -> 0 | AH83: =IFERROR(AG83/BusinessCurrencyTRM,"N/A") -> N/A | AJ83: =IFERROR(SUMIFS(OtherCosts!T:T,OtherCosts!A:A,B74,OtherCosts!B:B,"Insurance"),0) -> 0 | AK83: =IFERROR(AJ83/BusinessCurrencyTRM,"N/A") -> N/A | AN83: =SUM(AD83,AG83,AJ83) -> 0 | AO83: =IFERROR(AN83/BusinessCurrencyTRM,"N/A") -> N/A
U84: Others | V84: =IFERROR(SUMIFS(OtherCosts!Q:Q,OtherCosts!A:A,B74,OtherCosts!B:B,"Other"),0) -> 0 | W84: =IFERROR(V84/BusinessCurrencyTRM,"N/A") -> N/A | Y84: varTotalOthers | AC84: Others | AD84: =IFERROR(SUMIFS(OtherCosts!R:R,OtherCosts!A:A,B74,OtherCosts!B:B,"Other"),0) -> 0 | AE84: =IFERROR(AD84/BusinessCurrencyTRM,"N/A") -> N/A | AG84: =IFERROR(SUMIFS(OtherCosts!S:S,OtherCosts!A:A,B74,OtherCosts!B:B,"Other"),0) -> 0 | AH84: =IFERROR(AG84/BusinessCurrencyTRM,"N/A") -> N/A | AJ84: =IFERROR(SUMIFS(OtherCosts!T:T,OtherCosts!A:A,B74,OtherCosts!B:B,"Other"),0) -> 0 | AK84: =IFERROR(AJ84/BusinessCurrencyTRM,"N/A") -> N/A | AN84: =SUM(AD84,AG84,AJ84) -> 0 | AO84: =IFERROR(AN84/BusinessCurrencyTRM,"N/A") -> N/A
U85: Subtotal | V85: =SUM(V78:V84) -> 0 | W85: =IFERROR(V85/BusinessCurrencyTRM,"N/A") -> N/A | AC85: Subtotal | AD85: =SUM(AD78:AD84) -> 0 | AE85: =IFERROR(AD85/BusinessCurrencyTRM,"N/A") -> N/A | AG85: =SUM(AG78:AG84) -> 0 | AH85: =IFERROR(AG85/BusinessCurrencyTRM,"N/A") -> N/A | AJ85: =SUM(AJ78:AJ84) -> 0 | AK85: =IFERROR(AJ85/BusinessCurrencyTRM,"N/A") -> N/A | AN85: =SUM(AD85,AG85,AJ85) -> 0 | AO85: =IFERROR(AN85/BusinessCurrencyTRM,"N/A") -> N/A
G88: =ROUNDUP(SUM(G90:G121),2) -> 0 | J88: =ROUNDUP(SUM(J90:J121),2) -> 0 | T88: =ROUNDUP(SUM(T90:T121),2) -> 0 | W88: =SUM(W90:W119) -> 0 | Y88: varTotalFase | AD88: =SUM(AD90:AD121) -> 0 | AE88: =IFERROR(1-($W88/$AD88),0) -> 0 | AH88: =SUM(AH90:AH121) -> 0 | AK88: =ROUNDUP(SUM(AK90:AK121),2) -> 0 | AM88: =SUM(AM90:AM121) -> 0 | AN88: =SUM(AN90:AN121) -> 0 | AO88: =BillingCountryCurrency -> USD | AT88: =SUM(AT90:AU121) -> 0 | AV88: =BillingCountryCurrency -> USD | AW88: =IF(ISBLANK(BusinessCurrency),"N/A",BusinessCurrency) -> N/A
G89: Hours | H89: Risk | I89: EE | J89: Total | N89: Delivery Country | O89: Services Line | P89: Job Profile | Q89: Qty | R89: % Allocation | S89: Days | T89: Total Hours | U89: % Surcharge Hours | V89: Unit Cost Base | W89: Subtotal Cost | X89: FilterSL | Y89: FilterJP | AC89: Unit Price Base | AD89: Subtotal Price | AE89: % MaS | AG89: % Intercomp | AH89: $ Intercompany | AJ89: % WHT | AK89: $ WHT | AM89: Subtotal Price | AN89: Subtotal Price + Costs | AO89: Unit Price + Costs | AS89: Fact | AT89: Subtotal Price + Costs | AV89: Unit Price + Cost | AW89: Unit Price + Cost
B90: Observaciones / Incluido: | H90: 0 | I90: 0 | J90: =IFERROR(G90/(1-(H90+I90)),0) -> 0 | S90: =IF(ISBLANK(P90),0,$O$82*20) -> 0 | T90: =J88 -> 0 | U90: 0 | V90: =ROUNDUP(IFERROR(INDEX(CostRateTbl[Cost Rate],MATCH(_xlfn.CONCAT(N90,O90,P90,"NA"),CostRateTbl[KeyCostRate],0)),0)*BillingCurrencyTRM*(1+U90),2) -> 0 | W90: =T90*V90 -> 0 | X90: {=_xlfn.LET( _xlpm.valor, INDEX(CostRate!H:H, MATCH(1, (CostRate!A:A=N90)*1, 0)), _xlpm.posicion, MATCH(_xlpm.valor, FilterSL!$F$1:$Z$1, 0), _xlpm.direccionCompleta, ADDRESS(1, _xlpm.posicion + 5, 4), _xlpm.letraColumna, SUBSTITUTE(_xlpm.direccionCompleta, "1", ""), _xlpm.letraColumna )} -> #N/A | Y90: {=_xlfn.LET( _xlpm.valor, INDEX(CostRate!I:I, MATCH(1, (CostRate!A:A=N90)*(CostRate!B:B=O90), 0)), _xlpm.posicion, MATCH(_xlpm.valor, FilterJP!$E$1:$FZ$1, 0), _xlpm.direccionCompleta, ADDRESS(1, _xlpm.posicion + 4, 4), _xlpm.letraColumna, SUBSTITUTE(_xlpm.direccionCompleta, "1", ""), _xlpm.letraColumna )} -> #N/A | AC90: =ROUNDUP($V90/(1-$AV$76),2) -> 0 | AD90: =$T90*$AC90 -> 0 | AE90: =IFERROR(1-($W90/$AD90),0) -> 0 | AG90: =IFERROR(IF(OR(ISBLANK(N90),N90=CustomerCountry,COUNTIF($N90,"*xDC*")),0,10%),0) -> 0 | AH90: =W90*AG90 -> 0 | AJ90: {=IFERROR(INDEX(WHT!$C$7:$W$18,MATCH( _xlfn.SWITCH(N90,"xDC Medellin","Colombia","xDC Belo Horizonte","Brazil","xDC Guadalajara","Mexico","xDC Gurugram","India","xDC Leon","Spain","xDC San Jose","Costa Rica","xDC Warsaw","Poland",N90), WHT!$B$7:$B$18,0),MATCH(CustomerCountry,WHT!$C$5:$W$5,0)),0)} -> 0 | AK90: =(W90+AH90)*AJ90 -> 0 | AM90: =SUM($AD90,$AH90,$AK90) -> 0 | AN90: =AM90+IFERROR(SUM($AN$79:$AN$84)*AM90/$AM$88,0) -> 0 | AO90: =IFERROR($AN90/$T90,0) -> 0 | AS90: X | AT90: =IF(AS90="x",AM90+((SUM($AN$79:$AN$84)+SUMIF($AS$90:$AS$121,"<>x",$AM$90:$AM$121))*IFERROR(AM90/SUMIF($AS$90:$AS$121,"x",$AM$90:$AM$121),0)),0) -> 0 | AV90: =IFERROR(AT90/T90,0) -> 0 | AW90: =IFERROR(AV90/BusinessCurrencyTRM,"N/A") -> N/A
H91: 0 | I91: 0 | J91: =IFERROR(G91/(1-(H91+I91)),0) -> 0 | S91: =IF(ISBLANK(P91),0,$O$82*20) -> 0 | T91: =IF(ISBLANK($P91),0,IF(Approach="Team-Based",$Q91*$R91*$S91*HoursPerDayTeamBased,$J91)) -> 0 | U91: 0 | V91: =ROUNDUP(IFERROR(INDEX(CostRateTbl[Cost Rate],MATCH(_xlfn.CONCAT(N91,O91,P91,"NA"),CostRateTbl[KeyCostRate],0)),0)*BillingCurrencyTRM*(1+U91),2) -> 0 | W91: =T91*V91 -> 0 | X91: {=_xlfn.LET( _xlpm.valor, INDEX(CostRate!H:H, MATCH(1, (CostRate!A:A=N91)*1, 0)), _xlpm.posicion, MATCH(_xlpm.valor, FilterSL!$F$1:$Z$1, 0), _xlpm.direccionCompleta, ADDRESS(1, _xlpm.posicion + 5, 4), _xlpm.letraColumna, SUBSTITUTE(_xlpm.direccionCompleta, "1", ""), _xlpm.letraColumna )} -> #N/A | Y91: {=_xlfn.LET( _xlpm.valor, INDEX(CostRate!I:I, MATCH(1, (CostRate!A:A=N91)*(CostRate!B:B=O91), 0)), _xlpm.posicion, MATCH(_xlpm.valor, FilterJP!$E$1:$FZ$1, 0), _xlpm.direccionCompleta, ADDRESS(1, _xlpm.posicion + 4, 4), _xlpm.letraColumna, SUBSTITUTE(_xlpm.direccionCompleta, "1", ""), _xlpm.letraColumna )} -> #N/A | AC91: =ROUNDUP($V91/(1-$AV$76),2) -> 0 | AD91: =$T91*$AC91 -> 0 | AE91: =IFERROR(1-($W91/$AD91),0) -> 0 | AG91: =IFERROR(IF(OR(ISBLANK(N91),N91=CustomerCountry,COUNTIF($N91,"*xDC*")),0,10%),0) -> 0 | AH91: =W91*AG91 -> 0 | AJ91: {=IFERROR(INDEX(WHT!$C$7:$W$18,MATCH( _xlfn.SWITCH(N91,"xDC Medellin","Colombia","xDC Belo Horizonte","Brazil","xDC Guadalajara","Mexico","xDC Gurugram","India","xDC Leon","Spain","xDC San Jose","Costa Rica","xDC Warsaw","Poland",N91), WHT!$B$7:$B$18,0),MATCH(CustomerCountry,WHT!$C$5:$W$5,0)),0)} -> 0 | AK91: =(W91+AH91)*AJ91 -> 0 | AM91: =SUM($AD91,$AH91,$AK91) -> 0 | AN91: =AM91+IFERROR(SUM($AN$79:$AN$84)*AM91/$AM$88,0) -> 0 | AO91: =IFERROR($AN91/$T91,0) -> 0 | AS91: X | AT91: =IF(AS91="x",AM91+((SUM($AN$79:$AN$84)+SUMIF($AS$90:$AS$121,"<>x",$AM$90:$AM$121))*IFERROR(AM91/SUMIF($AS$90:$AS$121,"x",$AM$90:$AM$121),0)),0) -> 0 | AV91: =IFERROR(AT91/T91,0) -> 0 | AW91: =IFERROR(AV91/BusinessCurrencyTRM,"N/A") -> N/A
H92: 0 | I92: 0 | J92: =IFERROR(G92/(1-(H92+I92)),0) -> 0 | S92: =IF(ISBLANK(P92),0,$O$82*20) -> 0 | T92: =IF(ISBLANK($P92),0,IF(Approach="Team-Based",$Q92*$R92*$S92*HoursPerDayTeamBased,$J92)) -> 0 | U92: 0 | V92: =ROUNDUP(IFERROR(INDEX(CostRateTbl[Cost Rate],MATCH(_xlfn.CONCAT(N92,O92,P92,"NA"),CostRateTbl[KeyCostRate],0)),0)*BillingCurrencyTRM*(1+U92),2) -> 0 | W92: =T92*V92 -> 0 | X92: {=_xlfn.LET( _xlpm.valor, INDEX(CostRate!H:H, MATCH(1, (CostRate!A:A=N92)*1, 0)), _xlpm.posicion, MATCH(_xlpm.valor, FilterSL!$F$1:$Z$1, 0), _xlpm.direccionCompleta, ADDRESS(1, _xlpm.posicion + 5, 4), _xlpm.letraColumna, SUBSTITUTE(_xlpm.direccionCompleta, "1", ""), _xlpm.letraColumna )} -> #N/A | Y92: {=_xlfn.LET( _xlpm.valor, INDEX(CostRate!I:I, MATCH(1, (CostRate!A:A=N92)*(CostRate!B:B=O92), 0)), _xlpm.posicion, MATCH(_xlpm.valor, FilterJP!$E$1:$FZ$1, 0), _xlpm.direccionCompleta, ADDRESS(1, _xlpm.posicion + 4, 4), _xlpm.letraColumna, SUBSTITUTE(_xlpm.direccionCompleta, "1", ""), _xlpm.letraColumna )} -> #N/A | AC92: =ROUNDUP($V92/(1-$AV$76),2) -> 0 | AD92: =$T92*$AC92 -> 0 | AE92: =IFERROR(1-($W92/$AD92),0) -> 0 | AG92: =IFERROR(IF(OR(ISBLANK(N92),N92=CustomerCountry,COUNTIF($N92,"*xDC*")),0,10%),0) -> 0 | AH92: =W92*AG92 -> 0 | AJ92: {=IFERROR(INDEX(WHT!$C$7:$W$18,MATCH( _xlfn.SWITCH(N92,"xDC Medellin","Colombia","xDC Belo Horizonte","Brazil","xDC Guadalajara","Mexico","xDC Gurugram","India","xDC Leon","Spain","xDC San Jose","Costa Rica","xDC Warsaw","Poland",N92), WHT!$B$7:$B$18,0),MATCH(CustomerCountry,WHT!$C$5:$W$5,0)),0)} -> 0 | AK92: =(W92+AH92)*AJ92 -> 0 | AM92: =SUM($AD92,$AH92,$AK92) -> 0 | AN92: =AM92+IFERROR(SUM($AN$79:$AN$84)*AM92/$AM$88,0) -> 0 | AO92: =IFERROR($AN92/$T92,0) -> 0 | AS92: X | AT92: =IF(AS92="x",AM92+((SUM($AN$79:$AN$84)+SUMIF($AS$90:$AS$121,"<>x",$AM$90:$AM$121))*IFERROR(AM92/SUMIF($AS$90:$AS$121,"x",$AM$90:$AM$121),0)),0) -> 0 | AV92: =IFERROR(AT92/T92,0) -> 0 | AW92: =IFERROR(AV92/BusinessCurrencyTRM,"N/A") -> N/A
H93: 0 | I93: 0 | J93: =IFERROR(G93/(1-(H93+I93)),0) -> 0 | S93: =IF(ISBLANK(P93),0,$O$82*20) -> 0 | T93: =IF(ISBLANK($P93),0,IF(Approach="Team-Based",$Q93*$R93*$S93*HoursPerDayTeamBased,$J93)) -> 0 | U93: 0 | V93: =ROUNDUP(IFERROR(INDEX(CostRateTbl[Cost Rate],MATCH(_xlfn.CONCAT(N93,O93,P93,"NA"),CostRateTbl[KeyCostRate],0)),0)*BillingCurrencyTRM*(1+U93),2) -> 0 | W93: =T93*V93 -> 0 | X93: {=_xlfn.LET( _xlpm.valor, INDEX(CostRate!H:H, MATCH(1, (CostRate!A:A=N93)*1, 0)), _xlpm.posicion, MATCH(_xlpm.valor, FilterSL!$F$1:$Z$1, 0), _xlpm.direccionCompleta, ADDRESS(1, _xlpm.posicion + 5, 4), _xlpm.letraColumna, SUBSTITUTE(_xlpm.direccionCompleta, "1", ""), _xlpm.letraColumna )} -> #N/A | Y93: {=_xlfn.LET( _xlpm.valor, INDEX(CostRate!I:I, MATCH(1, (CostRate!A:A=N93)*(CostRate!B:B=O93), 0)), _xlpm.posicion, MATCH(_xlpm.valor, FilterJP!$E$1:$FZ$1, 0), _xlpm.direccionCompleta, ADDRESS(1, _xlpm.posicion + 4, 4), _xlpm.letraColumna, SUBSTITUTE(_xlpm.direccionCompleta, "1", ""), _xlpm.letraColumna )} -> #N/A | AC93: =ROUNDUP($V93/(1-$AV$76),2) -> 0 | AD93: =$T93*$AC93 -> 0 | AE93: =IFERROR(1-($W93/$AD93),0) -> 0 | AG93: =IFERROR(IF(OR(ISBLANK(N93),N93=CustomerCountry,COUNTIF($N93,"*xDC*")),0,10%),0) -> 0 | AH93: =W93*AG93 -> 0 | AJ93: {=IFERROR(INDEX(WHT!$C$7:$W$18,MATCH( _xlfn.SWITCH(N93,"xDC Medellin","Colombia","xDC Belo Horizonte","Brazil","xDC Guadalajara","Mexico","xDC Gurugram","India","xDC Leon","Spain","xDC San Jose","Costa Rica","xDC Warsaw","Poland",N93), WHT!$B$7:$B$18,0),MATCH(CustomerCountry,WHT!$C$5:$W$5,0)),0)} -> 0 | AK93: =(W93+AH93)*AJ93 -> 0 | AM93: =SUM($AD93,$AH93,$AK93) -> 0 | AN93: =AM93+IFERROR(SUM($AN$79:$AN$84)*AM93/$AM$88,0) -> 0 | AO93: =IFERROR($AN93/$T93,0) -> 0 | AS93: X | AT93: =IF(AS93="x",AM93+((SUM($AN$79:$AN$84)+SUMIF($AS$90:$AS$121,"<>x",$AM$90:$AM$121))*IFERROR(AM93/SUMIF($AS$90:$AS$121,"x",$AM$90:$AM$121),0)),0) -> 0 | AV93: =IFERROR(AT93/T93,0) -> 0 | AW93: =IFERROR(AV93/BusinessCurrencyTRM,"N/A") -> N/A
H94: 0 | I94: 0 | J94: =IFERROR(G94/(1-(H94+I94)),0) -> 0 | S94: =IF(ISBLANK(P94),0,$O$82*20) -> 0 | T94: =IF(ISBLANK($P94),0,IF(Approach="Team-Based",$Q94*$R94*$S94*HoursPerDayTeamBased,$J94)) -> 0 | U94: 0 | V94: =ROUNDUP(IFERROR(INDEX(CostRateTbl[Cost Rate],MATCH(_xlfn.CONCAT(N94,O94,P94,"NA"),CostRateTbl[KeyCostRate],0)),0)*BillingCurrencyTRM*(1+U94),2) -> 0 | W94: =T94*V94 -> 0 | X94: {=_xlfn.LET( _xlpm.valor, INDEX(CostRate!H:H, MATCH(1, (CostRate!A:A=N94)*1, 0)), _xlpm.posicion, MATCH(_xlpm.valor, FilterSL!$F$1:$Z$1, 0), _xlpm.direccionCompleta, ADDRESS(1, _xlpm.posicion + 5, 4), _xlpm.letraColumna, SUBSTITUTE(_xlpm.direccionCompleta, "1", ""), _xlpm.letraColumna )} -> #N/A | Y94: {=_xlfn.LET( _xlpm.valor, INDEX(CostRate!I:I, MATCH(1, (CostRate!A:A=N94)*(CostRate!B:B=O94), 0)), _xlpm.posicion, MATCH(_xlpm.valor, FilterJP!$E$1:$FZ$1, 0), _xlpm.direccionCompleta, ADDRESS(1, _xlpm.posicion + 4, 4), _xlpm.letraColumna, SUBSTITUTE(_xlpm.direccionCompleta, "1", ""), _xlpm.letraColumna )} -> #N/A | AC94: =ROUNDUP($V94/(1-$AV$76),2) -> 0 | AD94: =$T94*$AC94 -> 0 | AE94: =IFERROR(1-($W94/$AD94),0) -> 0 | AG94: =IFERROR(IF(OR(ISBLANK(N94),N94=CustomerCountry,COUNTIF($N94,"*xDC*")),0,10%),0) -> 0 | AH94: =W94*AG94 -> 0 | AJ94: {=IFERROR(INDEX(WHT!$C$7:$W$18,MATCH( _xlfn.SWITCH(N94,"xDC Medellin","Colombia","xDC Belo Horizonte","Brazil","xDC Guadalajara","Mexico","xDC Gurugram","India","xDC Leon","Spain","xDC San Jose","Costa Rica","xDC Warsaw","Poland",N94), WHT!$B$7:$B$18,0),MATCH(CustomerCountry,WHT!$C$5:$W$5,0)),0)} -> 0 | AK94: =(W94+AH94)*AJ94 -> 0 | AM94: =SUM($AD94,$AH94,$AK94) -> 0 | AN94: =AM94+IFERROR(SUM($AN$79:$AN$84)*AM94/$AM$88,0) -> 0 | AO94: =IFERROR($AN94/$T94,0) -> 0 | AS94: X | AT94: =IF(AS94="x",AM94+((SUM($AN$79:$AN$84)+SUMIF($AS$90:$AS$121,"<>x",$AM$90:$AM$121))*IFERROR(AM94/SUMIF($AS$90:$AS$121,"x",$AM$90:$AM$121),0)),0) -> 0 | AV94: =IFERROR(AT94/T94,0) -> 0 | AW94: =IFERROR(AV94/BusinessCurrencyTRM,"N/A") -> N/A
H95: 0 | I95: 0 | J95: =IFERROR(G95/(1-(H95+I95)),0) -> 0 | S95: =IF(ISBLANK(P95),0,$O$82*20) -> 0 | T95: =IF(ISBLANK($P95),0,IF(Approach="Team-Based",$Q95*$R95*$S95*HoursPerDayTeamBased,$J95)) -> 0 | U95: 0 | V95: =ROUNDUP(IFERROR(INDEX(CostRateTbl[Cost Rate],MATCH(_xlfn.CONCAT(N95,O95,P95,"NA"),CostRateTbl[KeyCostRate],0)),0)*BillingCurrencyTRM*(1+U95),2) -> 0 | W95: =T95*V95 -> 0 | X95: {=_xlfn.LET( _xlpm.valor, INDEX(CostRate!H:H, MATCH(1, (CostRate!A:A=N95)*1, 0)), _xlpm.posicion, MATCH(_xlpm.valor, FilterSL!$F$1:$Z$1, 0), _xlpm.direccionCompleta, ADDRESS(1, _xlpm.posicion + 5, 4), _xlpm.letraColumna, SUBSTITUTE(_xlpm.direccionCompleta, "1", ""), _xlpm.letraColumna )} -> #N/A | Y95: {=_xlfn.LET( _xlpm.valor, INDEX(CostRate!I:I, MATCH(1, (CostRate!A:A=N95)*(CostRate!B:B=O95), 0)), _xlpm.posicion, MATCH(_xlpm.valor, FilterJP!$E$1:$FZ$1, 0), _xlpm.direccionCompleta, ADDRESS(1, _xlpm.posicion + 4, 4), _xlpm.letraColumna, SUBSTITUTE(_xlpm.direccionCompleta, "1", ""), _xlpm.letraColumna )} -> #N/A | AC95: =ROUNDUP($V95/(1-$AV$76),2) -> 0 | AD95: =$T95*$AC95 -> 0 | AE95: =IFERROR(1-($W95/$AD95),0) -> 0 | AG95: =IFERROR(IF(OR(ISBLANK(N95),N95=CustomerCountry,COUNTIF($N95,"*xDC*")),0,10%),0) -> 0 | AH95: =W95*AG95 -> 0 | AJ95: {=IFERROR(INDEX(WHT!$C$7:$W$18,MATCH( _xlfn.SWITCH(N95,"xDC Medellin","Colombia","xDC Belo Horizonte","Brazil","xDC Guadalajara","Mexico","xDC Gurugram","India","xDC Leon","Spain","xDC San Jose","Costa Rica","xDC Warsaw","Poland",N95), WHT!$B$7:$B$18,0),MATCH(CustomerCountry,WHT!$C$5:$W$5,0)),0)} -> 0 | AK95: =(W95+AH95)*AJ95 -> 0 | AM95: =SUM($AD95,$AH95,$AK95) -> 0 | AN95: =AM95+IFERROR(SUM($AN$79:$AN$84)*AM95/$AM$88,0) -> 0 | AO95: =IFERROR($AN95/$T95,0) -> 0 | AS95: X | AT95: =IF(AS95="x",AM95+((SUM($AN$79:$AN$84)+SUMIF($AS$90:$AS$121,"<>x",$AM$90:$AM$121))*IFERROR(AM95/SUMIF($AS$90:$AS$121,"x",$AM$90:$AM$121),0)),0) -> 0 | AV95: =IFERROR(AT95/T95,0) -> 0 | AW95: =IFERROR(AV95/BusinessCurrencyTRM,"N/A") -> N/A
H96: 0 | I96: 0 | J96: =IFERROR(G96/(1-(H96+I96)),0) -> 0 | S96: =IF(ISBLANK(P96),0,$O$82*20) -> 0 | T96: =J88*20% -> 0 | U96: 0 | V96: =ROUNDUP(IFERROR(INDEX(CostRateTbl[Cost Rate],MATCH(_xlfn.CONCAT(N96,O96,P96,"NA"),CostRateTbl[KeyCostRate],0)),0)*BillingCurrencyTRM*(1+U96),2) -> 0 | W96: =T96*V96 -> 0 | X96: {=_xlfn.LET( _xlpm.valor, INDEX(CostRate!H:H, MATCH(1, (CostRate!A:A=N96)*1, 0)), _xlpm.posicion, MATCH(_xlpm.valor, FilterSL!$F$1:$Z$1, 0), _xlpm.direccionCompleta, ADDRESS(1, _xlpm.posicion + 5, 4), _xlpm.letraColumna, SUBSTITUTE(_xlpm.direccionCompleta, "1", ""), _xlpm.letraColumna )} -> #N/A | Y96: {=_xlfn.LET( _xlpm.valor, INDEX(CostRate!I:I, MATCH(1, (CostRate!A:A=N96)*(CostRate!B:B=O96), 0)), _xlpm.posicion, MATCH(_xlpm.valor, FilterJP!$E$1:$FZ$1, 0), _xlpm.direccionCompleta, ADDRESS(1, _xlpm.posicion + 4, 4), _xlpm.letraColumna, SUBSTITUTE(_xlpm.direccionCompleta, "1", ""), _xlpm.letraColumna )} -> #N/A | AC96: =ROUNDUP($V96/(1-$AV$76),2) -> 0 | AD96: =$T96*$AC96 -> 0 | AE96: =IFERROR(1-($W96/$AD96),0) -> 0 | AG96: =IFERROR(IF(OR(ISBLANK(N96),N96=CustomerCountry,COUNTIF($N96,"*xDC*")),0,10%),0) -> 0 | AH96: =W96*AG96 -> 0 | AJ96: {=IFERROR(INDEX(WHT!$C$7:$W$18,MATCH( _xlfn.SWITCH(N96,"xDC Medellin","Colombia","xDC Belo Horizonte","Brazil","xDC Guadalajara","Mexico","xDC Gurugram","India","xDC Leon","Spain","xDC San Jose","Costa Rica","xDC Warsaw","Poland",N96), WHT!$B$7:$B$18,0),MATCH(CustomerCountry,WHT!$C$5:$W$5,0)),0)} -> 0 | AK96: =(W96+AH96)*AJ96 -> 0 | AM96: =SUM($AD96,$AH96,$AK96) -> 0 | AN96: =AM96+IFERROR(SUM($AN$79:$AN$84)*AM96/$AM$88,0) -> 0 | AO96: =IFERROR($AN96/$T96,0) -> 0 | AS96: X | AT96: =IF(AS96="x",AM96+((SUM($AN$79:$AN$84)+SUMIF($AS$90:$AS$121,"<>x",$AM$90:$AM$121))*IFERROR(AM96/SUMIF($AS$90:$AS$121,"x",$AM$90:$AM$121),0)),0) -> 0 | AV96: =IFERROR(AT96/T96,0) -> 0 | AW96: =IFERROR(AV96/BusinessCurrencyTRM,"N/A") -> N/A
H97: 0 | I97: 0 | J97: =IFERROR(G97/(1-(H97+I97)),0) -> 0 | S97: =IF(ISBLANK(P97),0,$O$82*20) -> 0 | T97: =IF(ISBLANK($P97),0,IF(Approach="Team-Based",$Q97*$R97*$S97*HoursPerDayTeamBased,$J97)) -> 0 | U97: 0 | V97: =ROUNDUP(IFERROR(INDEX(CostRateTbl[Cost Rate],MATCH(_xlfn.CONCAT(N97,O97,P97,"NA"),CostRateTbl[KeyCostRate],0)),0)*BillingCurrencyTRM*(1+U97),2) -> 0 | W97: =T97*V97 -> 0 | X97: {=_xlfn.LET( _xlpm.valor, INDEX(CostRate!H:H, MATCH(1, (CostRate!A:A=N97)*1, 0)), _xlpm.posicion, MATCH(_xlpm.valor, FilterSL!$F$1:$Z$1, 0), _xlpm.direccionCompleta, ADDRESS(1, _xlpm.posicion + 5, 4), _xlpm.letraColumna, SUBSTITUTE(_xlpm.direccionCompleta, "1", ""), _xlpm.letraColumna )} -> #N/A | Y97: {=_xlfn.LET( _xlpm.valor, INDEX(CostRate!I:I, MATCH(1, (CostRate!A:A=N97)*(CostRate!B:B=O97), 0)), _xlpm.posicion, MATCH(_xlpm.valor, FilterJP!$E$1:$FZ$1, 0), _xlpm.direccionCompleta, ADDRESS(1, _xlpm.posicion + 4, 4), _xlpm.letraColumna, SUBSTITUTE(_xlpm.direccionCompleta, "1", ""), _xlpm.letraColumna )} -> #N/A | AC97: =ROUNDUP($V97/(1-$AV$76),2) -> 0 | AD97: =$T97*$AC97 -> 0 | AE97: =IFERROR(1-($W97/$AD97),0) -> 0 | AG97: =IFERROR(IF(OR(ISBLANK(N97),N97=CustomerCountry,COUNTIF($N97,"*xDC*")),0,10%),0) -> 0 | AH97: =W97*AG97 -> 0 | AJ97: {=IFERROR(INDEX(WHT!$C$7:$W$18,MATCH( _xlfn.SWITCH(N97,"xDC Medellin","Colombia","xDC Belo Horizonte","Brazil","xDC Guadalajara","Mexico","xDC Gurugram","India","xDC Leon","Spain","xDC San Jose","Costa Rica","xDC Warsaw","Poland",N97), WHT!$B$7:$B$18,0),MATCH(CustomerCountry,WHT!$C$5:$W$5,0)),0)} -> 0 | AK97: =(W97+AH97)*AJ97 -> 0 | AM97: =SUM($AD97,$AH97,$AK97) -> 0 | AN97: =AM97+IFERROR(SUM($AN$79:$AN$84)*AM97/$AM$88,0) -> 0 | AO97: =IFERROR($AN97/$T97,0) -> 0 | AS97: X | AT97: =IF(AS97="x",AM97+((SUM($AN$79:$AN$84)+SUMIF($AS$90:$AS$121,"<>x",$AM$90:$AM$121))*IFERROR(AM97/SUMIF($AS$90:$AS$121,"x",$AM$90:$AM$121),0)),0) -> 0 | AV97: =IFERROR(AT97/T97,0) -> 0 | AW97: =IFERROR(AV97/BusinessCurrencyTRM,"N/A") -> N/A
H98: 0 | I98: 0 | J98: =IFERROR(G98/(1-(H98+I98)),0) -> 0 | S98: =IF(ISBLANK(P98),0,$O$82*20) -> 0 | T98: =IF(ISBLANK($P98),0,IF(Approach="Team-Based",$Q98*$R98*$S98*HoursPerDayTeamBased,$J98)) -> 0 | U98: 0 | V98: =ROUNDUP(IFERROR(INDEX(CostRateTbl[Cost Rate],MATCH(_xlfn.CONCAT(N98,O98,P98,"NA"),CostRateTbl[KeyCostRate],0)),0)*BillingCurrencyTRM*(1+U98),2) -> 0 | W98: =T98*V98 -> 0 | X98: {=_xlfn.LET( _xlpm.valor, INDEX(CostRate!H:H, MATCH(1, (CostRate!A:A=N98)*1, 0)), _xlpm.posicion, MATCH(_xlpm.valor, FilterSL!$F$1:$Z$1, 0), _xlpm.direccionCompleta, ADDRESS(1, _xlpm.posicion + 5, 4), _xlpm.letraColumna, SUBSTITUTE(_xlpm.direccionCompleta, "1", ""), _xlpm.letraColumna )} -> #N/A | Y98: {=_xlfn.LET( _xlpm.valor, INDEX(CostRate!I:I, MATCH(1, (CostRate!A:A=N98)*(CostRate!B:B=O98), 0)), _xlpm.posicion, MATCH(_xlpm.valor, FilterJP!$E$1:$FZ$1, 0), _xlpm.direccionCompleta, ADDRESS(1, _xlpm.posicion + 4, 4), _xlpm.letraColumna, SUBSTITUTE(_xlpm.direccionCompleta, "1", ""), _xlpm.letraColumna )} -> #N/A | AC98: =ROUNDUP($V98/(1-$AV$76),2) -> 0 | AD98: =$T98*$AC98 -> 0 | AE98: =IFERROR(1-($W98/$AD98),0) -> 0 | AG98: =IFERROR(IF(OR(ISBLANK(N98),N98=CustomerCountry,COUNTIF($N98,"*xDC*")),0,10%),0) -> 0 | AH98: =W98*AG98 -> 0 | AJ98: {=IFERROR(INDEX(WHT!$C$7:$W$18,MATCH( _xlfn.SWITCH(N98,"xDC Medellin","Colombia","xDC Belo Horizonte","Brazil","xDC Guadalajara","Mexico","xDC Gurugram","India","xDC Leon","Spain","xDC San Jose","Costa Rica","xDC Warsaw","Poland",N98), WHT!$B$7:$B$18,0),MATCH(CustomerCountry,WHT!$C$5:$W$5,0)),0)} -> 0 | AK98: =(W98+AH98)*AJ98 -> 0 | AM98: =SUM($AD98,$AH98,$AK98) -> 0 | AN98: =AM98+IFERROR(SUM($AN$79:$AN$84)*AM98/$AM$88,0) -> 0 | AO98: =IFERROR($AN98/$T98,0) -> 0 | AS98: X | AT98: =IF(AS98="x",AM98+((SUM($AN$79:$AN$84)+SUMIF($AS$90:$AS$121,"<>x",$AM$90:$AM$121))*IFERROR(AM98/SUMIF($AS$90:$AS$121,"x",$AM$90:$AM$121),0)),0) -> 0 | AV98: =IFERROR(AT98/T98,0) -> 0 | AW98: =IFERROR(AV98/BusinessCurrencyTRM,"N/A") -> N/A
H99: 0 | I99: 0 | J99: =IFERROR(G99/(1-(H99+I99)),0) -> 0 | S99: =IF(ISBLANK(P99),0,$O$82*20) -> 0 | T99: =IF(ISBLANK($P99),0,IF(Approach="Team-Based",$Q99*$R99*$S99*HoursPerDayTeamBased,$J99)) -> 0 | U99: 0 | V99: =ROUNDUP(IFERROR(INDEX(CostRateTbl[Cost Rate],MATCH(_xlfn.CONCAT(N99,O99,P99,"NA"),CostRateTbl[KeyCostRate],0)),0)*BillingCurrencyTRM*(1+U99),2) -> 0 | W99: =T99*V99 -> 0 | X99: {=_xlfn.LET( _xlpm.valor, INDEX(CostRate!H:H, MATCH(1, (CostRate!A:A=N99)*1, 0)), _xlpm.posicion, MATCH(_xlpm.valor, FilterSL!$F$1:$Z$1, 0), _xlpm.direccionCompleta, ADDRESS(1, _xlpm.posicion + 5, 4), _xlpm.letraColumna, SUBSTITUTE(_xlpm.direccionCompleta, "1", ""), _xlpm.letraColumna )} -> #N/A | Y99: {=_xlfn.LET( _xlpm.valor, INDEX(CostRate!I:I, MATCH(1, (CostRate!A:A=N99)*(CostRate!B:B=O99), 0)), _xlpm.posicion, MATCH(_xlpm.valor, FilterJP!$E$1:$FZ$1, 0), _xlpm.direccionCompleta, ADDRESS(1, _xlpm.posicion + 4, 4), _xlpm.letraColumna, SUBSTITUTE(_xlpm.direccionCompleta, "1", ""), _xlpm.letraColumna )} -> #N/A | AC99: =ROUNDUP($V99/(1-$AV$76),2) -> 0 | AD99: =$T99*$AC99 -> 0 | AE99: =IFERROR(1-($W99/$AD99),0) -> 0 | AG99: =IFERROR(IF(OR(ISBLANK(N99),N99=CustomerCountry,COUNTIF($N99,"*xDC*")),0,10%),0) -> 0 | AH99: =W99*AG99 -> 0 | AJ99: {=IFERROR(INDEX(WHT!$C$7:$W$18,MATCH( _xlfn.SWITCH(N99,"xDC Medellin","Colombia","xDC Belo Horizonte","Brazil","xDC Guadalajara","Mexico","xDC Gurugram","India","xDC Leon","Spain","xDC San Jose","Costa Rica","xDC Warsaw","Poland",N99), WHT!$B$7:$B$18,0),MATCH(CustomerCountry,WHT!$C$5:$W$5,0)),0)} -> 0 | AK99: =(W99+AH99)*AJ99 -> 0 | AM99: =SUM($AD99,$AH99,$AK99) -> 0 | AN99: =AM99+IFERROR(SUM($AN$79:$AN$84)*AM99/$AM$88,0) -> 0 | AO99: =IFERROR($AN99/$T99,0) -> 0 | AS99: X | AT99: =IF(AS99="x",AM99+((SUM($AN$79:$AN$84)+SUMIF($AS$90:$AS$121,"<>x",$AM$90:$AM$121))*IFERROR(AM99/SUMIF($AS$90:$AS$121,"x",$AM$90:$AM$121),0)),0) -> 0 | AV99: =IFERROR(AT99/T99,0) -> 0 | AW99: =IFERROR(AV99/BusinessCurrencyTRM,"N/A") -> N/A
H100: 0 | I100: 0 | J100: =IFERROR(G100/(1-(H100+I100)),0) -> 0 | S100: =IF(ISBLANK(P100),0,$O$82*20) -> 0 | T100: =IF(ISBLANK($P100),0,IF(Approach="Team-Based",$Q100*$R100*$S100*HoursPerDayTeamBased,$J100)) -> 0 | U100: 0 | V100: =ROUNDUP(IFERROR(INDEX(CostRateTbl[Cost Rate],MATCH(_xlfn.CONCAT(N100,O100,P100,"NA"),CostRateTbl[KeyCostRate],0)),0)*BillingCurrencyTRM*(1+U100),2) -> 0 | W100: =T100*V100 -> 0 | X100: {=_xlfn.LET( _xlpm.valor, INDEX(CostRate!H:H, MATCH(1, (CostRate!A:A=N100)*1, 0)), _xlpm.posicion, MATCH(_xlpm.valor, FilterSL!$F$1:$Z$1, 0), _xlpm.direccionCompleta, ADDRESS(1, _xlpm.posicion + 5, 4), _xlpm.letraColumna, SUBSTITUTE(_xlpm.direccionCompleta, "1", ""), _xlpm.letraColumna )} -> #N/A | Y100: {=_xlfn.LET( _xlpm.valor, INDEX(CostRate!I:I, MATCH(1, (CostRate!A:A=N100)*(CostRate!B:B=O100), 0)), _xlpm.posicion, MATCH(_xlpm.valor, FilterJP!$E$1:$FZ$1, 0), _xlpm.direccionCompleta, ADDRESS(1, _xlpm.posicion + 4, 4), _xlpm.letraColumna, SUBSTITUTE(_xlpm.direccionCompleta, "1", ""), _xlpm.letraColumna )} -> #N/A | AC100: =ROUNDUP($V100/(1-$AV$76),2) -> 0 | AD100: =$T100*$AC100 -> 0 | AE100: =IFERROR(1-($W100/$AD100),0) -> 0 | AG100: =IFERROR(IF(OR(ISBLANK(N100),N100=CustomerCountry,COUNTIF($N100,"*xDC*")),0,10%),0) -> 0 | AH100: =W100*AG100 -> 0 | AJ100: {=IFERROR(INDEX(WHT!$C$7:$W$18,MATCH( _xlfn.SWITCH(N100,"xDC Medellin","Colombia","xDC Belo Horizonte","Brazil","xDC Guadalajara","Mexico","xDC Gurugram","India","xDC Leon","Spain","xDC San Jose","Costa Rica","xDC Warsaw","Poland",N100), WHT!$B$7:$B$18,0),MATCH(CustomerCountry,WHT!$C$5:$W$5,0)),0)} -> 0 | AK100: =(W100+AH100)*AJ100 -> 0 | AM100: =SUM($AD100,$AH100,$AK100) -> 0 | AN100: =AM100+IFERROR(SUM($AN$79:$AN$84)*AM100/$AM$88,0) -> 0 | AO100: =IFERROR($AN100/$T100,0) -> 0 | AS100: X | AT100: =IF(AS100="x",AM100+((SUM($AN$79:$AN$84)+SUMIF($AS$90:$AS$121,"<>x",$AM$90:$AM$121))*IFERROR(AM100/SUMIF($AS$90:$AS$121,"x",$AM$90:$AM$121),0)),0) -> 0 | AV100: =IFERROR(AT100/T100,0) -> 0 | AW100: =IFERROR(AV100/BusinessCurrencyTRM,"N/A") -> N/A
H101: 0 | I101: 0 | J101: =IFERROR(G101/(1-(H101+I101)),0) -> 0 | S101: =IF(ISBLANK(P101),0,$O$82*20) -> 0 | T101: =IF(ISBLANK($P101),0,IF(Approach="Team-Based",$Q101*$R101*$S101*HoursPerDayTeamBased,$J101)) -> 0 | U101: 0 | V101: =ROUNDUP(IFERROR(INDEX(CostRateTbl[Cost Rate],MATCH(_xlfn.CONCAT(N101,O101,P101,"NA"),CostRateTbl[KeyCostRate],0)),0)*BillingCurrencyTRM*(1+U101),2) -> 0 | W101: =T101*V101 -> 0 | X101: {=_xlfn.LET( _xlpm.valor, INDEX(CostRate!H:H, MATCH(1, (CostRate!A:A=N101)*1, 0)), _xlpm.posicion, MATCH(_xlpm.valor, FilterSL!$F$1:$Z$1, 0), _xlpm.direccionCompleta, ADDRESS(1, _xlpm.posicion + 5, 4), _xlpm.letraColumna, SUBSTITUTE(_xlpm.direccionCompleta, "1", ""), _xlpm.letraColumna )} -> #N/A | Y101: {=_xlfn.LET( _xlpm.valor, INDEX(CostRate!I:I, MATCH(1, (CostRate!A:A=N101)*(CostRate!B:B=O101), 0)), _xlpm.posicion, MATCH(_xlpm.valor, FilterJP!$E$1:$FZ$1, 0), _xlpm.direccionCompleta, ADDRESS(1, _xlpm.posicion + 4, 4), _xlpm.letraColumna, SUBSTITUTE(_xlpm.direccionCompleta, "1", ""), _xlpm.letraColumna )} -> #N/A | AC101: =ROUNDUP($V101/(1-$AV$76),2) -> 0 | AD101: =$T101*$AC101 -> 0 | AE101: =IFERROR(1-($W101/$AD101),0) -> 0 | AG101: =IFERROR(IF(OR(ISBLANK(N101),N101=CustomerCountry,COUNTIF($N101,"*xDC*")),0,10%),0) -> 0 | AH101: =W101*AG101 -> 0 | AJ101: {=IFERROR(INDEX(WHT!$C$7:$W$18,MATCH( _xlfn.SWITCH(N101,"xDC Medellin","Colombia","xDC Belo Horizonte","Brazil","xDC Guadalajara","Mexico","xDC Gurugram","India","xDC Leon","Spain","xDC San Jose","Costa Rica","xDC Warsaw","Poland",N101), WHT!$B$7:$B$18,0),MATCH(CustomerCountry,WHT!$C$5:$W$5,0)),0)} -> 0 | AK101: =(W101+AH101)*AJ101 -> 0 | AM101: =SUM($AD101,$AH101,$AK101) -> 0 | AN101: =AM101+IFERROR(SUM($AN$79:$AN$84)*AM101/$AM$88,0) -> 0 | AO101: =IFERROR($AN101/$T101,0) -> 0 | AS101: X | AT101: =IF(AS101="x",AM101+((SUM($AN$79:$AN$84)+SUMIF($AS$90:$AS$121,"<>x",$AM$90:$AM$121))*IFERROR(AM101/SUMIF($AS$90:$AS$121,"x",$AM$90:$AM$121),0)),0) -> 0 | AV101: =IFERROR(AT101/T101,0) -> 0 | AW101: =IFERROR(AV101/BusinessCurrencyTRM,"N/A") -> N/A
H102: 0 | I102: 0 | J102: =IFERROR(G102/(1-(H102+I102)),0) -> 0 | S102: =IF(ISBLANK(P102),0,$O$82*20) -> 0 | T102: =IF(ISBLANK($P102),0,IF(Approach="Team-Based",$Q102*$R102*$S102*HoursPerDayTeamBased,$J102)) -> 0 | U102: 0 | V102: =ROUNDUP(IFERROR(INDEX(CostRateTbl[Cost Rate],MATCH(_xlfn.CONCAT(N102,O102,P102,"NA"),CostRateTbl[KeyCostRate],0)),0)*BillingCurrencyTRM*(1+U102),2) -> 0 | W102: =T102*V102 -> 0 | X102: {=_xlfn.LET( _xlpm.valor, INDEX(CostRate!H:H, MATCH(1, (CostRate!A:A=N102)*1, 0)), _xlpm.posicion, MATCH(_xlpm.valor, FilterSL!$F$1:$Z$1, 0), _xlpm.direccionCompleta, ADDRESS(1, _xlpm.posicion + 5, 4), _xlpm.letraColumna, SUBSTITUTE(_xlpm.direccionCompleta, "1", ""), _xlpm.letraColumna )} -> #N/A | Y102: {=_xlfn.LET( _xlpm.valor, INDEX(CostRate!I:I, MATCH(1, (CostRate!A:A=N102)*(CostRate!B:B=O102), 0)), _xlpm.posicion, MATCH(_xlpm.valor, FilterJP!$E$1:$FZ$1, 0), _xlpm.direccionCompleta, ADDRESS(1, _xlpm.posicion + 4, 4), _xlpm.letraColumna, SUBSTITUTE(_xlpm.direccionCompleta, "1", ""), _xlpm.letraColumna )} -> #N/A | AC102: =ROUNDUP($V102/(1-$AV$76),2) -> 0 | AD102: =$T102*$AC102 -> 0 | AE102: =IFERROR(1-($W102/$AD102),0) -> 0 | AG102: =IFERROR(IF(OR(ISBLANK(N102),N102=CustomerCountry,COUNTIF($N102,"*xDC*")),0,10%),0) -> 0 | AH102: =W102*AG102 -> 0 | AJ102: {=IFERROR(INDEX(WHT!$C$7:$W$18,MATCH( _xlfn.SWITCH(N102,"xDC Medellin","Colombia","xDC Belo Horizonte","Brazil","xDC Guadalajara","Mexico","xDC Gurugram","India","xDC Leon","Spain","xDC San Jose","Costa Rica","xDC Warsaw","Poland",N102), WHT!$B$7:$B$18,0),MATCH(CustomerCountry,WHT!$C$5:$W$5,0)),0)} -> 0 | AK102: =(W102+AH102)*AJ102 -> 0 | AM102: =SUM($AD102,$AH102,$AK102) -> 0 | AN102: =AM102+IFERROR(SUM($AN$79:$AN$84)*AM102/$AM$88,0) -> 0 | AO102: =IFERROR($AN102/$T102,0) -> 0 | AS102: X | AT102: =IF(AS102="x",AM102+((SUM($AN$79:$AN$84)+SUMIF($AS$90:$AS$121,"<>x",$AM$90:$AM$121))*IFERROR(AM102/SUMIF($AS$90:$AS$121,"x",$AM$90:$AM$121),0)),0) -> 0 | AV102: =IFERROR(AT102/T102,0) -> 0 | AW102: =IFERROR(AV102/BusinessCurrencyTRM,"N/A") -> N/A
H103: 0 | I103: 0 | J103: =IFERROR(G103/(1-(H103+I103)),0) -> 0 | S103: =IF(ISBLANK(P103),0,$O$82*20) -> 0 | T103: =IF(ISBLANK($P103),0,IF(Approach="Team-Based",$Q103*$R103*$S103*HoursPerDayTeamBased,$J103)) -> 0 | U103: 0 | V103: =ROUNDUP(IFERROR(INDEX(CostRateTbl[Cost Rate],MATCH(_xlfn.CONCAT(N103,O103,P103,"NA"),CostRateTbl[KeyCostRate],0)),0)*BillingCurrencyTRM*(1+U103),2) -> 0 | W103: =T103*V103 -> 0 | X103: {=_xlfn.LET( _xlpm.valor, INDEX(CostRate!H:H, MATCH(1, (CostRate!A:A=N103)*1, 0)), _xlpm.posicion, MATCH(_xlpm.valor, FilterSL!$F$1:$Z$1, 0), _xlpm.direccionCompleta, ADDRESS(1, _xlpm.posicion + 5, 4), _xlpm.letraColumna, SUBSTITUTE(_xlpm.direccionCompleta, "1", ""), _xlpm.letraColumna )} -> #N/A | Y103: {=_xlfn.LET( _xlpm.valor, INDEX(CostRate!I:I, MATCH(1, (CostRate!A:A=N103)*(CostRate!B:B=O103), 0)), _xlpm.posicion, MATCH(_xlpm.valor, FilterJP!$E$1:$FZ$1, 0), _xlpm.direccionCompleta, ADDRESS(1, _xlpm.posicion + 4, 4), _xlpm.letraColumna, SUBSTITUTE(_xlpm.direccionCompleta, "1", ""), _xlpm.letraColumna )} -> #N/A | AC103: =ROUNDUP($V103/(1-$AV$76),2) -> 0 | AD103: =$T103*$AC103 -> 0 | AE103: =IFERROR(1-($W103/$AD103),0) -> 0 | AG103: =IFERROR(IF(OR(ISBLANK(N103),N103=CustomerCountry,COUNTIF($N103,"*xDC*")),0,10%),0) -> 0 | AH103: =W103*AG103 -> 0 | AJ103: {=IFERROR(INDEX(WHT!$C$7:$W$18,MATCH( _xlfn.SWITCH(N103,"xDC Medellin","Colombia","xDC Belo Horizonte","Brazil","xDC Guadalajara","Mexico","xDC Gurugram","India","xDC Leon","Spain","xDC San Jose","Costa Rica","xDC Warsaw","Poland",N103), WHT!$B$7:$B$18,0),MATCH(CustomerCountry,WHT!$C$5:$W$5,0)),0)} -> 0 | AK103: =(W103+AH103)*AJ103 -> 0 | AM103: =SUM($AD103,$AH103,$AK103) -> 0 | AN103: =AM103+IFERROR(SUM($AN$79:$AN$84)*AM103/$AM$88,0) -> 0 | AO103: =IFERROR($AN103/$T103,0) -> 0 | AS103: X | AT103: =IF(AS103="x",AM103+((SUM($AN$79:$AN$84)+SUMIF($AS$90:$AS$121,"<>x",$AM$90:$AM$121))*IFERROR(AM103/SUMIF($AS$90:$AS$121,"x",$AM$90:$AM$121),0)),0) -> 0 | AV103: =IFERROR(AT103/T103,0) -> 0 | AW103: =IFERROR(AV103/BusinessCurrencyTRM,"N/A") -> N/A
H104: 0 | I104: 0 | J104: =IFERROR(G104/(1-(H104+I104)),0) -> 0 | S104: =IF(ISBLANK(P104),0,$O$82*20) -> 0 | T104: =IF(ISBLANK($P104),0,IF(Approach="Team-Based",$Q104*$R104*$S104*HoursPerDayTeamBased,$J104)) -> 0 | U104: 0 | V104: =ROUNDUP(IFERROR(INDEX(CostRateTbl[Cost Rate],MATCH(_xlfn.CONCAT(N104,O104,P104,"NA"),CostRateTbl[KeyCostRate],0)),0)*BillingCurrencyTRM*(1+U104),2) -> 0 | W104: =T104*V104 -> 0 | X104: {=_xlfn.LET( _xlpm.valor, INDEX(CostRate!H:H, MATCH(1, (CostRate!A:A=N104)*1, 0)), _xlpm.posicion, MATCH(_xlpm.valor, FilterSL!$F$1:$Z$1, 0), _xlpm.direccionCompleta, ADDRESS(1, _xlpm.posicion + 5, 4), _xlpm.letraColumna, SUBSTITUTE(_xlpm.direccionCompleta, "1", ""), _xlpm.letraColumna )} -> #N/A | Y104: {=_xlfn.LET( _xlpm.valor, INDEX(CostRate!I:I, MATCH(1, (CostRate!A:A=N104)*(CostRate!B:B=O104), 0)), _xlpm.posicion, MATCH(_xlpm.valor, FilterJP!$E$1:$FZ$1, 0), _xlpm.direccionCompleta, ADDRESS(1, _xlpm.posicion + 4, 4), _xlpm.letraColumna, SUBSTITUTE(_xlpm.direccionCompleta, "1", ""), _xlpm.letraColumna )} -> #N/A | AC104: =ROUNDUP($V104/(1-$AV$76),2) -> 0 | AD104: =$T104*$AC104 -> 0 | AE104: =IFERROR(1-($W104/$AD104),0) -> 0 | AG104: =IFERROR(IF(OR(ISBLANK(N104),N104=CustomerCountry,COUNTIF($N104,"*xDC*")),0,10%),0) -> 0 | AH104: =W104*AG104 -> 0 | AJ104: {=IFERROR(INDEX(WHT!$C$7:$W$18,MATCH( _xlfn.SWITCH(N104,"xDC Medellin","Colombia","xDC Belo Horizonte","Brazil","xDC Guadalajara","Mexico","xDC Gurugram","India","xDC Leon","Spain","xDC San Jose","Costa Rica","xDC Warsaw","Poland",N104), WHT!$B$7:$B$18,0),MATCH(CustomerCountry,WHT!$C$5:$W$5,0)),0)} -> 0 | AK104: =(W104+AH104)*AJ104 -> 0 | AM104: =SUM($AD104,$AH104,$AK104) -> 0 | AN104: =AM104+IFERROR(SUM($AN$79:$AN$84)*AM104/$AM$88,0) -> 0 | AO104: =IFERROR($AN104/$T104,0) -> 0 | AS104: X | AT104: =IF(AS104="x",AM104+((SUM($AN$79:$AN$84)+SUMIF($AS$90:$AS$121,"<>x",$AM$90:$AM$121))*IFERROR(AM104/SUMIF($AS$90:$AS$121,"x",$AM$90:$AM$121),0)),0) -> 0 | AV104: =IFERROR(AT104/T104,0) -> 0 | AW104: =IFERROR(AV104/BusinessCurrencyTRM,"N/A") -> N/A
H105: 0 | I105: 0 | J105: =IFERROR(G105/(1-(H105+I105)),0) -> 0 | S105: =IF(ISBLANK(P105),0,$O$82*20) -> 0 | T105: =IF(ISBLANK($P105),0,IF(Approach="Team-Based",$Q105*$R105*$S105*HoursPerDayTeamBased,$J105)) -> 0 | U105: 0 | V105: =ROUNDUP(IFERROR(INDEX(CostRateTbl[Cost Rate],MATCH(_xlfn.CONCAT(N105,O105,P105,"NA"),CostRateTbl[KeyCostRate],0)),0)*BillingCurrencyTRM*(1+U105),2) -> 0 | W105: =T105*V105 -> 0 | X105: {=_xlfn.LET( _xlpm.valor, INDEX(CostRate!H:H, MATCH(1, (CostRate!A:A=N105)*1, 0)), _xlpm.posicion, MATCH(_xlpm.valor, FilterSL!$F$1:$Z$1, 0), _xlpm.direccionCompleta, ADDRESS(1, _xlpm.posicion + 5, 4), _xlpm.letraColumna, SUBSTITUTE(_xlpm.direccionCompleta, "1", ""), _xlpm.letraColumna )} -> #N/A | Y105: {=_xlfn.LET( _xlpm.valor, INDEX(CostRate!I:I, MATCH(1, (CostRate!A:A=N105)*(CostRate!B:B=O105), 0)), _xlpm.posicion, MATCH(_xlpm.valor, FilterJP!$E$1:$FZ$1, 0), _xlpm.direccionCompleta, ADDRESS(1, _xlpm.posicion + 4, 4), _xlpm.letraColumna, SUBSTITUTE(_xlpm.direccionCompleta, "1", ""), _xlpm.letraColumna )} -> #N/A | AC105: =ROUNDUP($V105/(1-$AV$76),2) -> 0 | AD105: =$T105*$AC105 -> 0 | AE105: =IFERROR(1-($W105/$AD105),0) -> 0 | AG105: =IFERROR(IF(OR(ISBLANK(N105),N105=CustomerCountry,COUNTIF($N105,"*xDC*")),0,10%),0) -> 0 | AH105: =W105*AG105 -> 0 | AJ105: {=IFERROR(INDEX(WHT!$C$7:$W$18,MATCH( _xlfn.SWITCH(N105,"xDC Medellin","Colombia","xDC Belo Horizonte","Brazil","xDC Guadalajara","Mexico","xDC Gurugram","India","xDC Leon","Spain","xDC San Jose","Costa Rica","xDC Warsaw","Poland",N105), WHT!$B$7:$B$18,0),MATCH(CustomerCountry,WHT!$C$5:$W$5,0)),0)} -> 0 | AK105: =(W105+AH105)*AJ105 -> 0 | AM105: =SUM($AD105,$AH105,$AK105) -> 0 | AN105: =AM105+IFERROR(SUM($AN$79:$AN$84)*AM105/$AM$88,0) -> 0 | AO105: =IFERROR($AN105/$T105,0) -> 0 | AS105: X | AT105: =IF(AS105="x",AM105+((SUM($AN$79:$AN$84)+SUMIF($AS$90:$AS$121,"<>x",$AM$90:$AM$121))*IFERROR(AM105/SUMIF($AS$90:$AS$121,"x",$AM$90:$AM$121),0)),0) -> 0 | AV105: =IFERROR(AT105/T105,0) -> 0 | AW105: =IFERROR(AV105/BusinessCurrencyTRM,"N/A") -> N/A
H106: 0 | I106: 0 | J106: =IFERROR(G106/(1-(H106+I106)),0) -> 0 | S106: =IF(ISBLANK(P106),0,$O$82*20) -> 0 | T106: =IF(ISBLANK($P106),0,IF(Approach="Team-Based",$Q106*$R106*$S106*HoursPerDayTeamBased,$J106)) -> 0 | U106: 0 | V106: =ROUNDUP(IFERROR(INDEX(CostRateTbl[Cost Rate],MATCH(_xlfn.CONCAT(N106,O106,P106,"NA"),CostRateTbl[KeyCostRate],0)),0)*BillingCurrencyTRM*(1+U106),2) -> 0 | W106: =T106*V106 -> 0 | X106: {=_xlfn.LET( _xlpm.valor, INDEX(CostRate!H:H, MATCH(1, (CostRate!A:A=N106)*1, 0)), _xlpm.posicion, MATCH(_xlpm.valor, FilterSL!$F$1:$Z$1, 0), _xlpm.direccionCompleta, ADDRESS(1, _xlpm.posicion + 5, 4), _xlpm.letraColumna, SUBSTITUTE(_xlpm.direccionCompleta, "1", ""), _xlpm.letraColumna )} -> #N/A | Y106: {=_xlfn.LET( _xlpm.valor, INDEX(CostRate!I:I, MATCH(1, (CostRate!A:A=N106)*(CostRate!B:B=O106), 0)), _xlpm.posicion, MATCH(_xlpm.valor, FilterJP!$E$1:$FZ$1, 0), _xlpm.direccionCompleta, ADDRESS(1, _xlpm.posicion + 4, 4), _xlpm.letraColumna, SUBSTITUTE(_xlpm.direccionCompleta, "1", ""), _xlpm.letraColumna )} -> #N/A | AC106: =ROUNDUP($V106/(1-$AV$76),2) -> 0 | AD106: =$T106*$AC106 -> 0 | AE106: =IFERROR(1-($W106/$AD106),0) -> 0 | AG106: =IFERROR(IF(OR(ISBLANK(N106),N106=CustomerCountry,COUNTIF($N106,"*xDC*")),0,10%),0) -> 0 | AH106: =W106*AG106 -> 0 | AJ106: {=IFERROR(INDEX(WHT!$C$7:$W$18,MATCH( _xlfn.SWITCH(N106,"xDC Medellin","Colombia","xDC Belo Horizonte","Brazil","xDC Guadalajara","Mexico","xDC Gurugram","India","xDC Leon","Spain","xDC San Jose","Costa Rica","xDC Warsaw","Poland",N106), WHT!$B$7:$B$18,0),MATCH(CustomerCountry,WHT!$C$5:$W$5,0)),0)} -> 0 | AK106: =(W106+AH106)*AJ106 -> 0 | AM106: =SUM($AD106,$AH106,$AK106) -> 0 | AN106: =AM106+IFERROR(SUM($AN$79:$AN$84)*AM106/$AM$88,0) -> 0 | AO106: =IFERROR($AN106/$T106,0) -> 0 | AS106: X | AT106: =IF(AS106="x",AM106+((SUM($AN$79:$AN$84)+SUMIF($AS$90:$AS$121,"<>x",$AM$90:$AM$121))*IFERROR(AM106/SUMIF($AS$90:$AS$121,"x",$AM$90:$AM$121),0)),0) -> 0 | AV106: =IFERROR(AT106/T106,0) -> 0 | AW106: =IFERROR(AV106/BusinessCurrencyTRM,"N/A") -> N/A
H107: 0 | I107: 0 | J107: =IFERROR(G107/(1-(H107+I107)),0) -> 0 | S107: =IF(ISBLANK(P107),0,$O$82*20) -> 0 | T107: =IF(ISBLANK($P107),0,IF(Approach="Team-Based",$Q107*$R107*$S107*HoursPerDayTeamBased,$J107)) -> 0 | U107: 0 | V107: =ROUNDUP(IFERROR(INDEX(CostRateTbl[Cost Rate],MATCH(_xlfn.CONCAT(N107,O107,P107,"NA"),CostRateTbl[KeyCostRate],0)),0)*BillingCurrencyTRM*(1+U107),2) -> 0 | W107: =T107*V107 -> 0 | X107: {=_xlfn.LET( _xlpm.valor, INDEX(CostRate!H:H, MATCH(1, (CostRate!A:A=N107)*1, 0)), _xlpm.posicion, MATCH(_xlpm.valor, FilterSL!$F$1:$Z$1, 0), _xlpm.direccionCompleta, ADDRESS(1, _xlpm.posicion + 5, 4), _xlpm.letraColumna, SUBSTITUTE(_xlpm.direccionCompleta, "1", ""), _xlpm.letraColumna )} -> #N/A | Y107: {=_xlfn.LET( _xlpm.valor, INDEX(CostRate!I:I, MATCH(1, (CostRate!A:A=N107)*(CostRate!B:B=O107), 0)), _xlpm.posicion, MATCH(_xlpm.valor, FilterJP!$E$1:$FZ$1, 0), _xlpm.direccionCompleta, ADDRESS(1, _xlpm.posicion + 4, 4), _xlpm.letraColumna, SUBSTITUTE(_xlpm.direccionCompleta, "1", ""), _xlpm.letraColumna )} -> #N/A | AC107: =ROUNDUP($V107/(1-$AV$76),2) -> 0 | AD107: =$T107*$AC107 -> 0 | AE107: =IFERROR(1-($W107/$AD107),0) -> 0 | AG107: =IFERROR(IF(OR(ISBLANK(N107),N107=CustomerCountry,COUNTIF($N107,"*xDC*")),0,10%),0) -> 0 | AH107: =W107*AG107 -> 0 | AJ107: {=IFERROR(INDEX(WHT!$C$7:$W$18,MATCH( _xlfn.SWITCH(N107,"xDC Medellin","Colombia","xDC Belo Horizonte","Brazil","xDC Guadalajara","Mexico","xDC Gurugram","India","xDC Leon","Spain","xDC San Jose","Costa Rica","xDC Warsaw","Poland",N107), WHT!$B$7:$B$18,0),MATCH(CustomerCountry,WHT!$C$5:$W$5,0)),0)} -> 0 | AK107: =(W107+AH107)*AJ107 -> 0 | AM107: =SUM($AD107,$AH107,$AK107) -> 0 | AN107: =AM107+IFERROR(SUM($AN$79:$AN$84)*AM107/$AM$88,0) -> 0 | AO107: =IFERROR($AN107/$T107,0) -> 0 | AS107: X | AT107: =IF(AS107="x",AM107+((SUM($AN$79:$AN$84)+SUMIF($AS$90:$AS$121,"<>x",$AM$90:$AM$121))*IFERROR(AM107/SUMIF($AS$90:$AS$121,"x",$AM$90:$AM$121),0)),0) -> 0 | AV107: =IFERROR(AT107/T107,0) -> 0 | AW107: =IFERROR(AV107/BusinessCurrencyTRM,"N/A") -> N/A
H108: 0 | I108: 0 | J108: =IFERROR(G108/(1-(H108+I108)),0) -> 0 | S108: =IF(ISBLANK(P108),0,$O$82*20) -> 0 | T108: =IF(ISBLANK($P108),0,IF(Approach="Team-Based",$Q108*$R108*$S108*HoursPerDayTeamBased,$J108)) -> 0 | U108: 0 | V108: =ROUNDUP(IFERROR(INDEX(CostRateTbl[Cost Rate],MATCH(_xlfn.CONCAT(N108,O108,P108,"NA"),CostRateTbl[KeyCostRate],0)),0)*BillingCurrencyTRM*(1+U108),2) -> 0 | W108: =T108*V108 -> 0 | X108: {=_xlfn.LET( _xlpm.valor, INDEX(CostRate!H:H, MATCH(1, (CostRate!A:A=N108)*1, 0)), _xlpm.posicion, MATCH(_xlpm.valor, FilterSL!$F$1:$Z$1, 0), _xlpm.direccionCompleta, ADDRESS(1, _xlpm.posicion + 5, 4), _xlpm.letraColumna, SUBSTITUTE(_xlpm.direccionCompleta, "1", ""), _xlpm.letraColumna )} -> #N/A | Y108: {=_xlfn.LET( _xlpm.valor, INDEX(CostRate!I:I, MATCH(1, (CostRate!A:A=N108)*(CostRate!B:B=O108), 0)), _xlpm.posicion, MATCH(_xlpm.valor, FilterJP!$E$1:$FZ$1, 0), _xlpm.direccionCompleta, ADDRESS(1, _xlpm.posicion + 4, 4), _xlpm.letraColumna, SUBSTITUTE(_xlpm.direccionCompleta, "1", ""), _xlpm.letraColumna )} -> #N/A | AC108: =ROUNDUP($V108/(1-$AV$76),2) -> 0 | AD108: =$T108*$AC108 -> 0 | AE108: =IFERROR(1-($W108/$AD108),0) -> 0 | AG108: =IFERROR(IF(OR(ISBLANK(N108),N108=CustomerCountry,COUNTIF($N108,"*xDC*")),0,10%),0) -> 0 | AH108: =W108*AG108 -> 0 | AJ108: {=IFERROR(INDEX(WHT!$C$7:$W$18,MATCH( _xlfn.SWITCH(N108,"xDC Medellin","Colombia","xDC Belo Horizonte","Brazil","xDC Guadalajara","Mexico","xDC Gurugram","India","xDC Leon","Spain","xDC San Jose","Costa Rica","xDC Warsaw","Poland",N108), WHT!$B$7:$B$18,0),MATCH(CustomerCountry,WHT!$C$5:$W$5,0)),0)} -> 0 | AK108: =(W108+AH108)*AJ108 -> 0 | AM108: =SUM($AD108,$AH108,$AK108) -> 0 | AN108: =AM108+IFERROR(SUM($AN$79:$AN$84)*AM108/$AM$88,0) -> 0 | AO108: =IFERROR($AN108/$T108,0) -> 0 | AS108: X | AT108: =IF(AS108="x",AM108+((SUM($AN$79:$AN$84)+SUMIF($AS$90:$AS$121,"<>x",$AM$90:$AM$121))*IFERROR(AM108/SUMIF($AS$90:$AS$121,"x",$AM$90:$AM$121),0)),0) -> 0 | AV108: =IFERROR(AT108/T108,0) -> 0 | AW108: =IFERROR(AV108/BusinessCurrencyTRM,"N/A") -> N/A
... H111: 0 | I111: 0 | J111: =IFERROR(G111/(1-(H111+I111)),0) -> 0 | S111: =IF(ISBLANK(P111),0,$O$82*20) -> 0 | T111: =IF(ISBLANK($P111),0,IF(Approach="Team-Based",$Q111*$R111*$S111*HoursPerDayTeamBased,$J111)) -> 0 | U111: 0 | V111: =ROUNDUP(IFERROR(INDEX(CostRateTbl[Cost Rate],MATCH(_xlfn.CONCAT(N111,O111,P111,"NA"),CostRateTbl[KeyCostRate],0)),0)*BillingCurrencyTRM*(1+U111),2) -> 0 | W111: =T111*V111 -> 0 | X111: {=_xlfn.LET( _xlpm.valor, INDEX(CostRate!H:H, MATCH(1, (CostRate!A:A=N111)*1, 0)), _xlpm.posicion, MATCH(_xlpm.valor, FilterSL!$F$1:$Z$1, 0), _xlpm.direccionCompleta, ADDRESS(1, _xlpm.posicion + 5, 4), _xlpm.letraColumna, SUBSTITUTE(_xlpm.direccionCompleta, "1", ""), _xlpm.letraColumna )} -> #N/A | Y111: {=_xlfn.LET( _xlpm.valor, INDEX(CostRate!I:I, MATCH(1, (CostRate!A:A=N111)*(CostRate!B:B=O111), 0)), _xlpm.posicion, MATCH(_xlpm.valor, FilterJP!$E$1:$FZ$1, 0), _xlpm.direccionCompleta, ADDRESS(1, _xlpm.posicion + 4, 4), _xlpm.letraColumna, SUBSTITUTE(_xlpm.direccionCompleta, "1", ""), _xlpm.letraColumna )} -> #N/A | AC111: =ROUNDUP($V111/(1-$AV$76),2) -> 0 | AD111: =$T111*$AC111 -> 0 | AE111: =IFERROR(1-($W111/$AD111),0) -> 0 | AG111: =IFERROR(IF(OR(ISBLANK(N111),N111=CustomerCountry,COUNTIF($N111,"*xDC*")),0,10%),0) -> 0 | AH111: =W111*AG111 -> 0 | AJ111: {=IFERROR(INDEX(WHT!$C$7:$W$18,MATCH( _xlfn.SWITCH(N111,"xDC Medellin","Colombia","xDC Belo Horizonte","Brazil","xDC Guadalajara","Mexico","xDC Gurugram","India","xDC Leon","Spain","xDC San Jose","Costa Rica","xDC Warsaw","Poland",N111), WHT!$B$7:$B$18,0),MATCH(CustomerCountry,WHT!$C$5:$W$5,0)),0)} -> 0 | AK111: =(W111+AH111)*AJ111 -> 0 | AM111: =SUM($AD111,$AH111,$AK111) -> 0 | AN111: =AM111+IFERROR(SUM($AN$79:$AN$84)*AM111/$AM$88,0) -> 0 | AO111: =IFERROR($AN111/$T111,0) -> 0 | AS111: X | AT111: =IF(AS111="x",AM111+((SUM($AN$79:$AN$84)+SUMIF($AS$90:$AS$121,"<>x",$AM$90:$AM$121))*IFERROR(AM111/SUMIF($AS$90:$AS$121,"x",$AM$90:$AM$121),0)),0) -> 0 | AV111: =IFERROR(AT111/T111,0) -> 0 | AW111: =IFERROR(AV111/BusinessCurrencyTRM,"N/A") -> N/A
H112: 0 | I112: 0 | J112: =IFERROR(G112/(1-(H112+I112)),0) -> 0
H113: 0 | I113: 0 | J113: =IFERROR(G113/(1-(H113+I113)),0) -> 0
H114: 0 | I114: 0 | J114: =IFERROR(G114/(1-(H114+I114)),0) -> 0
H115: 0 | I115: 0 | J115: =IFERROR(G115/(1-(H115+I115)),0) -> 0
...

Sheet CMSCore 2.8
A1: Scope | N1: Delivery Cost - Internal Use | AC1: Price - Internal Use | AT1: Año 1 Ingreso Mensual | BA1: Año 2 Ingreso Mensual | BH1: Año 3 Ingreso Mensual | BO1: Año 4 Ingreso Mensual | BV1: Año 5 Ingreso Mensual
B2: Fields with * are mandatory for both DealReview and HandOff; ** denotes HandOff-only requirements | N2: Fields with * are mandatory for both DealReview and HandOff; ** denotes HandOff-only requirements
B3: Customer Country * | C3: Colombia | N3: Approach * | O3: Team-Based | U3: HOURS | V3: =_xlfn.CONCAT("DELIVERY COST (",BillingCountryCurrency,")") -> DELIVERY COST (COP) | W3: =_xlfn.CONCAT("DELIVERY COST (",IF(ISBLANK(BusinessCurrency),"N/A",BusinessCurrency),")") -> DELIVERY COST (USD) | AD3: =_xlfn.CONCAT("PRICING (",BillingCountryCurrency,")") -> PRICING (COP) | AE3: =_xlfn.CONCAT("PRICING (",IF(ISBLANK(BusinessCurrency),"N/A",BusinessCurrency),")") -> PRICING (USD) | AF3: + | AG3: =_xlfn.CONCAT("Intercompany (",BillingCountryCurrency,")") -> Intercompany (COP) | AH3: =_xlfn.CONCAT("Intercompany (",IF(ISBLANK(BusinessCurrency),"N/A",BusinessCurrency),")") -> Intercompany (USD) | AI3: + | AJ3: =_xlfn.CONCAT("WHT (",BillingCountryCurrency,")") -> WHT (COP) | AK3: =_xlfn.CONCAT("WHT (",IF(ISBLANK(BusinessCurrency),"N/A",BusinessCurrency),")") -> WHT (USD) | AM3: = | AN3: =_xlfn.CONCAT("BUSINESS VOLUME (",BillingCountryCurrency,")") -> BUSINESS VOLUME (COP) | AO3: =_xlfn.CONCAT("BUSINESS VOLUME (",IF(ISBLANK(BusinessCurrency),"N/A",BusinessCurrency),")") -> BUSINESS VOLUME (USD) | AS3: MILESTONES | AV3: =BillingCountryCurrency -> COP | AW3: =IF(ISBLANK(BusinessCurrency),"N/A",BusinessCurrency) -> USD | BA3: MILESTONES | BC3: =BillingCountryCurrency -> COP | BD3: =IF(ISBLANK(BusinessCurrency),"N/A",BusinessCurrency) -> USD | BH3: MILESTONES | BJ3: =BillingCountryCurrency -> COP | BK3: =IF(ISBLANK(BusinessCurrency),"N/A",BusinessCurrency) -> USD | BO3: MILESTONES | BQ3: =BillingCountryCurrency -> COP | BR3: =IF(ISBLANK(BusinessCurrency),"N/A",BusinessCurrency) -> USD | BV3: MILESTONES | BX3: =BillingCountryCurrency -> COP | BY3: =IF(ISBLANK(BusinessCurrency),"N/A",BusinessCurrency) -> USD
B4: Customer Name * | N4: =IF(Approach="By Hours", "N/A for ByHours", "Hours/Day") -> Hours/Day | O4: 8.1 | T4: SERVICE COSTS | AC4: SERVICE PRICE | AS4: Hito 1 | AU4: 0 | AV4: 0 | AW4: =IFERROR(AV4/BusinessCurrencyTRM,"N/A") -> 0 | BA4: Hito 1 | BB4: 0 | BC4: 0 | BD4: =IFERROR(BC4/BusinessCurrencyTRM,"N/A") -> 0 | BH4: Hito 1 | BI4: 0 | BJ4: 0 | BK4: =IFERROR(BJ4/BusinessCurrencyTRM,"N/A") -> 0 | BO4: Hito 1 | BP4: 0 | BQ4: 0 | BR4: =IFERROR(BQ4/BusinessCurrencyTRM,"N/A") -> 0 | BV4: Hito 1 | BW4: 0 | BX4: 0 | BY4: =IFERROR(BX4/BusinessCurrencyTRM,"N/A") -> 0
B5: Project Name * | T5: Consultant Team | U5: =IFERROR(SUMIFS(O:O,Y:Y,"varTotalConsultant"),0) -> 157.36583 | V5: =IFERROR(SUMIFS(V:V,Y:Y,"varTotalConsultant"),0) -> 6327455.9 | W5: =IFERROR(V5/BusinessCurrencyTRM,"N/A") -> 1622.4246 | AC5: Consultant Team | AD5: =IFERROR(SUMIF(Y:Y,"varTotalConsultant",AD:AD),0) -> 9039222.9 | AE5: =IFERROR(AD5/BusinessCurrencyTRM,"N/A") -> 2317.7495 | AG5: =IFERROR(SUMIF(Y:Y,"varTotalConsultant",AG:AG),0) -> 0 | AH5: =IFERROR(AG5/BusinessCurrencyTRM,"N/A") -> 0 | AJ5: =IFERROR(SUMIF(Y:Y,"varTotalConsultant",AJ:AJ),0) -> 0 | AK5: =IFERROR(AJ5/BusinessCurrencyTRM,"N/A") -> 0 | AN5: =SUM(AD5,AG5,AJ5) -> 9039222.9 | AO5: =IFERROR(AN5/BusinessCurrencyTRM,"N/A") -> 2317.7495 | AS5: Hito 2 | AU5: 0 | AV5: 0 | AW5: =IFERROR(AV5/BusinessCurrencyTRM,"N/A") -> 0 | BA5: Hito 2 | BB5: 0 | BC5: 0 | BD5: =IFERROR(BC5/BusinessCurrencyTRM,"N/A") -> 0 | BH5: Hito 2 | BI5: 0 | BJ5: 0 | BK5: =IFERROR(BJ5/BusinessCurrencyTRM,"N/A") -> 0 | BO5: Hito 2 | BP5: 0 | BQ5: 0 | BR5: =IFERROR(BQ5/BusinessCurrencyTRM,"N/A") -> 0 | BV5: Hito 2 | BW5: 0 | BX5: 0 | BY5: =IFERROR(BX5/BusinessCurrencyTRM,"N/A") -> 0
B6: Opp ID * | N6: Account Manager * | T6: Project Managment | U6: =IFERROR(SUMIFS(O:O,Y:Y,"varTotalPM"),0) -> 34.02 | V6: =IFERROR(SUMIFS(V:V,Y:Y,"varTotalPM"),0) -> 0 | W6: =IFERROR(V6/BusinessCurrencyTRM,"N/A") -> 0 | AC6: Project Managment | AD6: =IFERROR(SUMIF(Y:Y,"varTotalPM",AD:AD),0) -> 0 | AE6: =IFERROR(AD6/BusinessCurrencyTRM,"N/A") -> 0 | AG6: =IFERROR(SUMIF(Y:Y,"varTotalPM",AG:AG),0) -> 0 | AH6: =IFERROR(AG6/BusinessCurrencyTRM,"N/A") -> 0 | AJ6: =IFERROR(SUMIF(Y:Y,"varTotalPM",AJ:AJ),0) -> 0 | AK6: =IFERROR(AJ6/BusinessCurrencyTRM,"N/A") -> 0 | AN6: =SUM(AD6,AG6,AJ6) -> 0 | AO6: =IFERROR(AN6/BusinessCurrencyTRM,"N/A") -> 0 | AS6: Hito 3 | AU6: 0 | AV6: 0 | AW6: =IFERROR(AV6/BusinessCurrencyTRM,"N/A") -> 0 | BA6: Hito 3 | BB6: 0 | BC6: 0 | BD6: =IFERROR(BC6/BusinessCurrencyTRM,"N/A") -> 0 | BH6: Hito 3 | BI6: 0 | BJ6: 0 | BK6: =IFERROR(BJ6/BusinessCurrencyTRM,"N/A") -> 0 | BO6: Hito 3 | BP6: 0 | BQ6: 0 | BR6: =IFERROR(BQ6/BusinessCurrencyTRM,"N/A") -> 0 | BV6: Hito 3 | BW6: 0 | BX6: 0 | BY6: =IFERROR(BX6/BusinessCurrencyTRM,"N/A") -> 0
B7: SWO Job ID / PRJ | N7: Pre-sale in Sale * | T7: Subtotal | U7: =IFERROR(SUM(U5:U6),0) -> 191.38583 | V7: =IFERROR(SUM($V$5:$V$6),0) -> 6327455.9 | W7: =IFERROR(V7/BusinessCurrencyTRM,"N/A") -> 1622.4246 | AC7: Subtotal | AD7: =IFERROR(SUM(AD5:AD6),0) -> 9039222.9 | AE7: =IFERROR(AD7/BusinessCurrencyTRM,"N/A") -> 2317.7495 | AG7: =IFERROR(SUM(AG5:AG6),0) -> 0 | AH7: =IFERROR(AG7/BusinessCurrencyTRM,"N/A") -> 0 | AJ7: =IFERROR(SUM(AJ5:AJ6),0) -> 0 | AK7: =IFERROR(AJ7/BusinessCurrencyTRM,"N/A") -> 0 | AN7: =IFERROR(SUM(AN5:AN6),0) -> 9039222.9 | AO7: =IFERROR(AN7/BusinessCurrencyTRM,"N/A") -> 2317.7495 | AS7: Hito 4 | AU7: 0 | AV7: 0 | AW7: =IFERROR(AV7/BusinessCurrencyTRM,"N/A") -> 0 | BA7: Hito 4 | BB7: 0 | BC7: 0 | BD7: =IFERROR(BC7/BusinessCurrencyTRM,"N/A") -> 0 | BH7: Hito 4 | BI7: 0 | BJ7: 0 | BK7: =IFERROR(BJ7/BusinessCurrencyTRM,"N/A") -> 0 | BO7: Hito 4 | BP7: 0 | BQ7: 0 | BR7: =IFERROR(BQ7/BusinessCurrencyTRM,"N/A") -> 0 | BV7: Hito 4 | BW7: 0 | BX7: 0 | BY7: =IFERROR(BX7/BusinessCurrencyTRM,"N/A") -> 0
B8: Main Business Line * | C8: Cloud Services Azure | N8: Pre-sale in Delivery * | AS8: Hito 5 | AU8: 0 | AV8: 0 | AW8: =IFERROR(AV8/BusinessCurrencyTRM,"N/A") -> 0 | BA8: Hito 5 | BB8: 0 | BC8: 0 | BD8: =IFERROR(BC8/BusinessCurrencyTRM,"N/A") -> 0 | BH8: Hito 5 | BI8: 0 | BJ8: 0 | BK8: =IFERROR(BJ8/BusinessCurrencyTRM,"N/A") -> 0 | BO8: Hito 5 | BP8: 0 | BQ8: 0 | BR8: =IFERROR(BQ8/BusinessCurrencyTRM,"N/A") -> 0 | BV8: Hito 5 | BW8: 0 | BX8: 0 | BY8: =IFERROR(BX8/BusinessCurrencyTRM,"N/A") -> 0
B9: Funding * | C9: Customer | T9: OTHER COSTS | AC9: OTHER PRICES | AS9: Hito 6 | AU9: 0 | AV9: 0 | AW9: =IFERROR(AV9/BusinessCurrencyTRM,"N/A") -> 0 | BA9: Hito 6 | BB9: 0 | BC9: 0 | BD9: =IFERROR(BC9/BusinessCurrencyTRM,"N/A") -> 0 | BH9: Hito 6 | BI9: 0 | BJ9: 0 | BK9: =IFERROR(BJ9/BusinessCurrencyTRM,"N/A") -> 0 | BO9: Hito 6 | BP9: 0 | BQ9: 0 | BR9: =IFERROR(BQ9/BusinessCurrencyTRM,"N/A") -> 0 | BV9: Hito 6 | BW9: 0 | BX9: 0 | BY9: =IFERROR(BX9/BusinessCurrencyTRM,"N/A") -> 0
B10: OPP Type * | C10: New | N10: Billing Country * | O10: =CustomerCountry -> Colombia | T10: Risks | V10: =IFERROR(SUMIF(Y:Y,"varTotalRisks",V:V),0) -> 0 | W10: =IFERROR(V10/BusinessCurrencyTRM,"N/A") -> 0 | AC10: Risks | AD10: =IFERROR(SUMIF(Y:Y,"varTotalRisks",AD:AD),0) -> 0 | AE10: =IFERROR(AD10/BusinessCurrencyTRM,"N/A") -> 0 | AG10: =IFERROR(SUMIF(Y:Y,"varTotalRisks",AG:AG),0) -> 0 | AH10: =IFERROR(AG10/BusinessCurrencyTRM,"N/A") -> 0 | AJ10: =IFERROR(SUMIF(Y:Y,"varTotalRisks",AJ:AJ),0) -> 0 | AK10: =IFERROR(AJ10/BusinessCurrencyTRM,"N/A") -> 0 | AN10: =SUM(AD10,AG10,AJ10) -> 0 | AO10: =IFERROR(AN10/BusinessCurrencyTRM,"N/A") -> 0 | AS10: Hito 7 | AU10: 0 | AV10: 0 | AW10: =IFERROR(AV10/BusinessCurrencyTRM,"N/A") -> 0 | BA10: Hito 7 | BB10: 0 | BC10: 0 | BD10: =IFERROR(BC10/BusinessCurrencyTRM,"N/A") -> 0 | BH10: Hito 7 | BI10: 0 | BJ10: 0 | BK10: =IFERROR(BJ10/BusinessCurrencyTRM,"N/A") -> 0 | BO10: Hito 7 | BP10: 0 | BQ10: 0 | BR10: =IFERROR(BQ10/BusinessCurrencyTRM,"N/A") -> 0 | BV10: Hito 7 | BW10: 0 | BX10: 0 | BY10: =IFERROR(BX10/BusinessCurrencyTRM,"N/A") -> 0
N11: Billing Country Currency * | O11: =INDEX(Paramenters!$C$28:$C$85,MATCH(BillingCountry,Paramenters!$A$28:$A$85,0)) -> COP | T11: Pay Rise | V11: =IFERROR(SUMIF(Y:Y,"varTotalPayRise",V:V),0) -> 0 | W11: =IFERROR(V11/BusinessCurrencyTRM,"N/A") -> 0 | AC11: Salary Increase | AD11: =IFERROR(SUMIF(Y:Y,"varTotalPayRise",AD:AD),0) -> 0 | AE11: =IFERROR(AD11/BusinessCurrencyTRM,"N/A") -> 0 | AG11: =IFERROR(SUMIF(Y:Y,"varTotalPayRise",AG:AG),0) -> 0 | AH11: =IFERROR(AG11/BusinessCurrencyTRM,"N/A") -> 0 | AJ11: =IFERROR(SUMIF(Y:Y,"varTotalPayRise",AJ:AJ),0) -> 0 | AK11: =IFERROR(AJ11/BusinessCurrencyTRM,"N/A") -> 0 | AN11: =SUM(AD11,AG11,AJ11) -> 0 | AO11: =IFERROR(AN11/BusinessCurrencyTRM,"N/A") -> 0 | AS11: Hito 8 | AU11: 0 | AV11: 0 | AW11: =IFERROR(AV11/BusinessCurrencyTRM,"N/A") -> 0 | BA11: Hito 8 | BB11: 0 | BC11: 0 | BD11: =IFERROR(BC11/BusinessCurrencyTRM,"N/A") -> 0 | BH11: Hito 8 | BI11: 0 | BJ11: 0 | BK11: =IFERROR(BJ11/BusinessCurrencyTRM,"N/A") -> 0 | BO11: Hito 8 | BP11: 0 | BQ11: 0 | BR11: =IFERROR(BQ11/BusinessCurrencyTRM,"N/A") -> 0 | BV11: Hito 8 | BW11: 0 | BX11: 0 | BY11: =IFERROR(BX11/BusinessCurrencyTRM,"N/A") -> 0
B12: SKUs Business Line SWO * | C12: SKUs OneSales Descripcion * | T12: Products | V12: =IFERROR(SUMIF(Y:Y,"varTotalProducts",V:V),0) -> 0 | W12: =IFERROR(V12/BusinessCurrencyTRM,"N/A") -> 0 | AC12: Products | AD12: =IFERROR(SUMIF(Y:Y,"varTotalProducts",AD:AD),0) -> 0 | AE12: =IFERROR(AD12/BusinessCurrencyTRM,"N/A") -> 0 | AG12: =IFERROR(SUMIF(Y:Y,"varTotalProducts",AG:AG),0) -> 0 | AH12: =IFERROR(AG12/BusinessCurrencyTRM,"N/A") -> 0 | AJ12: =IFERROR(SUMIF(Y:Y,"varTotalProducts",AJ:AJ),0) -> 0 | AK12: =IFERROR(AJ12/BusinessCurrencyTRM,"N/A") -> 0 | AN12: =SUM(AD12,AG12,AJ12) -> 0 | AO12: =IFERROR(AN12/BusinessCurrencyTRM,"N/A") -> 0 | AS12: Hito 9 | AU12: 0 | AV12: 0 | AW12: =IFERROR(AV12/BusinessCurrencyTRM,"N/A") -> 0 | BA12: Hito 9 | BB12: 0 | BC12: 0 | BD12: =IFERROR(BC12/BusinessCurrencyTRM,"N/A") -> 0 | BH12: Hito 9 | BI12: 0 | BJ12: 0 | BK12: =IFERROR(BJ12/BusinessCurrencyTRM,"N/A") -> 0 | BO12: Hito 9 | BP12: 0 | BQ12: 0 | BR12: =IFERROR(BQ12/BusinessCurrencyTRM,"N/A") -> 0 | BV12: Hito 9 | BW12: 0 | BX12: 0 | BY12: =IFERROR(BX12/BusinessCurrencyTRM,"N/A") -> 0
N13: Business Currency | O13: USD | T13: Vendors | V13: =IFERROR(SUMIF(Y:Y,"varTotalVAR",V:V),0) -> 0 | W13: =IFERROR(V13/BusinessCurrencyTRM,"N/A") -> 0 | AC13: Vendors | AD13: =IFERROR(SUMIF(Y:Y,"varTotalVAR",AD:AD),0) -> 0 | AE13: =IFERROR(AD13/BusinessCurrencyTRM,"N/A") -> 0 | AG13: =IFERROR(SUMIF(Y:Y,"varTotalVAR",AG:AG),0) -> 0 | AH13: =IFERROR(AG13/BusinessCurrencyTRM,"N/A") -> 0 | AJ13: =IFERROR(SUMIF(Y:Y,"varTotalVAR",AJ:AJ),0) -> 0 | AK13: =IFERROR(AJ13/BusinessCurrencyTRM,"N/A") -> 0 | AN13: =SUM(AD13,AG13,AJ13) -> 0 | AO13: =IFERROR(AN13/BusinessCurrencyTRM,"N/A") -> 0 | AS13: Hito 10 | AU13: 0 | AV13: 0 | AW13: =IFERROR(AV13/BusinessCurrencyTRM,"N/A") -> 0 | BA13: Hito 10 | BB13: 0 | BC13: 0 | BD13: =IFERROR(BC13/BusinessCurrencyTRM,"N/A") -> 0 | BH13: Hito 10 | BI13: 0 | BJ13: 0 | BK13: =IFERROR(BJ13/BusinessCurrencyTRM,"N/A") -> 0 | BO13: Hito 10 | BP13: 0 | BQ13: 0 | BR13: =IFERROR(BQ13/BusinessCurrencyTRM,"N/A") -> 0 | BV13: Hito 10 | BW13: 0 | BX13: 0 | BY13: =IFERROR(BX13/BusinessCurrencyTRM,"N/A") -> 0
N14: Currency Exchange Rate | O14: 3900 | T14: Insurances | V14: =IFERROR(SUMIF(Y:Y,"varTotalInsurances",V:V),0) -> 0 | W14: =IFERROR(V14/BusinessCurrencyTRM,"N/A") -> 0 | AC14: Insurances | AD14: =IFERROR(SUMIF(Y:Y,"varTotalInsurances",AD:AD),0) -> 0 | AE14: =IFERROR(AD14/BusinessCurrencyTRM,"N/A") -> 0 | AG14: =IFERROR(SUMIF(Y:Y,"varTotalInsurances",AG:AG),0) -> 0 | AH14: =IFERROR(AG14/BusinessCurrencyTRM,"N/A") -> 0 | AJ14: =IFERROR(SUMIF(Y:Y,"varTotalInsurances",AJ:AJ),0) -> 0 | AK14: =IFERROR(AJ14/BusinessCurrencyTRM,"N/A") -> 0 | AN14: =SUM(AD14,AG14,AJ14) -> 0 | AO14: =IFERROR(AN14/BusinessCurrencyTRM,"N/A") -> 0 | AS14: Hito 11 | AU14: 0 | AV14: 0 | AW14: =IFERROR(AV14/BusinessCurrencyTRM,"N/A") -> 0 | BA14: Hito 11 | BB14: 0 | BC14: 0 | BD14: =IFERROR(BC14/BusinessCurrencyTRM,"N/A") -> 0 | BH14: Hito 11 | BI14: 0 | BJ14: 0 | BK14: =IFERROR(BJ14/BusinessCurrencyTRM,"N/A") -> 0 | BO14: Hito 11 | BP14: 0 | BQ14: 0 | BR14: =IFERROR(BQ14/BusinessCurrencyTRM,"N/A") -> 0 | BV14: Hito 11 | BW14: 0 | BX14: 0 | BY14: =IFERROR(BX14/BusinessCurrencyTRM,"N/A") -> 0
N15: Exchange Rate Request Date | O15: 45909 | T15: Others | V15: =IFERROR(SUMIF(Y:Y,"varTotalOthers",V:V),0) -> 0 | W15: =IFERROR(V15/BusinessCurrencyTRM,"N/A") -> 0 | AC15: Others | AD15: =IFERROR(SUMIF(Y:Y,"varTotalOthers",AD:AD),0) -> 0 | AE15: =IFERROR(AD15/BusinessCurrencyTRM,"N/A") -> 0 | AG15: =IFERROR(SUMIF(Y:Y,"varTotalOthers",AG:AG),0) -> 0 | AH15: =IFERROR(AG15/BusinessCurrencyTRM,"N/A") -> 0 | AJ15: =IFERROR(SUMIF(Y:Y,"varTotalOthers",AJ:AJ),0) -> 0 | AK15: =IFERROR(AJ15/BusinessCurrencyTRM,"N/A") -> 0 | AN15: =SUM(AD15,AG15,AJ15) -> 0 | AO15: =IFERROR(AN15/BusinessCurrencyTRM,"N/A") -> 0 | AS15: Hito 12 | AU15: 0 | AV15: 0 | AW15: =IFERROR(AV15/BusinessCurrencyTRM,"N/A") -> 0 | BA15: Hito 12 | BB15: 0 | BC15: 0 | BD15: =IFERROR(BC15/BusinessCurrencyTRM,"N/A") -> 0 | BH15: Hito 12 | BI15: 0 | BJ15: 0 | BK15: =IFERROR(BJ15/BusinessCurrencyTRM,"N/A") -> 0 | BO15: Hito 12 | BP15: 0 | BQ15: 0 | BR15: =IFERROR(BQ15/BusinessCurrencyTRM,"N/A") -> 0 | BV15: Hito 12 | BW15: 0 | BX15: 0 | BY15: =IFERROR(BX15/BusinessCurrencyTRM,"N/A") -> 0
O16: * Request the official TRM/RMR from the financial area and/or official url in each billing country. | T16: Subtotal | V16: =IFERROR(SUM(V10:V15),0) -> 0 | W16: =IFERROR(V16/BusinessCurrencyTRM,"N/A") -> 0 | AC16: Subtotal | AD16: =IFERROR(SUM(AD10:AD15),0) -> 0 | AE16: =IFERROR(AD16/BusinessCurrencyTRM,"N/A") -> 0 | AG16: =IFERROR(SUM(AG10:AG15),0) -> 0 | AH16: =IFERROR(AG16/BusinessCurrencyTRM,"N/A") -> 0 | AJ16: =IFERROR(SUM(AJ10:AJ15),0) -> 0 | AK16: =IFERROR(AJ16/BusinessCurrencyTRM,"N/A") -> 0 | AN16: =IFERROR(SUM(AN10:AN15),0) -> 0 | AO16: =IFERROR(AN16/BusinessCurrencyTRM,"N/A") -> 0 | AU16: =SUM(AU4:AU15) -> 0 | AV16: =SUM(AV4:AV15) -> 0 | AW16: =SUM(AW4:AW15) -> 0 | BB16: =SUM(BB4:BB15) -> 0 | BC16: =SUM(BC4:BC15) -> 0 | BD16: =SUM(BD4:BD15) -> 0 | BI16: =SUM(BI4:BI15) -> 0 | BJ16: =SUM(BJ4:BJ15) -> 0 | BK16: =SUM(BK4:BK15) -> 0 | BP16: =SUM(BP4:BP15) -> 0 | BQ16: =SUM(BQ4:BQ15) -> 0 | BR16: =SUM(BR4:BR15) -> 0 | BW16: =SUM(BW4:BW15) -> 0 | BX16: =SUM(BX4:BX15) -> 0 | BY16: =SUM(BY4:BY15) -> 0
B17: Deal Comments
B18: [WRITE COMMENTS THAT WERE TAKEN INTO ACCOUNT IN THE MODELING] | AV18: =BillingCountryCurrency -> COP | AW18: =IF(ISBLANK(BusinessCurrency),"N/A",BusinessCurrency) -> USD
AC19: SUBTOTAL | AD19: =SUM(AD7,AD16) -> 9039222.9 | AE19: =IFERROR(AD19/BusinessCurrencyTRM,"N/A") -> 2317.7495 | AG19: =SUM(AG7,AG16) -> 0 | AH19: =IFERROR(AG19/BusinessCurrencyTRM,"N/A") -> 0 | AJ19: =SUM(AJ7,AJ16) -> 0 | AK19: =IFERROR(AJ19/BusinessCurrencyTRM,"N/A") -> 0 | AN19: =SUM(AN7,AN16) -> 9039222.9 | AO19: =IFERROR(AN19/BusinessCurrencyTRM,"N/A") -> 2317.7495 | AS19: BUSINESS PRICE | AV19: =AN21 -> 9039222.9 | AW19: =IFERROR(AV19/BusinessCurrencyTRM,"N/A") -> 2317.7495
AC20: ADDITIONAL GP | AD20: 0 | AE20: =IFERROR(AD20/BusinessCurrencyTRM,"N/A") -> 0 | AG20: 0 | AH20: =IFERROR(AG20/BusinessCurrencyTRM,"N/A") -> 0 | AJ20: 0 | AK20: =IFERROR(AJ20/BusinessCurrencyTRM,"N/A") -> 0 | AN20: =SUM(AD20,AG20,AJ20) -> 0 | AO20: =IFERROR(AN20/BusinessCurrencyTRM,"N/A") -> 0 | AS20: DELIVERY COST | AV20: =SUM($V$21,$AG$21,$AJ$21) -> 6327455.9 | AW20: =IFERROR(AV20/BusinessCurrencyTRM,"N/A") -> 1622.4246
N21: =IF(CustomerCountry="Colombia","Impuesto de Timbre","") -> Impuesto de Timbre | O21: =IF(CustomerCountry="Colombia","Aplica a nuevos contratos donde la cuantia supera los 6.000 UVT (COP 298.794.000)","") -> Aplica a nuevos contratos donde la cuantia supera los 6.000 UVT (COP 298.794.000) | T21: TOTAL COSTS | V21: =V7+V16 -> 6327455.9 | W21: =IFERROR(V21/BusinessCurrencyTRM,"N/A") -> 1622.4246 | X21: =INDEX(Paramenters!$D$28:$D$85,MATCH(BillingCountryCurrency,Paramenters!$C$28:$C$85,0)) -> 4919.6912 | Y21: BillingCurrencyTRM | AC21: TOTAL PRICE | AD21: =SUM(AD19:AD20) -> 9039222.9 | AE21: =IFERROR(AD21/BusinessCurrencyTRM,"N/A") -> 2317.7495 | AG21: =SUM(AG19:AG20) -> 0 | AH21: =IFERROR(AG21/BusinessCurrencyTRM,"N/A") -> 0 | AJ21: =SUM(AJ19:AJ20) -> 0 | AK21: =IFERROR(AJ21/BusinessCurrencyTRM,"N/A") -> 0 | AN21: =SUM(AN19:AN20) -> 9039222.9 | AO21: =IFERROR(AN21/BusinessCurrencyTRM,"N/A") -> 2317.7495 | AS21: % CONTRIBUTION MARGIN | AV21: =IFERROR(1-AV20/AV19,0) -> 0.30000001
B24: (Note 1) To add new phases/stages/blocks, it is recommended to use the phase/stage/block called "Phase_Name_7" which does not have fixed references and allows maintaining cell relationships.
B26: Equipo de Trabajo - Plantilla
N27: PROJECT WEIGHT BY PHASE | O27: Hours | P27: Percentage (%) | U27: COSTS BY PHASE | V27: =_xlfn.CONCAT("DELIVERY COST (",BillingCountryCurrency,")") -> DELIVERY COST (COP) | W27: =_xlfn.CONCAT("DELIVERY COST (",IF(ISBLANK(BusinessCurrency),"N/A",BusinessCurrency),")") -> DELIVERY COST (USD) | AC27: PRICE BY PHASE | AD27: =_xlfn.CONCAT("PRICING (",BillingCountryCurrency,")") -> PRICING (COP) | AE27: =_xlfn.CONCAT("PRICING (",IF(ISBLANK(BusinessCurrency),"N/A",BusinessCurrency),")") -> PRICING (USD) | AF27: + | AG27: =_xlfn.CONCAT("Intercompany (",BillingCountryCurrency,")") -> Intercompany (COP) | AH27: =_xlfn.CONCAT("Intercompany (",IF(ISBLANK(BusinessCurrency),"N/A",BusinessCurrency),")") -> Intercompany (USD) | AI27: + | AJ27: =_xlfn.CONCAT("WHT (",BillingCountryCurrency,")") -> WHT (COP) | AK27: =_xlfn.CONCAT("WHT (",IF(ISBLANK(BusinessCurrency),"N/A",BusinessCurrency),")") -> WHT (USD) | AM27: = | AN27: =_xlfn.CONCAT("SUBTOTAL PRICE (",BillingCountryCurrency,")") -> SUBTOTAL PRICE (COP) | AO27: =_xlfn.CONCAT("SUBTOTAL PRICE (",IF(ISBLANK(BusinessCurrency),"N/A",BusinessCurrency),")") -> SUBTOTAL PRICE (USD) | AS27: SUMMARY BY PHASE
N28: Consultant Team: | O28: =SUMIF($P42:$P71,"<>*Project Management*",$T42:$T71) -> 26.227638 | P28: =IFERROR(O28/O31,0) -> 0.82224389 | U28: Consultant Team | V28: =SUMIF(P42:P71,"<>*Project Management*",W42:W71) -> 1061346.2 | W28: =IFERROR(V28/BusinessCurrencyTRM,"N/A") -> 272.14005 | Y28: varTotalConsultant | AC28: Consultant Team | AD28: =SUMIF(P42:P71,"<>*Project Management*",AD42:AD71) -> 1516208.9 | AE28: =IFERROR(AD28/BusinessCurrencyTRM,"N/A") -> 388.7715 | AG28: =SUMIF(P42:P71,"<>*Project Management*",AH42:AH71) -> 0 | AH28: =IFERROR(AG28/BusinessCurrencyTRM,"N/A") -> 0 | AJ28: =SUMIF(P42:P71,"<>*Project Management*",AK42:AK71) -> 0 | AK28: =IFERROR(AJ28/BusinessCurrencyTRM,"N/A") -> 0 | AN28: =SUM(AD28,AG28,AJ28) -> 1516208.9 | AO28: =IFERROR(AN28/BusinessCurrencyTRM,"N/A") -> 388.7715 | AS28: % Margin a Sold * | AV28: =CMSResumen!H21 -> 0.3
N29: Project Managment: | O29: =SUMIF($P42:$P71,"=*Project Management*",$T42:T71) -> 5.67 | P29: =IFERROR(O29/O31,0) -> 0.17775611 | U29: Project Managment | V29: =SUMIF(P42:P71,"=*Project Management*",W42:W71) -> 0 | W29: =IFERROR(V29/BusinessCurrencyTRM,"N/A") -> 0 | Y29: varTotalPM | AC29: Project Managment | AD29: =SUMIF(P42:P71,"=*Project Management*",AD42:AD71) -> 0 | AE29: =IFERROR(AD29/BusinessCurrencyTRM,"N/A") -> 0 | AG29: =SUMIF(P42:P71,"=*Project Management*",AH42:AH71) -> 0 | AH29: =IFERROR(AG29/BusinessCurrencyTRM,"N/A") -> 0 | AJ29: =SUMIF(P42:P71,"=*Project Management*",AK42:AK71) -> 0 | AK29: =IFERROR(AJ29/BusinessCurrencyTRM,"N/A") -> 0 | AN29: =SUM(AD29,AG29,AJ29) -> 0 | AO29: =IFERROR(AN29/BusinessCurrencyTRM,"N/A") -> 0 | AS29: % Contribution Margin | AV29: =IFERROR(1-AV31/AV32,0) -> 0.30000001
N30: Risk / Extra Effort: | O30: =IF(Approach="Team-Based",SUM(O28:O29)*$O33,$J40-$G40) -> 0 | P30: =IFERROR(O30/O31,0) -> 0 | U30: Subtotal | V30: =SUM(V28:V29) -> 1061346.2 | W30: =IFERROR(V30/BusinessCurrencyTRM,"N/A") -> 272.14005 | AC30: Subtotal | AD30: =SUM(AD28:AD29) -> 1516208.9 | AE30: =IFERROR(AD30/BusinessCurrencyTRM,"N/A") -> 388.7715 | AG30: =SUM(AG28:AG29) -> 0 | AH30: =IFERROR(AG30/BusinessCurrencyTRM,"N/A") -> 0 | AJ30: =SUM(AJ28:AJ29) -> 0 | AK30: =IFERROR(AJ30/BusinessCurrencyTRM,"N/A") -> 0 | AN30: =SUM(AD30,AG30,AJ30) -> 1516208.9 | AO30: =IFERROR(AN30/BusinessCurrencyTRM,"N/A") -> 388.7715 | AV30: =BillingCountryCurrency -> COP | AW30: =IF(ISBLANK(BusinessCurrency),"N/A",BusinessCurrency) -> USD
N31: Total | O31: =SUM(O28:O30) -> 31.897638 | P31: =SUM(P28:P30) -> 1 | U31: Risks | V31: =ROUNDUP(V30*O33,2) -> 0 | W31: =IFERROR(V31/BusinessCurrencyTRM,"N/A") -> 0 | Y31: varTotalRisks | AC31: Risks | AD31: =ROUNDUP(V31/(1-$AV$28),2) -> 0 | AE31: =IFERROR(AD31/BusinessCurrencyTRM,"N/A") -> 0 | AG31: =IFERROR(V31*MAX(AG42:AG71),0) -> 0 | AH31: =IFERROR(AG31/BusinessCurrencyTRM,"N/A") -> 0 | AJ31: =IFERROR(SUM(V31,AG31)*MAX(AJ42:AJ71),0) -> 0 | AK31: =IFERROR(AJ31/BusinessCurrencyTRM,"N/A") -> 0 | AN31: =SUM(AD31,AG31,AJ31) -> 0 | AO31: =IFERROR(AN31/BusinessCurrencyTRM,"N/A") -> 0 | AS31: Phase Cost | AV31: =SUM(V37,AG37,AJ37) -> 1061346.2 | AW31: =IFERROR(AV31/BusinessCurrencyTRM,"N/A") -> 272.14005
U32: Pay Rise | V32: =IFERROR(SUMIF(PayRise!A:A,B26,PayRise!J:J),0) -> 0 | W32: =IFERROR(V32/BusinessCurrencyTRM,"N/A") -> 0 | Y32: varTotalPayRise | AC32: Pay Rise | AD32: =IFERROR(SUMIF(PayRise!A:A,B26,PayRise!K:K),0) -> 0 | AE32: =IFERROR(AD32/BusinessCurrencyTRM,"N/A") -> 0 | AG32: =IFERROR(SUMIF(PayRise!A:A,B26,PayRise!L:L),0) -> 0 | AH32: =IFERROR(AG32/BusinessCurrencyTRM,"N/A") -> 0 | AJ32: =IFERROR(SUMIF(PayRise!A:A,B26,PayRise!M:M),0) -> 0 | AK32: =IFERROR(AJ32/BusinessCurrencyTRM,"N/A") -> 0 | AN32: =SUM(AD32,AG32,AJ32) -> 0 | AO32: =IFERROR(AN32/BusinessCurrencyTRM,"N/A") -> 0 | AS32: Phase Price | AV32: =AN37 -> 1516208.9 | AW32: =IFERROR(AV32/BusinessCurrencyTRM,"N/A") -> 388.7715
N33: =IF(Approach="By Hours", "N/A for ByHours", "% Risks") -> % Risks | O33: 0 | U33: Products | V33: =IFERROR(SUMIFS(OtherCosts!Q:Q,OtherCosts!A:A,B26,OtherCosts!B:B,"Hardware/Software"),0) -> 0 | W33: =IFERROR(V33/BusinessCurrencyTRM,"N/A") -> 0 | Y33: varTotalProducts | AC33: Products | AD33: =IFERROR(SUMIFS(OtherCosts!R:R,OtherCosts!A:A,B26,OtherCosts!B:B,"Hardware/Software"),0) -> 0 | AE33: =IFERROR(AD33/BusinessCurrencyTRM,"N/A") -> 0 | AG33: =IFERROR(SUMIFS(OtherCosts!S:S,OtherCosts!A:A,B26,OtherCosts!B:B,"Hardware/Software"),0) -> 0 | AH33: =IFERROR(AG33/BusinessCurrencyTRM,"N/A") -> 0 | AJ33: =IFERROR(SUMIFS(OtherCosts!T:T,OtherCosts!A:A,B26,OtherCosts!B:B,"Hardware/Software"),0) -> 0 | AK33: =IFERROR(AJ33/BusinessCurrencyTRM,"N/A") -> 0 | AN33: =SUM(AD33,AG33,AJ33) -> 0 | AO33: =IFERROR(AN33/BusinessCurrencyTRM,"N/A") -> 0 | AS33: Monthly Price | AV33: =IFERROR(IF(O34<1,AN37,AN37/O34),0) -> 1516208.9 | AW33: =IFERROR(AV33/BusinessCurrencyTRM,"N/A") -> 388.7715
N34: =IF(Approach="By Hours", "N/A for ByHours", "Duration (Months) *") -> Duration (Months) * | O34: 1 | U34: Vendors | V34: =IFERROR(SUMIFS(OtherCosts!Q:Q,OtherCosts!A:A,B26,OtherCosts!B:B,"Vendor"),0) -> 0 | W34: =IFERROR(V34/BusinessCurrencyTRM,"N/A") -> 0 | Y34: varTotalVAR | AC34: Vendors | AD34: =IFERROR(SUMIFS(OtherCosts!R:R,OtherCosts!A:A,B26,OtherCosts!B:B,"Vendor"),0) -> 0 | AE34: =IFERROR(AD34/BusinessCurrencyTRM,"N/A") -> 0 | AG34: =IFERROR(SUMIFS(OtherCosts!S:S,OtherCosts!A:A,B26,OtherCosts!B:B,"Vendor"),0) -> 0 | AH34: =IFERROR(AG34/BusinessCurrencyTRM,"N/A") -> 0 | AJ34: =IFERROR(SUMIFS(OtherCosts!T:T,OtherCosts!A:A,B26,OtherCosts!B:B,"Vendor"),0) -> 0 | AK34: =IFERROR(AJ34/BusinessCurrencyTRM,"N/A") -> 0 | AN34: =SUM(AD34,AG34,AJ34) -> 0 | AO34: =IFERROR(AN34/BusinessCurrencyTRM,"N/A") -> 0 | AS34: Hour Price | AV34: =IFERROR(AN37/T40,0) -> 47530.058 | AW34: =IFERROR(AV34/BusinessCurrencyTRM,"N/A") -> 12.187194
U35: Insurances | V35: =IFERROR(SUMIFS(OtherCosts!Q:Q,OtherCosts!A:A,B26,OtherCosts!B:B,"Insurance"),0) -> 0 | W35: =IFERROR(V35/BusinessCurrencyTRM,"N/A") -> 0 | Y35: varTotalInsurances | AC35: Insurances | AD35: =IFERROR(SUMIFS(OtherCosts!R:R,OtherCosts!A:A,B26,OtherCosts!B:B,"Insurance"),0) -> 0 | AE35: =IFERROR(AD35/BusinessCurrencyTRM,"N/A") -> 0 | AG35: =IFERROR(SUMIFS(OtherCosts!S:S,OtherCosts!A:A,B26,OtherCosts!B:B,"Insurance"),0) -> 0 | AH35: =IFERROR(AG35/BusinessCurrencyTRM,"N/A") -> 0 | AJ35: =IFERROR(SUMIFS(OtherCosts!T:T,OtherCosts!A:A,B26,OtherCosts!B:B,"Insurance"),0) -> 0 | AK35: =IFERROR(AJ35/BusinessCurrencyTRM,"N/A") -> 0 | AN35: =SUM(AD35,AG35,AJ35) -> 0 | AO35: =IFERROR(AN35/BusinessCurrencyTRM,"N/A") -> 0
U36: Others | V36: =IFERROR(SUMIFS(OtherCosts!Q:Q,OtherCosts!A:A,B26,OtherCosts!B:B,"Other"),0) -> 0 | W36: =IFERROR(V36/BusinessCurrencyTRM,"N/A") -> 0 | Y36: varTotalOthers | AC36: Others | AD36: =IFERROR(SUMIFS(OtherCosts!R:R,OtherCosts!A:A,B26,OtherCosts!B:B,"Other"),0) -> 0 | AE36: =IFERROR(AD36/BusinessCurrencyTRM,"N/A") -> 0 | AG36: =IFERROR(SUMIFS(OtherCosts!S:S,OtherCosts!A:A,B26,OtherCosts!B:B,"Other"),0) -> 0 | AH36: =IFERROR(AG36/BusinessCurrencyTRM,"N/A") -> 0 | AJ36: =IFERROR(SUMIFS(OtherCosts!T:T,OtherCosts!A:A,B26,OtherCosts!B:B,"Other"),0) -> 0 | AK36: =IFERROR(AJ36/BusinessCurrencyTRM,"N/A") -> 0 | AN36: =SUM(AD36,AG36,AJ36) -> 0 | AO36: =IFERROR(AN36/BusinessCurrencyTRM,"N/A") -> 0
U37: Subtotal | V37: =SUM(V30:V36) -> 1061346.2 | W37: =IFERROR(V37/BusinessCurrencyTRM,"N/A") -> 272.14005 | AC37: Subtotal | AD37: =SUM(AD30:AD36) -> 1516208.9 | AE37: =IFERROR(AD37/BusinessCurrencyTRM,"N/A") -> 388.7715 | AG37: =SUM(AG30:AG36) -> 0 | AH37: =IFERROR(AG37/BusinessCurrencyTRM,"N/A") -> 0 | AJ37: =SUM(AJ30:AJ36) -> 0 | AK37: =IFERROR(AJ37/BusinessCurrencyTRM,"N/A") -> 0 | AN37: =SUM(AD37,AG37,AJ37) -> 1516208.9 | AO37: =IFERROR(AN37/BusinessCurrencyTRM,"N/A") -> 388.7715
G40: =ROUNDUP(SUM(G42:G71),2) -> 0 | J40: =ROUNDUP(SUM(J42:J71),2) -> 0 | T40: =ROUNDUP(SUM(T42:T71),2) -> 31.9 | W40: =SUM(W42:W69) -> 1061346.2 | Y40: varTotalFase | AD40: =SUM(AD42:AD71) -> 1516208.9 | AE40: =IFERROR(1-($W40/$AD40),0) -> 0.30000001 | AH40: =SUM(AH42:AH71) -> 0 | AK40: =ROUNDUP(SUM(AK42:AK71),2) -> 0 | AM40: =SUM(AM42:AM71) -> 1516208.9 | AN40: =SUM(AN42:AN71) -> 1516208.9 | AO40: =BillingCountryCurrency -> COP | AT40: =SUM(AT42:AU71) -> 1516208.9 | AV40: =BillingCountryCurrency -> COP | AW40: =IF(ISBLANK(BusinessCurrency),"N/A",BusinessCurrency) -> USD
G41: Hours | H41: Risk | I41: EE | J41: Total | N41: Delivery Country | O41: Services Line | P41: Job Profile | Q41: Qty | R41: % Allocation | S41: Days | T41: Total Hours | U41: % Surcharge Hours | V41: Unit Cost Base | W41: Subtotal Cost | X41: FilterSL | Y41: FilterJP | AC41: Unit Price Base | AD41: Subtotal Price | AE41: % MaS | AG41: % Intercomp | AH41: $ Intercompany | AJ41: % WHT | AK41: $ WHT | AM41: Subtotal Price | AN41: Subtotal Price + Costs | AO41: Unit Price + Costs | AS41: Fact | AT41: Subtotal Price + Costs | AV41: Unit Price + Cost | AW41: Unit Price + Cost
B42: Observaciones / Incluido: | C42: Gerencia del proyecto | G42: 0 | H42: 0 | I42: 0 | J42: =IFERROR(G42/(1-(H42+I42)),0) -> 0 | N42: xDC Medellin | O42: Other Services | P42: Expert Technology & Consulting Project Management | Q42: 1 | R42: 0.035 | S42: 20 | T42: =IF(ISBLANK($P42),0,IF(Approach="Team-Based",$Q42*$R42*$S42*HoursPerDayTeamBased,$J42)) -> 5.67 | U42: 0 | V42: =ROUNDUP(IFERROR(INDEX(CostRateTbl[Cost Rate],MATCH(_xlfn.CONCAT(N42,O42,P42,"NA"),CostRateTbl[KeyCostRate],0)),0)*BillingCurrencyTRM*(1+U42),2) -> 0 | W42: =T42*V42 -> 0 | X42: {=_xlfn.LET( _xlpm.valor, INDEX(CostRate!H:H, MATCH(1, (CostRate!A:A=N42)*1, 0)), _xlpm.posicion, MATCH(_xlpm.valor, FilterSL!$F$1:$Z$1, 0), _xlpm.direccionCompleta, ADDRESS(1, _xlpm.posicion + 5, 4), _xlpm.letraColumna, SUBSTITUTE(_xlpm.direccionCompleta, "1", ""), _xlpm.letraColumna )} -> R | Y42: {=_xlfn.LET( _xlpm.valor, INDEX(CostRate!I:I, MATCH(1, (CostRate!A:A=N42)*(CostRate!B:B=O42), 0)), _xlpm.posicion, MATCH(_xlpm.valor, FilterJP!$E$1:$FZ$1, 0), _xlpm.direccionCompleta, ADDRESS(1, _xlpm.posicion + 4, 4), _xlpm.letraColumna, SUBSTITUTE(_xlpm.direccionCompleta, "1", ""), _xlpm.letraColumna )} -> BO | AC42: =ROUNDUP($V42/(1-$AV$28),2) -> 0 | AD42: =$T42*$AC42 -> 0 | AE42: =IFERROR(1-($W42/$AD42),0) -> 0 | AG42: =IFERROR(IF(OR(ISBLANK(N42),N42=CustomerCountry,COUNTIF($N42,"*xDC*")),0,10%),0) -> 0 | AH42: =W42*AG42 -> 0 | AJ42: {=IFERROR(INDEX(WHT!$C$7:$W$18,MATCH( _xlfn.SWITCH(N42,"xDC Medellin","Colombia","xDC Belo Horizonte","Brazil","xDC Guadalajara","Mexico","xDC Gurugram","India","xDC Leon","Spain","xDC San Jose","Costa Rica","xDC Warsaw","Poland",N42), WHT!$B$7:$B$18,0),MATCH(CustomerCountry,WHT!$C$5:$W$5,0)),0)} -> 0 | AK42: =(W42+AH42)*AJ42 -> 0 | AM42: =SUM($AD42,$AH42,$AK42) -> 0 | AN42: =AM42+IFERROR(SUM($AN$31:$AN$36)*AM42/$AM$40,0) -> 0 | AO42: =IFERROR($AN42/$T42,0) -> 0 | AS42: X | AT42: =IF(AS42="x",AM42+((SUM($AN$31:$AN$36)+SUMIF($AS$42:$AS$71,"<>x",$AM$42:$AM$71))*IFERROR(AM42/SUMIF($AS$42:$AS$71,"x",$AM$42:$AM$71),0)),0) -> 0 | AV42: =IFERROR(AT42/T42,0) -> 0 | AW42: =IFERROR(AV42/BusinessCurrencyTRM,"N/A") -> 0
C43: Administrador Azure | G43: 0 | H43: 0 | I43: 0 | J43: =IFERROR(G43/(1-(H43+I43)),0) -> 0 | N43: xDC Medellin | O43: Other Services | P43: Expert Managed Operations | Q43: 1 | R43: 0.078 | S43: 20 | T43: =IF(ISBLANK($P43),0,IF(Approach="Team-Based",$Q43*$R43*$S43*HoursPerDayTeamBased,$J43)) -> 12.636 | U43: 0 | V43: =ROUNDUP(IFERROR(INDEX(CostRateTbl[Cost Rate],MATCH(_xlfn.CONCAT(N43,O43,P43,"NA"),CostRateTbl[KeyCostRate],0)),0)*BillingCurrencyTRM*(1+U43),2) -> 0 | W43: =T43*V43 -> 0 | X43: {=_xlfn.LET( _xlpm.valor, INDEX(CostRate!H:H, MATCH(1, (CostRate!A:A=N43)*1, 0)), _xlpm.posicion, MATCH(_xlpm.valor, FilterSL!$F$1:$Z$1, 0), _xlpm.direccionCompleta, ADDRESS(1, _xlpm.posicion + 5, 4), _xlpm.letraColumna, SUBSTITUTE(_xlpm.direccionCompleta, "1", ""), _xlpm.letraColumna )} -> R | Y43: {=_xlfn.LET( _xlpm.valor, INDEX(CostRate!I:I, MATCH(1, (CostRate!A:A=N43)*(CostRate!B:B=O43), 0)), _xlpm.posicion, MATCH(_xlpm.valor, FilterJP!$E$1:$FZ$1, 0), _xlpm.direccionCompleta, ADDRESS(1, _xlpm.posicion + 4, 4), _xlpm.letraColumna, SUBSTITUTE(_xlpm.direccionCompleta, "1", ""), _xlpm.letraColumna )} -> BO | AC43: =ROUNDUP($V43/(1-$AV$28),2) -> 0 | AD43: =$T43*$AC43 -> 0 | AE43: =IFERROR(1-($W43/$AD43),0) -> 0 | AG43: =IFERROR(IF(OR(ISBLANK(N43),N43=CustomerCountry,COUNTIF($N43,"*xDC*")),0,10%),0) -> 0 | AH43: =W43*AG43 -> 0 | AJ43: {=IFERROR(INDEX(WHT!$C$7:$W$18,MATCH( _xlfn.SWITCH(N43,"xDC Medellin","Colombia","xDC Belo Horizonte","Brazil","xDC Guadalajara","Mexico","xDC Gurugram","India","xDC Leon","Spain","xDC San Jose","Costa Rica","xDC Warsaw","Poland",N43), WHT!$B$7:$B$18,0),MATCH(CustomerCountry,WHT!$C$5:$W$5,0)),0)} -> 0 | AK43: =(W43+AH43)*AJ43 -> 0 | AM43: =SUM($AD43,$AH43,$AK43) -> 0 | AN43: =AM43+IFERROR(SUM($AN$31:$AN$36)*AM43/$AM$40,0) -> 0 | AO43: =IFERROR($AN43/$T43,0) -> 0 | AS43: X | AT43: =IF(AS43="x",AM43+((SUM($AN$31:$AN$36)+SUMIF($AS$42:$AS$71,"<>x",$AM$42:$AM$71))*IFERROR(AM43/SUMIF($AS$42:$AS$71,"x",$AM$42:$AM$71),0)),0) -> 0 | AV43: =IFERROR(AT43/T43,0) -> 0 | AW43: =IFERROR(AV43/BusinessCurrencyTRM,"N/A") -> 0
C44: Arquitecto / especialista | G44: 0 | H44: 0 | I44: 0 | J44: =IFERROR(G44/(1-(H44+I44)),0) -> 0 | N44: xDC Medellin | O44: Cloud Services Azure | P44: Expert Technology Implementation & Consulting (General) | Q44: 1 | R44: 0.035 | S44: 20 | T44: =IF(ISBLANK($P44),0,IF(Approach="Team-Based",$Q44*$R44*$S44*HoursPerDayTeamBased,$J44)) -> 5.67 | U44: 0 | V44: =ROUNDUP(IFERROR(INDEX(CostRateTbl[Cost Rate],MATCH(_xlfn.CONCAT(N44,O44,P44,"NA"),CostRateTbl[KeyCostRate],0)),0)*BillingCurrencyTRM*(1+U44),2) -> 133425.46 | W44: =T44*V44 -> 756522.36 | X44: {=_xlfn.LET( _xlpm.valor, INDEX(CostRate!H:H, MATCH(1, (CostRate!A:A=N44)*1, 0)), _xlpm.posicion, MATCH(_xlpm.valor, FilterSL!$F$1:$Z$1, 0), _xlpm.direccionCompleta, ADDRESS(1, _xlpm.posicion + 5, 4), _xlpm.letraColumna, SUBSTITUTE(_xlpm.direccionCompleta, "1", ""), _xlpm.letraColumna )} -> R | Y44: {=_xlfn.LET( _xlpm.valor, INDEX(CostRate!I:I, MATCH(1, (CostRate!A:A=N44)*(CostRate!B:B=O44), 0)), _xlpm.posicion, MATCH(_xlpm.valor, FilterJP!$E$1:$FZ$1, 0), _xlpm.direccionCompleta, ADDRESS(1, _xlpm.posicion + 4, 4), _xlpm.letraColumna, SUBSTITUTE(_xlpm.direccionCompleta, "1", ""), _xlpm.letraColumna )} -> BI | AC44: =ROUNDUP($V44/(1-$AV$28),2) -> 190607.8 | AD44: =$T44*$AC44 -> 1080746.2 | AE44: =IFERROR(1-($W44/$AD44),0) -> 0.3 | AG44: =IFERROR(IF(OR(ISBLANK(N44),N44=CustomerCountry,COUNTIF($N44,"*xDC*")),0,10%),0) -> 0 | AH44: =W44*AG44 -> 0 | AJ44: {=IFERROR(INDEX(WHT!$C$7:$W$18,MATCH( _xlfn.SWITCH(N44,"xDC Medellin","Colombia","xDC Belo Horizonte","Brazil","xDC Guadalajara","Mexico","xDC Gurugram","India","xDC Leon","Spain","xDC San Jose","Costa Rica","xDC Warsaw","Poland",N44), WHT!$B$7:$B$18,0),MATCH(CustomerCountry,WHT!$C$5:$W$5,0)),0)} -> 0 | AK44: =(W44+AH44)*AJ44 -> 0 | AM44: =SUM($AD44,$AH44,$AK44) -> 1080746.2 | AN44: =AM44+IFERROR(SUM($AN$31:$AN$36)*AM44/$AM$40,0) -> 1080746.2 | AO44: =IFERROR($AN44/$T44,0) -> 190607.8 | AS44: X | AT44: =IF(AS44="x",AM44+((SUM($AN$31:$AN$36)+SUMIF($AS$42:$AS$71,"<>x",$AM$42:$AM$71))*IFERROR(AM44/SUMIF($AS$42:$AS$71,"x",$AM$42:$AM$71),0)),0) -> 1080746.2 | AV44: =IFERROR(AT44/T44,0) -> 190607.8 | AW44: =IFERROR(AV44/BusinessCurrencyTRM,"N/A") -> 48.873795
C45: Monitoreo / operación | G45: 0 | H45: 0 | I45: 0 | J45: =IFERROR(G45/(1-(H45+I45)),0) -> 0 | N45: xDC Medellin | O45: Other Services | P45: Associate Expert Managed Operations | Q45: 1 | R45: 0.035 | S45: 20 | T45: =IF(ISBLANK($P45),0,IF(Approach="Team-Based",$Q45*$R45*$S45*HoursPerDayTeamBased,$J45)) -> 5.67 | U45: 0 | V45: =ROUNDUP(IFERROR(INDEX(CostRateTbl[Cost Rate],MATCH(_xlfn.CONCAT(N45,O45,P45,"NA"),CostRateTbl[KeyCostRate],0)),0)*BillingCurrencyTRM*(1+U45),2) -> 46596.59 | W45: =T45*V45 -> 264202.67 | X45: {=_xlfn.LET( _xlpm.valor, INDEX(CostRate!H:H, MATCH(1, (CostRate!A:A=N45)*1, 0)), _xlpm.posicion, MATCH(_xlpm.valor, FilterSL!$F$1:$Z$1, 0), _xlpm.direccionCompleta, ADDRESS(1, _xlpm.posicion + 5, 4), _xlpm.letraColumna, SUBSTITUTE(_xlpm.direccionCompleta, "1", ""), _xlpm.letraColumna )} -> R | Y45: {=_xlfn.LET( _xlpm.valor, INDEX(CostRate!I:I, MATCH(1, (CostRate!A:A=N45)*(CostRate!B:B=O45), 0)), _xlpm.posicion, MATCH(_xlpm.valor, FilterJP!$E$1:$FZ$1, 0), _xlpm.direccionCompleta, ADDRESS(1, _xlpm.posicion + 4, 4), _xlpm.letraColumna, SUBSTITUTE(_xlpm.direccionCompleta, "1", ""), _xlpm.letraColumna )} -> BO | AC45: =ROUNDUP($V45/(1-$AV$28),2) -> 66566.56 | AD45: =$T45*$AC45 -> 377432.4 | AE45: =IFERROR(1-($W45/$AD45),0) -> 0.30000003 | AG45: =IFERROR(IF(OR(ISBLANK(N45),N45=CustomerCountry,COUNTIF($N45,"*xDC*")),0,10%),0) -> 0 | AH45: =W45*AG45 -> 0 | AJ45: {=IFERROR(INDEX(WHT!$C$7:$W$18,MATCH( _xlfn.SWITCH(N45,"xDC Medellin","Colombia","xDC Belo Horizonte","Brazil","xDC Guadalajara","Mexico","xDC Gurugram","India","xDC Leon","Spain","xDC San Jose","Costa Rica","xDC Warsaw","Poland",N45), WHT!$B$7:$B$18,0),MATCH(CustomerCountry,WHT!$C$5:$W$5,0)),0)} -> 0 | AK45: =(W45+AH45)*AJ45 -> 0 | AM45: =SUM($AD45,$AH45,$AK45) -> 377432.4 | AN45: =AM45+IFERROR(SUM($AN$31:$AN$36)*AM45/$AM$40,0) -> 377432.4 | AO45: =IFERROR($AN45/$T45,0) -> 66566.56 | AS45: X | AT45: =IF(AS45="x",AM45+((SUM($AN$31:$AN$36)+SUMIF($AS$42:$AS$71,"<>x",$AM$42:$AM$71))*IFERROR(AM45/SUMIF($AS$42:$AS$71,"x",$AM$42:$AM$71),0)),0) -> 377432.4 | AV45: =IFERROR(AT45/T45,0) -> 66566.56 | AW45: =IFERROR(AV45/BusinessCurrencyTRM,"N/A") -> 17.068349
C46: Administrador Azure - 10% Horas Extras + 25% | G46: 0 | H46: 0 | I46: 0 | J46: =IFERROR(G46/(1-(H46+I46)),0) -> 0 | N46: xDC Medellin | O46: Other Services | P46: Expert Managed Operations | Q46: 1.23 | R46: =(10%*T43)/S46/HoursPerDayTeamBased -> 0.078 | S46: =20*10% -> 2 | T46: =IF(ISBLANK($P46),0,IF(Approach="Team-Based",$Q46*$R46*$S46*HoursPerDayTeamBased,$J46)) -> 1.554228 | U46: 0.25 | V46: =ROUNDUP(IFERROR(INDEX(CostRateTbl[Cost Rate],MATCH(_xlfn.CONCAT(N46,O46,P46,"NA"),CostRateTbl[KeyCostRate],0)),0)*BillingCurrencyTRM*(1+U46),2) -> 0 | W46: =T46*V46 -> 0 | X46: {=_xlfn.LET( _xlpm.valor, INDEX(CostRate!H:H, MATCH(1, (CostRate!A:A=N46)*1, 0)), _xlpm.posicion, MATCH(_xlpm.valor, FilterSL!$F$1:$Z$1, 0), _xlpm.direccionCompleta, ADDRESS(1, _xlpm.posicion + 5, 4), _xlpm.letraColumna, SUBSTITUTE(_xlpm.direccionCompleta, "1", ""), _xlpm.letraColumna )} -> R | Y46: {=_xlfn.LET( _xlpm.valor, INDEX(CostRate!I:I, MATCH(1, (CostRate!A:A=N46)*(CostRate!B:B=O46), 0)), _xlpm.posicion, MATCH(_xlpm.valor, FilterJP!$E$1:$FZ$1, 0), _xlpm.direccionCompleta, ADDRESS(1, _xlpm.posicion + 4, 4), _xlpm.letraColumna, SUBSTITUTE(_xlpm.direccionCompleta, "1", ""), _xlpm.letraColumna )} -> BO | AC46: =ROUNDUP($V46/(1-$AV$28),2) -> 0 | AD46: =$T46*$AC46 -> 0 | AE46: =IFERROR(1-($W46/$AD46),0) -> 0 | AG46: =IFERROR(IF(OR(ISBLANK(N46),N46=CustomerCountry,COUNTIF($N46,"*xDC*")),0,10%),0) -> 0 | AH46: =W46*AG46 -> 0 | AJ46: {=IFERROR(INDEX(WHT!$C$7:$W$18,MATCH( _xlfn.SWITCH(N46,"xDC Medellin","Colombia","xDC Belo Horizonte","Brazil","xDC Guadalajara","Mexico","xDC Gurugram","India","xDC Leon","Spain","xDC San Jose","Costa Rica","xDC Warsaw","Poland",N46), WHT!$B$7:$B$18,0),MATCH(CustomerCountry,WHT!$C$5:$W$5,0)),0)} -> 0 | AK46: =(W46+AH46)*AJ46 -> 0 | AM46: =SUM($AD46,$AH46,$AK46) -> 0 | AN46: =AM46+IFERROR(SUM($AN$31:$AN$36)*AM46/$AM$40,0) -> 0 | AO46: =IFERROR($AN46/$T46,0) -> 0 | AS46: X | AT46: =IF(AS46="x",AM46+((SUM($AN$31:$AN$36)+SUMIF($AS$42:$AS$71,"<>x",$AM$42:$AM$71))*IFERROR(AM46/SUMIF($AS$42:$AS$71,"x",$AM$42:$AM$71),0)),0) -> 0 | AV46: =IFERROR(AT46/T46,0) -> 0 | AW46: =IFERROR(AV46/BusinessCurrencyTRM,"N/A") -> 0
C47: Monitoreo / operación - 10% Horas Extras + 25% | G47: 0 | H47: 0 | I47: 0 | J47: =IFERROR(G47/(1-(H47+I47)),0) -> 0 | N47: xDC Medellin | O47: Other Services | P47: Associate Expert Managed Operations | Q47: 1.23 | R47: =(10%*T44)/S47/HoursPerDayTeamBased -> 0.035 | S47: =20*10% -> 2 | T47: =IF(ISBLANK($P47),0,IF(Approach="Team-Based",$Q47*$R47*$S47*HoursPerDayTeamBased,$J47)) -> 0.69741 | U47: 0.25 | V47: =ROUNDUP(IFERROR(INDEX(CostRateTbl[Cost Rate],MATCH(_xlfn.CONCAT(N47,O47,P47,"NA"),CostRateTbl[KeyCostRate],0)),0)*BillingCurrencyTRM*(1+U47),2) -> 58245.74 | W47: =T47*V47 -> 40621.162 | X47: {=_xlfn.LET( _xlpm.valor, INDEX(CostRate!H:H, MATCH(1, (CostRate!A:A=N47)*1, 0)), _xlpm.posicion, MATCH(_xlpm.valor, FilterSL!$F$1:$Z$1, 0), _xlpm.direccionCompleta, ADDRESS(1, _xlpm.posicion + 5, 4), _xlpm.letraColumna, SUBSTITUTE(_xlpm.direccionCompleta, "1", ""), _xlpm.letraColumna )} -> R | Y47: {=_xlfn.LET( _xlpm.valor, INDEX(CostRate!I:I, MATCH(1, (CostRate!A:A=N47)*(CostRate!B:B=O47), 0)), _xlpm.posicion, MATCH(_xlpm.valor, FilterJP!$E$1:$FZ$1, 0), _xlpm.direccionCompleta, ADDRESS(1, _xlpm.posicion + 4, 4), _xlpm.letraColumna, SUBSTITUTE(_xlpm.direccionCompleta, "1", ""), _xlpm.letraColumna )} -> BO | AC47: =ROUNDUP($V47/(1-$AV$28),2) -> 83208.2 | AD47: =$T47*$AC47 -> 58030.231 | AE47: =IFERROR(1-($W47/$AD47),0) -> 0.3 | AG47: =IFERROR(IF(OR(ISBLANK(N47),N47=CustomerCountry,COUNTIF($N47,"*xDC*")),0,10%),0) -> 0 | AH47: =W47*AG47 -> 0 | AJ47: {=IFERROR(INDEX(WHT!$C$7:$W$18,MATCH( _xlfn.SWITCH(N47,"xDC Medellin","Colombia","xDC Belo Horizonte","Brazil","xDC Guadalajara","Mexico","xDC Gurugram","India","xDC Leon","Spain","xDC San Jose","Costa Rica","xDC Warsaw","Poland",N47), WHT!$B$7:$B$18,0),MATCH(CustomerCountry,WHT!$C$5:$W$5,0)),0)} -> 0 | AK47: =(W47+AH47)*AJ47 -> 0 | AM47: =SUM($AD47,$AH47,$AK47) -> 58030.231 | AN47: =AM47+IFERROR(SUM($AN$31:$AN$36)*AM47/$AM$40,0) -> 58030.231 | AO47: =IFERROR($AN47/$T47,0) -> 83208.2 | AS47: X | AT47: =IF(AS47="x",AM47+((SUM($AN$31:$AN$36)+SUMIF($AS$42:$AS$71,"<>x",$AM$42:$AM$71))*IFERROR(AM47/SUMIF($AS$42:$AS$71,"x",$AM$42:$AM$71),0)),0) -> 58030.231 | AV47: =IFERROR(AT47/T47,0) -> 83208.2 | AW47: =IFERROR(AV47/BusinessCurrencyTRM,"N/A") -> 21.335436
C48: Administrador Azure - Disponibilidad - Incluir costo 200 USD x Mes | G48: 0 | H48: 0 | I48: 0 | J48: =IFERROR(G48/(1-(H48+I48)),0) -> 0 | S48: =IF(ISBLANK(P48),0,$O$34*20) -> 0 | T48: =IF(ISBLANK($P48),0,IF(Approach="Team-Based",$Q48*$R48*$S48*HoursPerDayTeamBased,$J48)) -> 0 | U48: 0 | V48: =ROUNDUP(IFERROR(INDEX(CostRateTbl[Cost Rate],MATCH(_xlfn.CONCAT(N48,O48,P48,"NA"),CostRateTbl[KeyCostRate],0)),0)*BillingCurrencyTRM*(1+U48),2) -> 0 | W48: =T48*V48 -> 0 | X48: {=_xlfn.LET( _xlpm.valor, INDEX(CostRate!H:H, MATCH(1, (CostRate!A:A=N48)*1, 0)), _xlpm.posicion, MATCH(_xlpm.valor, FilterSL!$F$1:$Z$1, 0), _xlpm.direccionCompleta, ADDRESS(1, _xlpm.posicion + 5, 4), _xlpm.letraColumna, SUBSTITUTE(_xlpm.direccionCompleta, "1", ""), _xlpm.letraColumna )} -> #N/A | Y48: {=_xlfn.LET( _xlpm.valor, INDEX(CostRate!I:I, MATCH(1, (CostRate!A:A=N48)*(CostRate!B:B=O48), 0)), _xlpm.posicion, MATCH(_xlpm.valor, FilterJP!$E$1:$FZ$1, 0), _xlpm.direccionCompleta, ADDRESS(1, _xlpm.posicion + 4, 4), _xlpm.letraColumna, SUBSTITUTE(_xlpm.direccionCompleta, "1", ""), _xlpm.letraColumna )} -> #N/A | AC48: =ROUNDUP($V48/(1-$AV$28),2) -> 0 | AD48: =$T48*$AC48 -> 0 | AE48: =IFERROR(1-($W48/$AD48),0) -> 0 | AG48: =IFERROR(IF(OR(ISBLANK(N48),N48=CustomerCountry,COUNTIF($N48,"*xDC*")),0,10%),0) -> 0 | AH48: =W48*AG48 -> 0 | AJ48: {=IFERROR(INDEX(WHT!$C$7:$W$18,MATCH( _xlfn.SWITCH(N48,"xDC Medellin","Colombia","xDC Belo Horizonte","Brazil","xDC Guadalajara","Mexico","xDC Gurugram","India","xDC Leon","Spain","xDC San Jose","Costa Rica","xDC Warsaw","Poland",N48), WHT!$B$7:$B$18,0),MATCH(CustomerCountry,WHT!$C$5:$W$5,0)),0)} -> 0 | AK48: =(W48+AH48)*AJ48 -> 0 | AM48: =SUM($AD48,$AH48,$AK48) -> 0 | AN48: =AM48+IFERROR(SUM($AN$31:$AN$36)*AM48/$AM$40,0) -> 0 | AO48: =IFERROR($AN48/$T48,0) -> 0 | AS48: X | AT48: =IF(AS48="x",AM48+((SUM($AN$31:$AN$36)+SUMIF($AS$42:$AS$71,"<>x",$AM$42:$AM$71))*IFERROR(AM48/SUMIF($AS$42:$AS$71,"x",$AM$42:$AM$71),0)),0) -> 0 | AV48: =IFERROR(AT48/T48,0) -> 0 | AW48: =IFERROR(AV48/BusinessCurrencyTRM,"N/A") -> 0
G49: 0 | H49: 0 | I49: 0 | J49: =IFERROR(G49/(1-(H49+I49)),0) -> 0 | S49: =IF(ISBLANK(P49),0,$O$34*20) -> 0 | T49: =IF(ISBLANK($P49),0,IF(Approach="Team-Based",$Q49*$R49*$S49*HoursPerDayTeamBased,$J49)) -> 0 | U49: 0 | V49: =ROUNDUP(IFERROR(INDEX(CostRateTbl[Cost Rate],MATCH(_xlfn.CONCAT(N49,O49,P49,"NA"),CostRateTbl[KeyCostRate],0)),0)*BillingCurrencyTRM*(1+U49),2) -> 0 | W49: =T49*V49 -> 0 | X49: {=_xlfn.LET( _xlpm.valor, INDEX(CostRate!H:H, MATCH(1, (CostRate!A:A=N49)*1, 0)), _xlpm.posicion, MATCH(_xlpm.valor, FilterSL!$F$1:$Z$1, 0), _xlpm.direccionCompleta, ADDRESS(1, _xlpm.posicion + 5, 4), _xlpm.letraColumna, SUBSTITUTE(_xlpm.direccionCompleta, "1", ""), _xlpm.letraColumna )} -> #N/A | Y49: {=_xlfn.LET( _xlpm.valor, INDEX(CostRate!I:I, MATCH(1, (CostRate!A:A=N49)*(CostRate!B:B=O49), 0)), _xlpm.posicion, MATCH(_xlpm.valor, FilterJP!$E$1:$FZ$1, 0), _xlpm.direccionCompleta, ADDRESS(1, _xlpm.posicion + 4, 4), _xlpm.letraColumna, SUBSTITUTE(_xlpm.direccionCompleta, "1", ""), _xlpm.letraColumna )} -> #N/A | AC49: =ROUNDUP($V49/(1-$AV$28),2) -> 0 | AD49: =$T49*$AC49 -> 0 | AE49: =IFERROR(1-($W49/$AD49),0) -> 0 | AG49: =IFERROR(IF(OR(ISBLANK(N49),N49=CustomerCountry,COUNTIF($N49,"*xDC*")),0,10%),0) -> 0 | AH49: =W49*AG49 -> 0 | AJ49: {=IFERROR(INDEX(WHT!$C$7:$W$18,MATCH( _xlfn.SWITCH(N49,"xDC Medellin","Colombia","xDC Belo Horizonte","Brazil","xDC Guadalajara","Mexico","xDC Gurugram","India","xDC Leon","Spain","xDC San Jose","Costa Rica","xDC Warsaw","Poland",N49), WHT!$B$7:$B$18,0),MATCH(CustomerCountry,WHT!$C$5:$W$5,0)),0)} -> 0 | AK49: =(W49+AH49)*AJ49 -> 0 | AM49: =SUM($AD49,$AH49,$AK49) -> 0 | AN49: =AM49+IFERROR(SUM($AN$31:$AN$36)*AM49/$AM$40,0) -> 0 | AO49: =IFERROR($AN49/$T49,0) -> 0 | AS49: X | AT49: =IF(AS49="x",AM49+((SUM($AN$31:$AN$36)+SUMIF($AS$42:$AS$71,"<>x",$AM$42:$AM$71))*IFERROR(AM49/SUMIF($AS$42:$AS$71,"x",$AM$42:$AM$71),0)),0) -> 0 | AV49: =IFERROR(AT49/T49,0) -> 0 | AW49: =IFERROR(AV49/BusinessCurrencyTRM,"N/A") -> 0
G50: 0 | H50: 0 | I50: 0 | J50: =IFERROR(G50/(1-(H50+I50)),0) -> 0 | S50: =IF(ISBLANK(P50),0,$O$34*20) -> 0 | T50: =IF(ISBLANK($P50),0,IF(Approach="Team-Based",$Q50*$R50*$S50*HoursPerDayTeamBased,$J50)) -> 0 | U50: 0 | V50: =ROUNDUP(IFERROR(INDEX(CostRateTbl[Cost Rate],MATCH(_xlfn.CONCAT(N50,O50,P50,"NA"),CostRateTbl[KeyCostRate],0)),0)*BillingCurrencyTRM*(1+U50),2) -> 0 | W50: =T50*V50 -> 0 | X50: {=_xlfn.LET( _xlpm.valor, INDEX(CostRate!H:H, MATCH(1, (CostRate!A:A=N50)*1, 0)), _xlpm.posicion, MATCH(_xlpm.valor, FilterSL!$F$1:$Z$1, 0), _xlpm.direccionCompleta, ADDRESS(1, _xlpm.posicion + 5, 4), _xlpm.letraColumna, SUBSTITUTE(_xlpm.direccionCompleta, "1", ""), _xlpm.letraColumna )} -> #N/A | Y50: {=_xlfn.LET( _xlpm.valor, INDEX(CostRate!I:I, MATCH(1, (CostRate!A:A=N50)*(CostRate!B:B=O50), 0)), _xlpm.posicion, MATCH(_xlpm.valor, FilterJP!$E$1:$FZ$1, 0), _xlpm.direccionCompleta, ADDRESS(1, _xlpm.posicion + 4, 4), _xlpm.letraColumna, SUBSTITUTE(_xlpm.direccionCompleta, "1", ""), _xlpm.letraColumna )} -> #N/A | AC50: =ROUNDUP($V50/(1-$AV$28),2) -> 0 | AD50: =$T50*$AC50 -> 0 | AE50: =IFERROR(1-($W50/$AD50),0) -> 0 | AG50: =IFERROR(IF(OR(ISBLANK(N50),N50=CustomerCountry,COUNTIF($N50,"*xDC*")),0,10%),0) -> 0 | AH50: =W50*AG50 -> 0 | AJ50: {=IFERROR(INDEX(WHT!$C$7:$W$18,MATCH( _xlfn.SWITCH(N50,"xDC Medellin","Colombia","xDC Belo Horizonte","Brazil","xDC Guadalajara","Mexico","xDC Gurugram","India","xDC Leon","Spain","xDC San Jose","Costa Rica","xDC Warsaw","Poland",N50), WHT!$B$7:$B$18,0),MATCH(CustomerCountry,WHT!$C$5:$W$5,0)),0)} -> 0 | AK50: =(W50+AH50)*AJ50 -> 0 | AM50: =SUM($AD50,$AH50,$AK50) -> 0 | AN50: =AM50+IFERROR(SUM($AN$31:$AN$36)*AM50/$AM$40,0) -> 0 | AO50: =IFERROR($AN50/$T50,0) -> 0 | AS50: X | AT50: =IF(AS50="x",AM50+((SUM($AN$31:$AN$36)+SUMIF($AS$42:$AS$71,"<>x",$AM$42:$AM$71))*IFERROR(AM50/SUMIF($AS$42:$AS$71,"x",$AM$42:$AM$71),0)),0) -> 0 | AV50: =IFERROR(AT50/T50,0) -> 0 | AW50: =IFERROR(AV50/BusinessCurrencyTRM,"N/A") -> 0
G51: 0 | H51: 0 | I51: 0 | J51: =IFERROR(G51/(1-(H51+I51)),0) -> 0 | S51: =IF(ISBLANK(P51),0,$O$34*20) -> 0 | T51: =IF(ISBLANK($P51),0,IF(Approach="Team-Based",$Q51*$R51*$S51*HoursPerDayTeamBased,$J51)) -> 0 | U51: 0 | V51: =ROUNDUP(IFERROR(INDEX(CostRateTbl[Cost Rate],MATCH(_xlfn.CONCAT(N51,O51,P51,"NA"),CostRateTbl[KeyCostRate],0)),0)*BillingCurrencyTRM*(1+U51),2) -> 0 | W51: =T51*V51 -> 0 | X51: {=_xlfn.LET( _xlpm.valor, INDEX(CostRate!H:H, MATCH(1, (CostRate!A:A=N51)*1, 0)), _xlpm.posicion, MATCH(_xlpm.valor, FilterSL!$F$1:$Z$1, 0), _xlpm.direccionCompleta, ADDRESS(1, _xlpm.posicion + 5, 4), _xlpm.letraColumna, SUBSTITUTE(_xlpm.direccionCompleta, "1", ""), _xlpm.letraColumna )} -> #N/A | Y51: {=_xlfn.LET( _xlpm.valor, INDEX(CostRate!I:I, MATCH(1, (CostRate!A:A=N51)*(CostRate!B:B=O51), 0)), _xlpm.posicion, MATCH(_xlpm.valor, FilterJP!$E$1:$FZ$1, 0), _xlpm.direccionCompleta, ADDRESS(1, _xlpm.posicion + 4, 4), _xlpm.letraColumna, SUBSTITUTE(_xlpm.direccionCompleta, "1", ""), _xlpm.letraColumna )} -> #N/A | AC51: =ROUNDUP($V51/(1-$AV$28),2) -> 0 | AD51: =$T51*$AC51 -> 0 | AE51: =IFERROR(1-($W51/$AD51),0) -> 0 | AG51: =IFERROR(IF(OR(ISBLANK(N51),N51=CustomerCountry,COUNTIF($N51,"*xDC*")),0,10%),0) -> 0 | AH51: =W51*AG51 -> 0 | AJ51: {=IFERROR(INDEX(WHT!$C$7:$W$18,MATCH( _xlfn.SWITCH(N51,"xDC Medellin","Colombia","xDC Belo Horizonte","Brazil","xDC Guadalajara","Mexico","xDC Gurugram","India","xDC Leon","Spain","xDC San Jose","Costa Rica","xDC Warsaw","Poland",N51), WHT!$B$7:$B$18,0),MATCH(CustomerCountry,WHT!$C$5:$W$5,0)),0)} -> 0 | AK51: =(W51+AH51)*AJ51 -> 0 | AM51: =SUM($AD51,$AH51,$AK51) -> 0 | AN51: =AM51+IFERROR(SUM($AN$31:$AN$36)*AM51/$AM$40,0) -> 0 | AO51: =IFERROR($AN51/$T51,0) -> 0 | AS51: X | AT51: =IF(AS51="x",AM51+((SUM($AN$31:$AN$36)+SUMIF($AS$42:$AS$71,"<>x",$AM$42:$AM$71))*IFERROR(AM51/SUMIF($AS$42:$AS$71,"x",$AM$42:$AM$71),0)),0) -> 0 | AV51: =IFERROR(AT51/T51,0) -> 0 | AW51: =IFERROR(AV51/BusinessCurrencyTRM,"N/A") -> 0
G52: 0 | H52: 0 | I52: 0 | J52: =IFERROR(G52/(1-(H52+I52)),0) -> 0 | S52: =IF(ISBLANK(P52),0,$O$34*20) -> 0 | T52: =IF(ISBLANK($P52),0,IF(Approach="Team-Based",$Q52*$R52*$S52*HoursPerDayTeamBased,$J52)) -> 0 | U52: 0 | V52: =ROUNDUP(IFERROR(INDEX(CostRateTbl[Cost Rate],MATCH(_xlfn.CONCAT(N52,O52,P52,"NA"),CostRateTbl[KeyCostRate],0)),0)*BillingCurrencyTRM*(1+U52),2) -> 0 | W52: =T52*V52 -> 0 | X52: {=_xlfn.LET( _xlpm.valor, INDEX(CostRate!H:H, MATCH(1, (CostRate!A:A=N52)*1, 0)), _xlpm.posicion, MATCH(_xlpm.valor, FilterSL!$F$1:$Z$1, 0), _xlpm.direccionCompleta, ADDRESS(1, _xlpm.posicion + 5, 4), _xlpm.letraColumna, SUBSTITUTE(_xlpm.direccionCompleta, "1", ""), _xlpm.letraColumna )} -> #N/A | Y52: {=_xlfn.LET( _xlpm.valor, INDEX(CostRate!I:I, MATCH(1, (CostRate!A:A=N52)*(CostRate!B:B=O52), 0)), _xlpm.posicion, MATCH(_xlpm.valor, FilterJP!$E$1:$FZ$1, 0), _xlpm.direccionCompleta, ADDRESS(1, _xlpm.posicion + 4, 4), _xlpm.letraColumna, SUBSTITUTE(_xlpm.direccionCompleta, "1", ""), _xlpm.letraColumna )} -> #N/A | AC52: =ROUNDUP($V52/(1-$AV$28),2) -> 0 | AD52: =$T52*$AC52 -> 0 | AE52: =IFERROR(1-($W52/$AD52),0) -> 0 | AG52: =IFERROR(IF(OR(ISBLANK(N52),N52=CustomerCountry,COUNTIF($N52,"*xDC*")),0,10%),0) -> 0 | AH52: =W52*AG52 -> 0 | AJ52: {=IFERROR(INDEX(WHT!$C$7:$W$18,MATCH( _xlfn.SWITCH(N52,"xDC Medellin","Colombia","xDC Belo Horizonte","Brazil","xDC Guadalajara","Mexico","xDC Gurugram","India","xDC Leon","Spain","xDC San Jose","Costa Rica","xDC Warsaw","Poland",N52), WHT!$B$7:$B$18,0),MATCH(CustomerCountry,WHT!$C$5:$W$5,0)),0)} -> 0 | AK52: =(W52+AH52)*AJ52 -> 0 | AM52: =SUM($AD52,$AH52,$AK52) -> 0 | AN52: =AM52+IFERROR(SUM($AN$31:$AN$36)*AM52/$AM$40,0) -> 0 | AO52: =IFERROR($AN52/$T52,0) -> 0 | AS52: X | AT52: =IF(AS52="x",AM52+((SUM($AN$31:$AN$36)+SUMIF($AS$42:$AS$71,"<>x",$AM$42:$AM$71))*IFERROR(AM52/SUMIF($AS$42:$AS$71,"x",$AM$42:$AM$71),0)),0) -> 0 | AV52: =IFERROR(AT52/T52,0) -> 0 | AW52: =IFERROR(AV52/BusinessCurrencyTRM,"N/A") -> 0
G53: 0 | H53: 0 | I53: 0 | J53: =IFERROR(G53/(1-(H53+I53)),0) -> 0 | S53: =IF(ISBLANK(P53),0,$O$34*20) -> 0 | T53: =IF(ISBLANK($P53),0,IF(Approach="Team-Based",$Q53*$R53*$S53*HoursPerDayTeamBased,$J53)) -> 0 | U53: 0 | V53: =ROUNDUP(IFERROR(INDEX(CostRateTbl[Cost Rate],MATCH(_xlfn.CONCAT(N53,O53,P53,"NA"),CostRateTbl[KeyCostRate],0)),0)*BillingCurrencyTRM*(1+U53),2) -> 0 | W53: =T53*V53 -> 0 | X53: {=_xlfn.LET( _xlpm.valor, INDEX(CostRate!H:H, MATCH(1, (CostRate!A:A=N53)*1, 0)), _xlpm.posicion, MATCH(_xlpm.valor, FilterSL!$F$1:$Z$1, 0), _xlpm.direccionCompleta, ADDRESS(1, _xlpm.posicion + 5, 4), _xlpm.letraColumna, SUBSTITUTE(_xlpm.direccionCompleta, "1", ""), _xlpm.letraColumna )} -> #N/A | Y53: {=_xlfn.LET( _xlpm.valor, INDEX(CostRate!I:I, MATCH(1, (CostRate!A:A=N53)*(CostRate!B:B=O53), 0)), _xlpm.posicion, MATCH(_xlpm.valor, FilterJP!$E$1:$FZ$1, 0), _xlpm.direccionCompleta, ADDRESS(1, _xlpm.posicion + 4, 4), _xlpm.letraColumna, SUBSTITUTE(_xlpm.direccionCompleta, "1", ""), _xlpm.letraColumna )} -> #N/A | AC53: =ROUNDUP($V53/(1-$AV$28),2) -> 0 | AD53: =$T53*$AC53 -> 0 | AE53: =IFERROR(1-($W53/$AD53),0) -> 0 | AG53: =IFERROR(IF(OR(ISBLANK(N53),N53=CustomerCountry,COUNTIF($N53,"*xDC*")),0,10%),0) -> 0 | AH53: =W53*AG53 -> 0 | AJ53: {=IFERROR(INDEX(WHT!$C$7:$W$18,MATCH( _xlfn.SWITCH(N53,"xDC Medellin","Colombia","xDC Belo Horizonte","Brazil","xDC Guadalajara","Mexico","xDC Gurugram","India","xDC Leon","Spain","xDC San Jose","Costa Rica","xDC Warsaw","Poland",N53), WHT!$B$7:$B$18,0),MATCH(CustomerCountry,WHT!$C$5:$W$5,0)),0)} -> 0 | AK53: =(W53+AH53)*AJ53 -> 0 | AM53: =SUM($AD53,$AH53,$AK53) -> 0 | AN53: =AM53+IFERROR(SUM($AN$31:$AN$36)*AM53/$AM$40,0) -> 0 | AO53: =IFERROR($AN53/$T53,0) -> 0 | AS53: X | AT53: =IF(AS53="x",AM53+((SUM($AN$31:$AN$36)+SUMIF($AS$42:$AS$71,"<>x",$AM$42:$AM$71))*IFERROR(AM53/SUMIF($AS$42:$AS$71,"x",$AM$42:$AM$71),0)),0) -> 0 | AV53: =IFERROR(AT53/T53,0) -> 0 | AW53: =IFERROR(AV53/BusinessCurrencyTRM,"N/A") -> 0
G54: 0 | H54: 0 | I54: 0 | J54: =IFERROR(G54/(1-(H54+I54)),0) -> 0 | S54: =IF(ISBLANK(P54),0,$O$34*20) -> 0 | T54: =IF(ISBLANK($P54),0,IF(Approach="Team-Based",$Q54*$R54*$S54*HoursPerDayTeamBased,$J54)) -> 0 | U54: 0 | V54: =ROUNDUP(IFERROR(INDEX(CostRateTbl[Cost Rate],MATCH(_xlfn.CONCAT(N54,O54,P54,"NA"),CostRateTbl[KeyCostRate],0)),0)*BillingCurrencyTRM*(1+U54),2) -> 0 | W54: =T54*V54 -> 0 | X54: {=_xlfn.LET( _xlpm.valor, INDEX(CostRate!H:H, MATCH(1, (CostRate!A:A=N54)*1, 0)), _xlpm.posicion, MATCH(_xlpm.valor, FilterSL!$F$1:$Z$1, 0), _xlpm.direccionCompleta, ADDRESS(1, _xlpm.posicion + 5, 4), _xlpm.letraColumna, SUBSTITUTE(_xlpm.direccionCompleta, "1", ""), _xlpm.letraColumna )} -> #N/A | Y54: {=_xlfn.LET( _xlpm.valor, INDEX(CostRate!I:I, MATCH(1, (CostRate!A:A=N54)*(CostRate!B:B=O54), 0)), _xlpm.posicion, MATCH(_xlpm.valor, FilterJP!$E$1:$FZ$1, 0), _xlpm.direccionCompleta, ADDRESS(1, _xlpm.posicion + 4, 4), _xlpm.letraColumna, SUBSTITUTE(_xlpm.direccionCompleta, "1", ""), _xlpm.letraColumna )} -> #N/A | AC54: =ROUNDUP($V54/(1-$AV$28),2) -> 0 | AD54: =$T54*$AC54 -> 0 | AE54: =IFERROR(1-($W54/$AD54),0) -> 0 | AG54: =IFERROR(IF(OR(ISBLANK(N54),N54=CustomerCountry,COUNTIF($N54,"*xDC*")),0,10%),0) -> 0 | AH54: =W54*AG54 -> 0 | AJ54: {=IFERROR(INDEX(WHT!$C$7:$W$18,MATCH( _xlfn.SWITCH(N54,"xDC Medellin","Colombia","xDC Belo Horizonte","Brazil","xDC Guadalajara","Mexico","xDC Gurugram","India","xDC Leon","Spain","xDC San Jose","Costa Rica","xDC Warsaw","Poland",N54), WHT!$B$7:$B$18,0),MATCH(CustomerCountry,WHT!$C$5:$W$5,0)),0)} -> 0 | AK54: =(W54+AH54)*AJ54 -> 0 | AM54: =SUM($AD54,$AH54,$AK54) -> 0 | AN54: =AM54+IFERROR(SUM($AN$31:$AN$36)*AM54/$AM$40,0) -> 0 | AO54: =IFERROR($AN54/$T54,0) -> 0 | AS54: X | AT54: =IF(AS54="x",AM54+((SUM($AN$31:$AN$36)+SUMIF($AS$42:$AS$71,"<>x",$AM$42:$AM$71))*IFERROR(AM54/SUMIF($AS$42:$AS$71,"x",$AM$42:$AM$71),0)),0) -> 0 | AV54: =IFERROR(AT54/T54,0) -> 0 | AW54: =IFERROR(AV54/BusinessCurrencyTRM,"N/A") -> 0
G55: 0 | H55: 0 | I55: 0 | J55: =IFERROR(G55/(1-(H55+I55)),0) -> 0 | S55: =IF(ISBLANK(P55),0,$O$34*20) -> 0 | T55: =IF(ISBLANK($P55),0,IF(Approach="Team-Based",$Q55*$R55*$S55*HoursPerDayTeamBased,$J55)) -> 0 | U55: 0 | V55: =ROUNDUP(IFERROR(INDEX(CostRateTbl[Cost Rate],MATCH(_xlfn.CONCAT(N55,O55,P55,"NA"),CostRateTbl[KeyCostRate],0)),0)*BillingCurrencyTRM*(1+U55),2) -> 0 | W55: =T55*V55 -> 0 | X55: {=_xlfn.LET( _xlpm.valor, INDEX(CostRate!H:H, MATCH(1, (CostRate!A:A=N55)*1, 0)), _xlpm.posicion, MATCH(_xlpm.valor, FilterSL!$F$1:$Z$1, 0), _xlpm.direccionCompleta, ADDRESS(1, _xlpm.posicion + 5, 4), _xlpm.letraColumna, SUBSTITUTE(_xlpm.direccionCompleta, "1", ""), _xlpm.letraColumna )} -> #N/A | Y55: {=_xlfn.LET( _xlpm.valor, INDEX(CostRate!I:I, MATCH(1, (CostRate!A:A=N55)*(CostRate!B:B=O55), 0)), _xlpm.posicion, MATCH(_xlpm.valor, FilterJP!$E$1:$FZ$1, 0), _xlpm.direccionCompleta, ADDRESS(1, _xlpm.posicion + 4, 4), _xlpm.letraColumna, SUBSTITUTE(_xlpm.direccionCompleta, "1", ""), _xlpm.letraColumna )} -> #N/A | AC55: =ROUNDUP($V55/(1-$AV$28),2) -> 0 | AD55: =$T55*$AC55 -> 0 | AE55: =IFERROR(1-($W55/$AD55),0) -> 0 | AG55: =IFERROR(IF(OR(ISBLANK(N55),N55=CustomerCountry,COUNTIF($N55,"*xDC*")),0,10%),0) -> 0 | AH55: =W55*AG55 -> 0 | AJ55: {=IFERROR(INDEX(WHT!$C$7:$W$18,MATCH( _xlfn.SWITCH(N55,"xDC Medellin","Colombia","xDC Belo Horizonte","Brazil","xDC Guadalajara","Mexico","xDC Gurugram","India","xDC Leon","Spain","xDC San Jose","Costa Rica","xDC Warsaw","Poland",N55), WHT!$B$7:$B$18,0),MATCH(CustomerCountry,WHT!$C$5:$W$5,0)),0)} -> 0 | AK55: =(W55+AH55)*AJ55 -> 0 | AM55: =SUM($AD55,$AH55,$AK55) -> 0 | AN55: =AM55+IFERROR(SUM($AN$31:$AN$36)*AM55/$AM$40,0) -> 0 | AO55: =IFERROR($AN55/$T55,0) -> 0 | AS55: X | AT55: =IF(AS55="x",AM55+((SUM($AN$31:$AN$36)+SUMIF($AS$42:$AS$71,"<>x",$AM$42:$AM$71))*IFERROR(AM55/SUMIF($AS$42:$AS$71,"x",$AM$42:$AM$71),0)),0) -> 0 | AV55: =IFERROR(AT55/T55,0) -> 0 | AW55: =IFERROR(AV55/BusinessCurrencyTRM,"N/A") -> 0
G56: 0 | H56: 0 | I56: 0 | J56: =IFERROR(G56/(1-(H56+I56)),0) -> 0 | S56: =IF(ISBLANK(P56),0,$O$34*20) -> 0 | T56: =IF(ISBLANK($P56),0,IF(Approach="Team-Based",$Q56*$R56*$S56*HoursPerDayTeamBased,$J56)) -> 0 | U56: 0 | V56: =ROUNDUP(IFERROR(INDEX(CostRateTbl[Cost Rate],MATCH(_xlfn.CONCAT(N56,O56,P56,"NA"),CostRateTbl[KeyCostRate],0)),0)*BillingCurrencyTRM*(1+U56),2) -> 0 | W56: =T56*V56 -> 0 | X56: {=_xlfn.LET( _xlpm.valor, INDEX(CostRate!H:H, MATCH(1, (CostRate!A:A=N56)*1, 0)), _xlpm.posicion, MATCH(_xlpm.valor, FilterSL!$F$1:$Z$1, 0), _xlpm.direccionCompleta, ADDRESS(1, _xlpm.posicion + 5, 4), _xlpm.letraColumna, SUBSTITUTE(_xlpm.direccionCompleta, "1", ""), _xlpm.letraColumna )} -> #N/A | Y56: {=_xlfn.LET( _xlpm.valor, INDEX(CostRate!I:I, MATCH(1, (CostRate!A:A=N56)*(CostRate!B:B=O56), 0)), _xlpm.posicion, MATCH(_xlpm.valor, FilterJP!$E$1:$FZ$1, 0), _xlpm.direccionCompleta, ADDRESS(1, _xlpm.posicion + 4, 4), _xlpm.letraColumna, SUBSTITUTE(_xlpm.direccionCompleta, "1", ""), _xlpm.letraColumna )} -> #N/A | AC56: =ROUNDUP($V56/(1-$AV$28),2) -> 0 | AD56: =$T56*$AC56 -> 0 | AE56: =IFERROR(1-($W56/$AD56),0) -> 0 | AG56: =IFERROR(IF(OR(ISBLANK(N56),N56=CustomerCountry,COUNTIF($N56,"*xDC*")),0,10%),0) -> 0 | AH56: =W56*AG56 -> 0 | AJ56: {=IFERROR(INDEX(WHT!$C$7:$W$18,MATCH( _xlfn.SWITCH(N56,"xDC Medellin","Colombia","xDC Belo Horizonte","Brazil","xDC Guadalajara","Mexico","xDC Gurugram","India","xDC Leon","Spain","xDC San Jose","Costa Rica","xDC Warsaw","Poland",N56), WHT!$B$7:$B$18,0),MATCH(CustomerCountry,WHT!$C$5:$W$5,0)),0)} -> 0 | AK56: =(W56+AH56)*AJ56 -> 0 | AM56: =SUM($AD56,$AH56,$AK56) -> 0 | AN56: =AM56+IFERROR(SUM($AN$31:$AN$36)*AM56/$AM$40,0) -> 0 | AO56: =IFERROR($AN56/$T56,0) -> 0 | AS56: X | AT56: =IF(AS56="x",AM56+((SUM($AN$31:$AN$36)+SUMIF($AS$42:$AS$71,"<>x",$AM$42:$AM$71))*IFERROR(AM56/SUMIF($AS$42:$AS$71,"x",$AM$42:$AM$71),0)),0) -> 0 | AV56: =IFERROR(AT56/T56,0) -> 0 | AW56: =IFERROR(AV56/BusinessCurrencyTRM,"N/A") -> 0
G57: 0 | H57: 0 | I57: 0 | J57: =IFERROR(G57/(1-(H57+I57)),0) -> 0 | S57: =IF(ISBLANK(P57),0,$O$34*20) -> 0 | T57: =IF(ISBLANK($P57),0,IF(Approach="Team-Based",$Q57*$R57*$S57*HoursPerDayTeamBased,$J57)) -> 0 | U57: 0 | V57: =ROUNDUP(IFERROR(INDEX(CostRateTbl[Cost Rate],MATCH(_xlfn.CONCAT(N57,O57,P57,"NA"),CostRateTbl[KeyCostRate],0)),0)*BillingCurrencyTRM*(1+U57),2) -> 0 | W57: =T57*V57 -> 0 | X57: {=_xlfn.LET( _xlpm.valor, INDEX(CostRate!H:H, MATCH(1, (CostRate!A:A=N57)*1, 0)), _xlpm.posicion, MATCH(_xlpm.valor, FilterSL!$F$1:$Z$1, 0), _xlpm.direccionCompleta, ADDRESS(1, _xlpm.posicion + 5, 4), _xlpm.letraColumna, SUBSTITUTE(_xlpm.direccionCompleta, "1", ""), _xlpm.letraColumna )} -> #N/A | Y57: {=_xlfn.LET( _xlpm.valor, INDEX(CostRate!I:I, MATCH(1, (CostRate!A:A=N57)*(CostRate!B:B=O57), 0)), _xlpm.posicion, MATCH(_xlpm.valor, FilterJP!$E$1:$FZ$1, 0), _xlpm.direccionCompleta, ADDRESS(1, _xlpm.posicion + 4, 4), _xlpm.letraColumna, SUBSTITUTE(_xlpm.direccionCompleta, "1", ""), _xlpm.letraColumna )} -> #N/A | AC57: =ROUNDUP($V57/(1-$AV$28),2) -> 0 | AD57: =$T57*$AC57 -> 0 | AE57: =IFERROR(1-($W57/$AD57),0) -> 0 | AG57: =IFERROR(IF(OR(ISBLANK(N57),N57=CustomerCountry,COUNTIF($N57,"*xDC*")),0,10%),0) -> 0 | AH57: =W57*AG57 -> 0 | AJ57: {=IFERROR(INDEX(WHT!$C$7:$W$18,MATCH( _xlfn.SWITCH(N57,"xDC Medellin","Colombia","xDC Belo Horizonte","Brazil","xDC Guadalajara","Mexico","xDC Gurugram","India","xDC Leon","Spain","xDC San Jose","Costa Rica","xDC Warsaw","Poland",N57), WHT!$B$7:$B$18,0),MATCH(CustomerCountry,WHT!$C$5:$W$5,0)),0)} -> 0 | AK57: =(W57+AH57)*AJ57 -> 0 | AM57: =SUM($AD57,$AH57,$AK57) -> 0 | AN57: =AM57+IFERROR(SUM($AN$31:$AN$36)*AM57/$AM$40,0) -> 0 | AO57: =IFERROR($AN57/$T57,0) -> 0 | AS57: X | AT57: =IF(AS57="x",AM57+((SUM($AN$31:$AN$36)+SUMIF($AS$42:$AS$71,"<>x",$AM$42:$AM$71))*IFERROR(AM57/SUMIF($AS$42:$AS$71,"x",$AM$42:$AM$71),0)),0) -> 0 | AV57: =IFERROR(AT57/T57,0) -> 0 | AW57: =IFERROR(AV57/BusinessCurrencyTRM,"N/A") -> 0
G58: 0 | H58: 0 | I58: 0 | J58: =IFERROR(G58/(1-(H58+I58)),0) -> 0 | S58: =IF(ISBLANK(P58),0,$O$34*20) -> 0 | T58: =IF(ISBLANK($P58),0,IF(Approach="Team-Based",$Q58*$R58*$S58*HoursPerDayTeamBased,$J58)) -> 0 | U58: 0 | V58: =ROUNDUP(IFERROR(INDEX(CostRateTbl[Cost Rate],MATCH(_xlfn.CONCAT(N58,O58,P58,"NA"),CostRateTbl[KeyCostRate],0)),0)*BillingCurrencyTRM*(1+U58),2) -> 0 | W58: =T58*V58 -> 0 | X58: {=_xlfn.LET( _xlpm.valor, INDEX(CostRate!H:H, MATCH(1, (CostRate!A:A=N58)*1, 0)), _xlpm.posicion, MATCH(_xlpm.valor, FilterSL!$F$1:$Z$1, 0), _xlpm.direccionCompleta, ADDRESS(1, _xlpm.posicion + 5, 4), _xlpm.letraColumna, SUBSTITUTE(_xlpm.direccionCompleta, "1", ""), _xlpm.letraColumna )} -> #N/A | Y58: {=_xlfn.LET( _xlpm.valor, INDEX(CostRate!I:I, MATCH(1, (CostRate!A:A=N58)*(CostRate!B:B=O58), 0)), _xlpm.posicion, MATCH(_xlpm.valor, FilterJP!$E$1:$FZ$1, 0), _xlpm.direccionCompleta, ADDRESS(1, _xlpm.posicion + 4, 4), _xlpm.letraColumna, SUBSTITUTE(_xlpm.direccionCompleta, "1", ""), _xlpm.letraColumna )} -> #N/A | AC58: =ROUNDUP($V58/(1-$AV$28),2) -> 0 | AD58: =$T58*$AC58 -> 0 | AE58: =IFERROR(1-($W58/$AD58),0) -> 0 | AG58: =IFERROR(IF(OR(ISBLANK(N58),N58=CustomerCountry,COUNTIF($N58,"*xDC*")),0,10%),0) -> 0 | AH58: =W58*AG58 -> 0 | AJ58: {=IFERROR(INDEX(WHT!$C$7:$W$18,MATCH( _xlfn.SWITCH(N58,"xDC Medellin","Colombia","xDC Belo Horizonte","Brazil","xDC Guadalajara","Mexico","xDC Gurugram","India","xDC Leon","Spain","xDC San Jose","Costa Rica","xDC Warsaw","Poland",N58), WHT!$B$7:$B$18,0),MATCH(CustomerCountry,WHT!$C$5:$W$5,0)),0)} -> 0 | AK58: =(W58+AH58)*AJ58 -> 0 | AM58: =SUM($AD58,$AH58,$AK58) -> 0 | AN58: =AM58+IFERROR(SUM($AN$31:$AN$36)*AM58/$AM$40,0) -> 0 | AO58: =IFERROR($AN58/$T58,0) -> 0 | AS58: X | AT58: =IF(AS58="x",AM58+((SUM($AN$31:$AN$36)+SUMIF($AS$42:$AS$71,"<>x",$AM$42:$AM$71))*IFERROR(AM58/SUMIF($AS$42:$AS$71,"x",$AM$42:$AM$71),0)),0) -> 0 | AV58: =IFERROR(AT58/T58,0) -> 0 | AW58: =IFERROR(AV58/BusinessCurrencyTRM,"N/A") -> 0
G59: 0 | H59: 0 | I59: 0 | J59: =IFERROR(G59/(1-(H59+I59)),0) -> 0 | S59: =IF(ISBLANK(P59),0,$O$34*20) -> 0 | T59: =IF(ISBLANK($P59),0,IF(Approach="Team-Based",$Q59*$R59*$S59*HoursPerDayTeamBased,$J59)) -> 0 | U59: 0 | V59: =ROUNDUP(IFERROR(INDEX(CostRateTbl[Cost Rate],MATCH(_xlfn.CONCAT(N59,O59,P59,"NA"),CostRateTbl[KeyCostRate],0)),0)*BillingCurrencyTRM*(1+U59),2) -> 0 | W59: =T59*V59 -> 0 | X59: {=_xlfn.LET( _xlpm.valor, INDEX(CostRate!H:H, MATCH(1, (CostRate!A:A=N59)*1, 0)), _xlpm.posicion, MATCH(_xlpm.valor, FilterSL!$F$1:$Z$1, 0), _xlpm.direccionCompleta, ADDRESS(1, _xlpm.posicion + 5, 4), _xlpm.letraColumna, SUBSTITUTE(_xlpm.direccionCompleta, "1", ""), _xlpm.letraColumna )} -> #N/A | Y59: {=_xlfn.LET( _xlpm.valor, INDEX(CostRate!I:I, MATCH(1, (CostRate!A:A=N59)*(CostRate!B:B=O59), 0)), _xlpm.posicion, MATCH(_xlpm.valor, FilterJP!$E$1:$FZ$1, 0), _xlpm.direccionCompleta, ADDRESS(1, _xlpm.posicion + 4, 4), _xlpm.letraColumna, SUBSTITUTE(_xlpm.direccionCompleta, "1", ""), _xlpm.letraColumna )} -> #N/A | AC59: =ROUNDUP($V59/(1-$AV$28),2) -> 0 | AD59: =$T59*$AC59 -> 0 | AE59: =IFERROR(1-($W59/$AD59),0) -> 0 | AG59: =IFERROR(IF(OR(ISBLANK(N59),N59=CustomerCountry,COUNTIF($N59,"*xDC*")),0,10%),0) -> 0 | AH59: =W59*AG59 -> 0 | AJ59: {=IFERROR(INDEX(WHT!$C$7:$W$18,MATCH( _xlfn.SWITCH(N59,"xDC Medellin","Colombia","xDC Belo Horizonte","Brazil","xDC Guadalajara","Mexico","xDC Gurugram","India","xDC Leon","Spain","xDC San Jose","Costa Rica","xDC Warsaw","Poland",N59), WHT!$B$7:$B$18,0),MATCH(CustomerCountry,WHT!$C$5:$W$5,0)),0)} -> 0 | AK59: =(W59+AH59)*AJ59 -> 0 | AM59: =SUM($AD59,$AH59,$AK59) -> 0 | AN59: =AM59+IFERROR(SUM($AN$31:$AN$36)*AM59/$AM$40,0) -> 0 | AO59: =IFERROR($AN59/$T59,0) -> 0 | AS59: X | AT59: =IF(AS59="x",AM59+((SUM($AN$31:$AN$36)+SUMIF($AS$42:$AS$71,"<>x",$AM$42:$AM$71))*IFERROR(AM59/SUMIF($AS$42:$AS$71,"x",$AM$42:$AM$71),0)),0) -> 0 | AV59: =IFERROR(AT59/T59,0) -> 0 | AW59: =IFERROR(AV59/BusinessCurrencyTRM,"N/A") -> 0
G60: 0 | H60: 0 | I60: 0 | J60: =IFERROR(G60/(1-(H60+I60)),0) -> 0 | S60: =IF(ISBLANK(P60),0,$O$34*20) -> 0 | T60: =IF(ISBLANK($P60),0,IF(Approach="Team-Based",$Q60*$R60*$S60*HoursPerDayTeamBased,$J60)) -> 0 | U60: 0 | V60: =ROUNDUP(IFERROR(INDEX(CostRateTbl[Cost Rate],MATCH(_xlfn.CONCAT(N60,O60,P60,"NA"),CostRateTbl[KeyCostRate],0)),0)*BillingCurrencyTRM*(1+U60),2) -> 0 | W60: =T60*V60 -> 0 | X60: {=_xlfn.LET( _xlpm.valor, INDEX(CostRate!H:H, MATCH(1, (CostRate!A:A=N60)*1, 0)), _xlpm.posicion, MATCH(_xlpm.valor, FilterSL!$F$1:$Z$1, 0), _xlpm.direccionCompleta, ADDRESS(1, _xlpm.posicion + 5, 4), _xlpm.letraColumna, SUBSTITUTE(_xlpm.direccionCompleta, "1", ""), _xlpm.letraColumna )} -> #N/A | Y60: {=_xlfn.LET( _xlpm.valor, INDEX(CostRate!I:I, MATCH(1, (CostRate!A:A=N60)*(CostRate!B:B=O60), 0)), _xlpm.posicion, MATCH(_xlpm.valor, FilterJP!$E$1:$FZ$1, 0), _xlpm.direccionCompleta, ADDRESS(1, _xlpm.posicion + 4, 4), _xlpm.letraColumna, SUBSTITUTE(_xlpm.direccionCompleta, "1", ""), _xlpm.letraColumna )} -> #N/A | AC60: =ROUNDUP($V60/(1-$AV$28),2) -> 0 | AD60: =$T60*$AC60 -> 0 | AE60: =IFERROR(1-($W60/$AD60),0) -> 0 | AG60: =IFERROR(IF(OR(ISBLANK(N60),N60=CustomerCountry,COUNTIF($N60,"*xDC*")),0,10%),0) -> 0 | AH60: =W60*AG60 -> 0 | AJ60: {=IFERROR(INDEX(WHT!$C$7:$W$18,MATCH( _xlfn.SWITCH(N60,"xDC Medellin","Colombia","xDC Belo Horizonte","Brazil","xDC Guadalajara","Mexico","xDC Gurugram","India","xDC Leon","Spain","xDC San Jose","Costa Rica","xDC Warsaw","Poland",N60), WHT!$B$7:$B$18,0),MATCH(CustomerCountry,WHT!$C$5:$W$5,0)),0)} -> 0 | AK60: =(W60+AH60)*AJ60 -> 0 | AM60: =SUM($AD60,$AH60,$AK60) -> 0 | AN60: =AM60+IFERROR(SUM($AN$31:$AN$36)*AM60/$AM$40,0) -> 0 | AO60: =IFERROR($AN60/$T60,0) -> 0 | AS60: X | AT60: =IF(AS60="x",AM60+((SUM($AN$31:$AN$36)+SUMIF($AS$42:$AS$71,"<>x",$AM$42:$AM$71))*IFERROR(AM60/SUMIF($AS$42:$AS$71,"x",$AM$42:$AM$71),0)),0) -> 0 | AV60: =IFERROR(AT60/T60,0) -> 0 | AW60: =IFERROR(AV60/BusinessCurrencyTRM,"N/A") -> 0
... G71: 0 | H71: 0 | I71: 0 | J71: =IFERROR(G71/(1-(H71+I71)),0) -> 0 | S71: =IF(ISBLANK(P71),0,$O$34*20) -> 0 | T71: =IF(ISBLANK($P71),0,IF(Approach="Team-Based",$Q71*$R71*$S71*HoursPerDayTeamBased,$J71)) -> 0 | U71: 0 | V71: =ROUNDUP(IFERROR(INDEX(CostRateTbl[Cost Rate],MATCH(_xlfn.CONCAT(N71,O71,P71,"NA"),CostRateTbl[KeyCostRate],0)),0)*BillingCurrencyTRM*(1+U71),2) -> 0 | W71: =T71*V71 -> 0 | X71: {=_xlfn.LET( _xlpm.valor, INDEX(CostRate!H:H, MATCH(1, (CostRate!A:A=N71)*1, 0)), _xlpm.posicion, MATCH(_xlpm.valor, FilterSL!$F$1:$Z$1, 0), _xlpm.direccionCompleta, ADDRESS(1, _xlpm.posicion + 5, 4), _xlpm.letraColumna, SUBSTITUTE(_xlpm.direccionCompleta, "1", ""), _xlpm.letraColumna )} -> #N/A | Y71: {=_xlfn.LET( _xlpm.valor, INDEX(CostRate!I:I, MATCH(1, (CostRate!A:A=N71)*(CostRate!B:B=O71), 0)), _xlpm.posicion, MATCH(_xlpm.valor, FilterJP!$E$1:$FZ$1, 0), _xlpm.direccionCompleta, ADDRESS(1, _xlpm.posicion + 4, 4), _xlpm.letraColumna, SUBSTITUTE(_xlpm.direccionCompleta, "1", ""), _xlpm.letraColumna )} -> #N/A | AC71: =ROUNDUP($V71/(1-$AV$28),2) -> 0 | AD71: =$T71*$AC71 -> 0 | AE71: =IFERROR(1-($W71/$AD71),0) -> 0 | AG71: =IFERROR(IF(OR(ISBLANK(N71),N71=CustomerCountry,COUNTIF($N71,"*xDC*")),0,10%),0) -> 0 | AH71: =W71*AG71 -> 0 | AJ71: {=IFERROR(INDEX(WHT!$C$7:$W$18,MATCH( _xlfn.SWITCH(N71,"xDC Medellin","Colombia","xDC Belo Horizonte","Brazil","xDC Guadalajara","Mexico","xDC Gurugram","India","xDC Leon","Spain","xDC San Jose","Costa Rica","xDC Warsaw","Poland",N71), WHT!$B$7:$B$18,0),MATCH(CustomerCountry,WHT!$C$5:$W$5,0)),0)} -> 0 | AK71: =(W71+AH71)*AJ71 -> 0 | AM71: =SUM($AD71,$AH71,$AK71) -> 0 | AN71: =AM71+IFERROR(SUM($AN$31:$AN$36)*AM71/$AM$40,0) -> 0 | AO71: =IFERROR($AN71/$T71,0) -> 0 | AS71: X | AT71: =IF(AS71="x",AM71+((SUM($AN$31:$AN$36)+SUMIF($AS$42:$AS$71,"<>x",$AM$42:$AM$71))*IFERROR(AM71/SUMIF($AS$42:$AS$71,"x",$AM$42:$AM$71),0)),0) -> 0 | AV71: =IFERROR(AT71/T71,0) -> 0 | AW71: =IFERROR(AV71/BusinessCurrencyTRM,"N/A") -> 0
B74: =CMSResumen!G3 -> Nombre de Suscripcion 1
N75: PROJECT WEIGHT BY PHASE | O75: Hours | P75: Percentage (%) | U75: COSTS BY PHASE | V75: =_xlfn.CONCAT("DELIVERY COST (",BillingCountryCurrency,")") -> DELIVERY COST (COP) | W75: =_xlfn.CONCAT("DELIVERY COST (",IF(ISBLANK(BusinessCurrency),"N/A",BusinessCurrency),")") -> DELIVERY COST (USD) | AC75: PRICE BY PHASE | AD75: =_xlfn.CONCAT("PRICING (",BillingCountryCurrency,")") -> PRICING (COP) | AE75: =_xlfn.CONCAT("PRICING (",IF(ISBLANK(BusinessCurrency),"N/A",BusinessCurrency),")") -> PRICING (USD) | AF75: + | AG75: =_xlfn.CONCAT("Intercompany (",BillingCountryCurrency,")") -> Intercompany (COP) | AH75: =_xlfn.CONCAT("Intercompany (",IF(ISBLANK(BusinessCurrency),"N/A",BusinessCurrency),")") -> Intercompany (USD) | AI75: + | AJ75: =_xlfn.CONCAT("WHT (",BillingCountryCurrency,")") -> WHT (COP) | AK75: =_xlfn.CONCAT("WHT (",IF(ISBLANK(BusinessCurrency),"N/A",BusinessCurrency),")") -> WHT (USD) | AM75: = | AN75: =_xlfn.CONCAT("SUBTOTAL PRICE (",BillingCountryCurrency,")") -> SUBTOTAL PRICE (COP) | AO75: =_xlfn.CONCAT("SUBTOTAL PRICE (",IF(ISBLANK(BusinessCurrency),"N/A",BusinessCurrency),")") -> SUBTOTAL PRICE (USD) | AS75: SUMMARY BY PHASE
N76: Consultant Team: | O76: =SUMIF($P90:$P119,"<>*Project Management*",$T90:$T119) -> 26.227638 | P76: =IFERROR(O76/O79,0) -> 0.82224389 | U76: Consultant Team | V76: =SUMIF(P90:P119,"<>*Project Management*",W90:W119) -> 1053222 | W76: =IFERROR(V76/BusinessCurrencyTRM,"N/A") -> 270.05691 | Y76: varTotalConsultant | AC76: Consultant Team | AD76: =SUMIF(P90:P119,"<>*Project Management*",AD90:AD119) -> 1504602.8 | AE76: =IFERROR(AD76/BusinessCurrencyTRM,"N/A") -> 385.79559 | AG76: =SUMIF(P90:P119,"<>*Project Management*",AH90:AH119) -> 0 | AH76: =IFERROR(AG76/BusinessCurrencyTRM,"N/A") -> 0 | AJ76: =SUMIF(P90:P119,"<>*Project Management*",AK90:AK119) -> 0 | AK76: =IFERROR(AJ76/BusinessCurrencyTRM,"N/A") -> 0 | AN76: =SUM(AD76,AG76,AJ76) -> 1504602.8 | AO76: =IFERROR(AN76/BusinessCurrencyTRM,"N/A") -> 385.79559 | AS76: % Margin a Sold * | AV76: =CMSResumen!H21 -> 0.3
N77: Project Managment: | O77: =SUMIF($P90:$P119,"=*Project Management*",$T90:T119) -> 5.67 | P77: =IFERROR(O77/O79,0) -> 0.17775611 | U77: Project Managment | V77: =SUMIF(P90:P119,"=*Project Management*",W90:W119) -> 0 | W77: =IFERROR(V77/BusinessCurrencyTRM,"N/A") -> 0 | Y77: varTotalPM | AC77: Project Managment | AD77: =SUMIF(P90:P119,"=*Project Management*",AD90:AD119) -> 0 | AE77: =IFERROR(AD77/BusinessCurrencyTRM,"N/A") -> 0 | AG77: =SUMIF(P90:P119,"=*Project Management*",AH90:AH119) -> 0 | AH77: =IFERROR(AG77/BusinessCurrencyTRM,"N/A") -> 0 | AJ77: =SUMIF(P90:P119,"=*Project Management*",AK90:AK119) -> 0 | AK77: =IFERROR(AJ77/BusinessCurrencyTRM,"N/A") -> 0 | AN77: =SUM(AD77,AG77,AJ77) -> 0 | AO77: =IFERROR(AN77/BusinessCurrencyTRM,"N/A") -> 0 | AS77: % Contribution Margin | AV77: =IFERROR(1-AV79/AV80,0) -> 0.30000001
N78: Risk / Extra Effort: | O78: =IF(Approach="Team-Based",SUM(O76:O77)*$O81,$J88-$G88) -> 0 | P78: =IFERROR(O78/O79,0) -> 0 | U78: Subtotal | V78: =SUM(V76:V77) -> 1053222 | W78: =IFERROR(V78/BusinessCurrencyTRM,"N/A") -> 270.05691 | AC78: Subtotal | AD78: =SUM(AD76:AD77) -> 1504602.8 | AE78: =IFERROR(AD78/BusinessCurrencyTRM,"N/A") -> 385.79559 | AG78: =SUM(AG76:AG77) -> 0 | AH78: =IFERROR(AG78/BusinessCurrencyTRM,"N/A") -> 0 | AJ78: =SUM(AJ76:AJ77) -> 0 | AK78: =IFERROR(AJ78/BusinessCurrencyTRM,"N/A") -> 0 | AN78: =SUM(AD78,AG78,AJ78) -> 1504602.8 | AO78: =IFERROR(AN78/BusinessCurrencyTRM,"N/A") -> 385.79559 | AV78: =BillingCountryCurrency -> COP | AW78: =IF(ISBLANK(BusinessCurrency),"N/A",BusinessCurrency) -> USD
N79: Total | O79: =SUM(O76:O78) -> 31.897638 | P79: =SUM(P76:P78) -> 1 | U79: Risks | V79: =ROUNDUP(V78*O81,2) -> 0 | W79: =IFERROR(V79/BusinessCurrencyTRM,"N/A") -> 0 | Y79: varTotalRisks | AC79: Risks | AD79: =ROUNDUP(V79/(1-$AV$76),2) -> 0 | AE79: =IFERROR(AD79/BusinessCurrencyTRM,"N/A") -> 0 | AG79: =IFERROR(V79*MAX(AG90:AG119),0) -> 0 | AH79: =IFERROR(AG79/BusinessCurrencyTRM,"N/A") -> 0 | AJ79: =IFERROR(SUM(V79,AG79)*MAX(AJ90:AJ119),0) -> 0 | AK79: =IFERROR(AJ79/BusinessCurrencyTRM,"N/A") -> 0 | AN79: =SUM(AD79,AG79,AJ79) -> 0 | AO79: =IFERROR(AN79/BusinessCurrencyTRM,"N/A") -> 0 | AS79: Phase Cost | AV79: =SUM(V85,AG85,AJ85) -> 1053222 | AW79: =IFERROR(AV79/BusinessCurrencyTRM,"N/A") -> 270.05691
U80: Pay Rise | V80: =IFERROR(SUMIF(PayRise!A:A,B74,PayRise!J:J),0) -> 0 | W80: =IFERROR(V80/BusinessCurrencyTRM,"N/A") -> 0 | Y80: varTotalPayRise | AC80: Pay Rise | AD80: =IFERROR(SUMIF(PayRise!A:A,B74,PayRise!K:K),0) -> 0 | AE80: =IFERROR(AD80/BusinessCurrencyTRM,"N/A") -> 0 | AG80: =IFERROR(SUMIF(PayRise!A:A,B74,PayRise!L:L),0) -> 0 | AH80: =IFERROR(AG80/BusinessCurrencyTRM,"N/A") -> 0 | AJ80: =IFERROR(SUMIF(PayRise!A:A,B74,PayRise!M:M),0) -> 0 | AK80: =IFERROR(AJ80/BusinessCurrencyTRM,"N/A") -> 0 | AN80: =SUM(AD80,AG80,AJ80) -> 0 | AO80: =IFERROR(AN80/BusinessCurrencyTRM,"N/A") -> 0 | AS80: Phase Price | AV80: =AN85 -> 1504602.8 | AW80: =IFERROR(AV80/BusinessCurrencyTRM,"N/A") -> 385.79559
N81: =IF(Approach="By Hours", "N/A for ByHours", "% Risks") -> % Risks | O81: 0 | U81: Products | V81: =IFERROR(SUMIFS(OtherCosts!Q:Q,OtherCosts!A:A,B74,OtherCosts!B:B,"Hardware/Software"),0) -> 0 | W81: =IFERROR(V81/BusinessCurrencyTRM,"N/A") -> 0 | Y81: varTotalProducts | AC81: Products | AD81: =IFERROR(SUMIFS(OtherCosts!R:R,OtherCosts!A:A,B74,OtherCosts!B:B,"Hardware/Software"),0) -> 0 | AE81: =IFERROR(AD81/BusinessCurrencyTRM,"N/A") -> 0 | AG81: =IFERROR(SUMIFS(OtherCosts!S:S,OtherCosts!A:A,B74,OtherCosts!B:B,"Hardware/Software"),0) -> 0 | AH81: =IFERROR(AG81/BusinessCurrencyTRM,"N/A") -> 0 | AJ81: =IFERROR(SUMIFS(OtherCosts!T:T,OtherCosts!A:A,B74,OtherCosts!B:B,"Hardware/Software"),0) -> 0 | AK81: =IFERROR(AJ81/BusinessCurrencyTRM,"N/A") -> 0 | AN81: =SUM(AD81,AG81,AJ81) -> 0 | AO81: =IFERROR(AN81/BusinessCurrencyTRM,"N/A") -> 0 | AS81: Monthly Price | AV81: =IFERROR(IF(O82<1,AN85,AN85/O82),0) -> 1504602.8 | AW81: =IFERROR(AV81/BusinessCurrencyTRM,"N/A") -> 385.79559
N82: =IF(Approach="By Hours", "N/A for ByHours", "Duration (Months) *") -> Duration (Months) * | O82: 0 | U82: Vendors | V82: =IFERROR(SUMIFS(OtherCosts!Q:Q,OtherCosts!A:A,B74,OtherCosts!B:B,"Vendor"),0) -> 0 | W82: =IFERROR(V82/BusinessCurrencyTRM,"N/A") -> 0 | Y82: varTotalVAR | AC82: Vendors | AD82: =IFERROR(SUMIFS(OtherCosts!R:R,OtherCosts!A:A,B74,OtherCosts!B:B,"Vendor"),0) -> 0 | AE82: =IFERROR(AD82/BusinessCurrencyTRM,"N/A") -> 0 | AG82: =IFERROR(SUMIFS(OtherCosts!S:S,OtherCosts!A:A,B74,OtherCosts!B:B,"Vendor"),0) -> 0 | AH82: =IFERROR(AG82/BusinessCurrencyTRM,"N/A") -> 0 | AJ82: =IFERROR(SUMIFS(OtherCosts!T:T,OtherCosts!A:A,B74,OtherCosts!B:B,"Vendor"),0) -> 0 | AK82: =IFERROR(AJ82/BusinessCurrencyTRM,"N/A") -> 0 | AN82: =SUM(AD82,AG82,AJ82) -> 0 | AO82: =IFERROR(AN82/BusinessCurrencyTRM,"N/A") -> 0 | AS82: Hour Price | AV82: =IFERROR(AN85/T88,0) -> 47166.232 | AW82: =IFERROR(AV82/BusinessCurrencyTRM,"N/A") -> 12.093906
U83: Insurances | V83: =IFERROR(SUMIFS(OtherCosts!Q:Q,OtherCosts!A:A,B74,OtherCosts!B:B,"Insurance"),0) -> 0 | W83: =IFERROR(V83/BusinessCurrencyTRM,"N/A") -> 0 | Y83: varTotalInsurances | AC83: Insurances | AD83: =IFERROR(SUMIFS(OtherCosts!R:R,OtherCosts!A:A,B74,OtherCosts!B:B,"Insurance"),0) -> 0 | AE83: =IFERROR(AD83/BusinessCurrencyTRM,"N/A") -> 0 | AG83: =IFERROR(SUMIFS(OtherCosts!S:S,OtherCosts!A:A,B74,OtherCosts!B:B,"Insurance"),0) -> 0 | AH83: =IFERROR(AG83/BusinessCurrencyTRM,"N/A") -> 0 | AJ83: =IFERROR(SUMIFS(OtherCosts!T:T,OtherCosts!A:A,B74,OtherCosts!B:B,"Insurance"),0) -> 0 | AK83: =IFERROR(AJ83/BusinessCurrencyTRM,"N/A") -> 0 | AN83: =SUM(AD83,AG83,AJ83) -> 0 | AO83: =IFERROR(AN83/BusinessCurrencyTRM,"N/A") -> 0
U84: Others | V84: =IFERROR(SUMIFS(OtherCosts!Q:Q,OtherCosts!A:A,B74,OtherCosts!B:B,"Other"),0) -> 0 | W84: =IFERROR(V84/BusinessCurrencyTRM,"N/A") -> 0 | Y84: varTotalOthers | AC84: Others | AD84: =IFERROR(SUMIFS(OtherCosts!R:R,OtherCosts!A:A,B74,OtherCosts!B:B,"Other"),0) -> 0 | AE84: =IFERROR(AD84/BusinessCurrencyTRM,"N/A") -> 0 | AG84: =IFERROR(SUMIFS(OtherCosts!S:S,OtherCosts!A:A,B74,OtherCosts!B:B,"Other"),0) -> 0 | AH84: =IFERROR(AG84/BusinessCurrencyTRM,"N/A") -> 0 | AJ84: =IFERROR(SUMIFS(OtherCosts!T:T,OtherCosts!A:A,B74,OtherCosts!B:B,"Other"),0) -> 0 | AK84: =IFERROR(AJ84/BusinessCurrencyTRM,"N/A") -> 0 | AN84: =SUM(AD84,AG84,AJ84) -> 0 | AO84: =IFERROR(AN84/BusinessCurrencyTRM,"N/A") -> 0
U85: Subtotal | V85: =SUM(V78:V84) -> 1053222 | W85: =IFERROR(V85/BusinessCurrencyTRM,"N/A") -> 270.05691 | AC85: Subtotal | AD85: =SUM(AD78:AD84) -> 1504602.8 | AE85: =IFERROR(AD85/BusinessCurrencyTRM,"N/A") -> 385.79559 | AG85: =SUM(AG78:AG84) -> 0 | AH85: =IFERROR(AG85/BusinessCurrencyTRM,"N/A") -> 0 | AJ85: =SUM(AJ78:AJ84) -> 0 | AK85: =IFERROR(AJ85/BusinessCurrencyTRM,"N/A") -> 0 | AN85: =SUM(AD85,AG85,AJ85) -> 1504602.8 | AO85: =IFERROR(AN85/BusinessCurrencyTRM,"N/A") -> 385.79559
G88: =ROUNDUP(SUM(G90:G119),2) -> 0 | J88: =ROUNDUP(SUM(J90:J119),2) -> 0 | T88: =ROUNDUP(SUM(T90:T119),2) -> 31.9 | W88: =SUM(W90:W117) -> 1053222 | Y88: varTotalFase | AD88: =SUM(AD90:AD119) -> 1504602.8 | AE88: =IFERROR(1-($W88/$AD88),0) -> 0.30000001 | AH88: =SUM(AH90:AH119) -> 0 | AK88: =ROUNDUP(SUM(AK90:AK119),2) -> 0 | AM88: =SUM(AM90:AM119) -> 1504602.8 | AN88: =SUM(AN90:AN119) -> 1504602.8 | AO88: =BillingCountryCurrency -> COP | AT88: =SUM(AT90:AU119) -> 1504602.8 | AV88: =BillingCountryCurrency -> COP | AW88: =IF(ISBLANK(BusinessCurrency),"N/A",BusinessCurrency) -> USD
G89: Hours | H89: Risk | I89: EE | J89: Total | N89: Delivery Country | O89: Services Line | P89: Job Profile | Q89: Qty | R89: % Allocation | S89: Days | T89: Total Hours | U89: % Surcharge Hours | V89: Unit Cost Base | W89: Subtotal Cost | X89: FilterSL | Y89: FilterJP | AC89: Unit Price Base | AD89: Subtotal Price | AE89: % MaS | AG89: % Intercomp | AH89: $ Intercompany | AJ89: % WHT | AK89: $ WHT | AM89: Subtotal Price | AN89: Subtotal Price + Costs | AO89: Unit Price + Costs | AS89: Fact | AT89: Subtotal Price + Costs | AV89: Unit Price + Cost | AW89: Unit Price + Cost
B90: Observaciones / Incluido: | C90: Gerencia del proyecto | G90: 0 | H90: 0 | I90: 0 | J90: =IFERROR(G90/(1-(H90+I90)),0) -> 0 | N90: xDC Medellin | O90: Other Services | P90: Expert Technology & Consulting Project Management | Q90: 1 | R90: {=$R$42*(1+(INDIRECT("CMSResumen!L"&(MAX(IF(INDIRECT("CMSResumen!B1:B"&ROW()-10)=B74,ROW(INDIRECT("CMSResumen!B1:B"&ROW()-10)),0)+17)))))} -> 0.035 | S90: 20 | T90: =IF(ISBLANK($P90),0,IF(Approach="Team-Based",$Q90*$R90*$S90*HoursPerDayTeamBased,$J90)) -> 5.67 | U90: 0 | V90: =ROUNDUP(IFERROR(INDEX(CostRateTbl[Cost Rate],MATCH(_xlfn.CONCAT(N90,O90,P90,"NA"),CostRateTbl[KeyCostRate],0)),0)*BillingCurrencyTRM*(1+U90),2) -> 0 | W90: =T90*V90 -> 0 | X90: {=_xlfn.LET( _xlpm.valor, INDEX(CostRate!H:H, MATCH(1, (CostRate!A:A=N90)*1, 0)), _xlpm.posicion, MATCH(_xlpm.valor, FilterSL!$F$1:$Z$1, 0), _xlpm.direccionCompleta, ADDRESS(1, _xlpm.posicion + 5, 4), _xlpm.letraColumna, SUBSTITUTE(_xlpm.direccionCompleta, "1", ""), _xlpm.letraColumna )} -> R | Y90: {=_xlfn.LET( _xlpm.valor, INDEX(CostRate!I:I, MATCH(1, (CostRate!A:A=N90)*(CostRate!B:B=O90), 0)), _xlpm.posicion, MATCH(_xlpm.valor, FilterJP!$E$1:$FZ$1, 0), _xlpm.direccionCompleta, ADDRESS(1, _xlpm.posicion + 4, 4), _xlpm.letraColumna, SUBSTITUTE(_xlpm.direccionCompleta, "1", ""), _xlpm.letraColumna )} -> BO | AC90: =ROUNDUP($V90/(1-$AV$76),2) -> 0 | AD90: =$T90*$AC90 -> 0 | AE90: =IFERROR(1-($W90/$AD90),0) -> 0 | AG90: =IFERROR(IF(OR(ISBLANK(N90),N90=CustomerCountry,COUNTIF($N90,"*xDC*")),0,10%),0) -> 0 | AH90: =W90*AG90 -> 0 | AJ90: {=IFERROR(INDEX(WHT!$C$7:$W$18,MATCH( _xlfn.SWITCH(N90,"xDC Medellin","Colombia","xDC Belo Horizonte","Brazil","xDC Guadalajara","Mexico","xDC Gurugram","India","xDC Leon","Spain","xDC San Jose","Costa Rica","xDC Warsaw","Poland",N90), WHT!$B$7:$B$18,0),MATCH(CustomerCountry,WHT!$C$5:$W$5,0)),0)} -> 0 | AK90: =(W90+AH90)*AJ90 -> 0 | AM90: =SUM($AD90,$AH90,$AK90) -> 0 | AN90: =AM90+IFERROR(SUM($AN$79:$AN$84)*AM90/$AM$88,0) -> 0 | AO90: =IFERROR($AN90/$T90,0) -> 0 | AS90: X | AT90: =IF(AS90="x",AM90+((SUM($AN$79:$AN$84)+SUMIF($AS$90:$AS$119,"<>x",$AM$90:$AM$119))*IFERROR(AM90/SUMIF($AS$90:$AS$119,"x",$AM$90:$AM$119),0)),0) -> 0 | AV90: =IFERROR(AT90/T90,0) -> 0 | AW90: =IFERROR(AV90/BusinessCurrencyTRM,"N/A") -> 0
C91: Administrador Azure | G91: 0 | H91: 0 | I91: 0 | J91: =IFERROR(G91/(1-(H91+I91)),0) -> 0 | N91: xDC Medellin | O91: Other Services | P91: Expert Managed Operations | Q91: 1 | R91: {=$R$43*(1+(INDIRECT("CMSResumen!L"&(MAX(IF(INDIRECT("CMSResumen!B1:B"&ROW()-10)=B73,ROW(INDIRECT("CMSResumen!B1:B"&ROW()-10)),0)+18)))))} -> 0.078 | S91: 20 | T91: =IF(ISBLANK($P91),0,IF(Approach="Team-Based",$Q91*$R91*$S91*HoursPerDayTeamBased,$J91)) -> 12.636 | U91: 0 | V91: =ROUNDUP(IFERROR(INDEX(CostRateTbl[Cost Rate],MATCH(_xlfn.CONCAT(N91,O91,P91,"NA"),CostRateTbl[KeyCostRate],0)),0)*BillingCurrencyTRM*(1+U91),2) -> 0 | W91: =T91*V91 -> 0 | X91: {=_xlfn.LET( _xlpm.valor, INDEX(CostRate!H:H, MATCH(1, (CostRate!A:A=N91)*1, 0)), _xlpm.posicion, MATCH(_xlpm.valor, FilterSL!$F$1:$Z$1, 0), _xlpm.direccionCompleta, ADDRESS(1, _xlpm.posicion + 5, 4), _xlpm.letraColumna, SUBSTITUTE(_xlpm.direccionCompleta, "1", ""), _xlpm.letraColumna )} -> R | Y91: {=_xlfn.LET( _xlpm.valor, INDEX(CostRate!I:I, MATCH(1, (CostRate!A:A=N91)*(CostRate!B:B=O91), 0)), _xlpm.posicion, MATCH(_xlpm.valor, FilterJP!$E$1:$FZ$1, 0), _xlpm.direccionCompleta, ADDRESS(1, _xlpm.posicion + 4, 4), _xlpm.letraColumna, SUBSTITUTE(_xlpm.direccionCompleta, "1", ""), _xlpm.letraColumna )} -> BO | AC91: =ROUNDUP($V91/(1-$AV$76),2) -> 0 | AD91: =$T91*$AC91 -> 0 | AE91: =IFERROR(1-($W91/$AD91),0) -> 0 | AG91: =IFERROR(IF(OR(ISBLANK(N91),N91=CustomerCountry,COUNTIF($N91,"*xDC*")),0,10%),0) -> 0 | AH91: =W91*AG91 -> 0 | AJ91: {=IFERROR(INDEX(WHT!$C$7:$W$18,MATCH( _xlfn.SWITCH(N91,"xDC Medellin","Colombia","xDC Belo Horizonte","Brazil","xDC Guadalajara","Mexico","xDC Gurugram","India","xDC Leon","Spain","xDC San Jose","Costa Rica","xDC Warsaw","Poland",N91), WHT!$B$7:$B$18,0),MATCH(CustomerCountry,WHT!$C$5:$W$5,0)),0)} -> 0 | AK91: =(W91+AH91)*AJ91 -> 0 | AM91: =SUM($AD91,$AH91,$AK91) -> 0 | AN91: =AM91+IFERROR(SUM($AN$79:$AN$84)*AM91/$AM$88,0) -> 0 | AO91: =IFERROR($AN91/$T91,0) -> 0 | AS91: X | AT91: =IF(AS91="x",AM91+((SUM($AN$79:$AN$84)+SUMIF($AS$90:$AS$119,"<>x",$AM$90:$AM$119))*IFERROR(AM91/SUMIF($AS$90:$AS$119,"x",$AM$90:$AM$119),0)),0) -> 0 | AV91: =IFERROR(AT91/T91,0) -> 0 | AW91: =IFERROR(AV91/BusinessCurrencyTRM,"N/A") -> 0
C92: Arquitecto / especialista | G92: 0 | H92: 0 | I92: 0 | J92: =IFERROR(G92/(1-(H92+I92)),0) -> 0 | N92: xDC Medellin | O92: Cloud Services Azure | P92: Expert Technology Implementation & Consulting (General) | Q92: 1 | R92: {=$R$44*(1+(INDIRECT("CMSResumen!L"&(MAX(IF(INDIRECT("CMSResumen!B1:B"&ROW()-10)=B73,ROW(INDIRECT("CMSResumen!B1:B"&ROW()-10)),0)+19)))))} -> 0.035 | S92: 20 | T92: =IF(ISBLANK($P92),0,IF(Approach="Team-Based",$Q92*$R92*$S92*HoursPerDayTeamBased,$J92)) -> 5.67 | U92: 0 | V92: =ROUNDUP(IFERROR(INDEX(CostRateTbl[Cost Rate],MATCH(_xlfn.CONCAT(N92,O92,P92,"NA"),CostRateTbl[KeyCostRate],0)),0)*BillingCurrencyTRM*(1+U92),2) -> 133425.46 | W92: =T92*V92 -> 756522.36 | X92: {=_xlfn.LET( _xlpm.valor, INDEX(CostRate!H:H, MATCH(1, (CostRate!A:A=N92)*1, 0)), _xlpm.posicion, MATCH(_xlpm.valor, FilterSL!$F$1:$Z$1, 0), _xlpm.direccionCompleta, ADDRESS(1, _xlpm.posicion + 5, 4), _xlpm.letraColumna, SUBSTITUTE(_xlpm.direccionCompleta, "1", ""), _xlpm.letraColumna )} -> R | Y92: {=_xlfn.LET( _xlpm.valor, INDEX(CostRate!I:I, MATCH(1, (CostRate!A:A=N92)*(CostRate!B:B=O92), 0)), _xlpm.posicion, MATCH(_xlpm.valor, FilterJP!$E$1:$FZ$1, 0), _xlpm.direccionCompleta, ADDRESS(1, _xlpm.posicion + 4, 4), _xlpm.letraColumna, SUBSTITUTE(_xlpm.direccionCompleta, "1", ""), _xlpm.letraColumna )} -> BI | AC92: =ROUNDUP($V92/(1-$AV$76),2) -> 190607.8 | AD92: =$T92*$AC92 -> 1080746.2 | AE92: =IFERROR(1-($W92/$AD92),0) -> 0.3 | AG92: =IFERROR(IF(OR(ISBLANK(N92),N92=CustomerCountry,COUNTIF($N92,"*xDC*")),0,10%),0) -> 0 | AH92: =W92*AG92 -> 0 | AJ92: {=IFERROR(INDEX(WHT!$C$7:$W$18,MATCH( _xlfn.SWITCH(N92,"xDC Medellin","Colombia","xDC Belo Horizonte","Brazil","xDC Guadalajara","Mexico","xDC Gurugram","India","xDC Leon","Spain","xDC San Jose","Costa Rica","xDC Warsaw","Poland",N92), WHT!$B$7:$B$18,0),MATCH(CustomerCountry,WHT!$C$5:$W$5,0)),0)} -> 0 | AK92: =(W92+AH92)*AJ92 -> 0 | AM92: =SUM($AD92,$AH92,$AK92) -> 1080746.2 | AN92: =AM92+IFERROR(SUM($AN$79:$AN$84)*AM92/$AM$88,0) -> 1080746.2 | AO92: =IFERROR($AN92/$T92,0) -> 190607.8 | AS92: X | AT92: =IF(AS92="x",AM92+((SUM($AN$79:$AN$84)+SUMIF($AS$90:$AS$119,"<>x",$AM$90:$AM$119))*IFERROR(AM92/SUMIF($AS$90:$AS$119,"x",$AM$90:$AM$119),0)),0) -> 1080746.2 | AV92: =IFERROR(AT92/T92,0) -> 190607.8 | AW92: =IFERROR(AV92/BusinessCurrencyTRM,"N/A") -> 48.873795
C93: Monitoreo / operación | G93: 0 | H93: 0 | I93: 0 | J93: =IFERROR(G93/(1-(H93+I93)),0) -> 0 | N93: xDC Medellin | O93: Other Services | P93: Associate Expert Managed Operations | Q93: 1 | R93: {=$R$45*(1+(INDIRECT("CMSResumen!L"&(MAX(IF(INDIRECT("CMSResumen!B1:B"&ROW()-10)=B73,ROW(INDIRECT("CMSResumen!B1:B"&ROW()-10)),0)+20)))))} -> 0.035 | S93: 20 | T93: =IF(ISBLANK($P93),0,IF(Approach="Team-Based",$Q93*$R93*$S93*HoursPerDayTeamBased,$J93)) -> 5.67 | U93: 0 | V93: =ROUNDUP(IFERROR(INDEX(CostRateTbl[Cost Rate],MATCH(_xlfn.CONCAT(N93,O93,P93,"NA"),CostRateTbl[KeyCostRate],0)),0)*BillingCurrencyTRM*(1+U93),2) -> 46596.59 | W93: =T93*V93 -> 264202.67 | X93: {=_xlfn.LET( _xlpm.valor, INDEX(CostRate!H:H, MATCH(1, (CostRate!A:A=N93)*1, 0)), _xlpm.posicion, MATCH(_xlpm.valor, FilterSL!$F$1:$Z$1, 0), _xlpm.direccionCompleta, ADDRESS(1, _xlpm.posicion + 5, 4), _xlpm.letraColumna, SUBSTITUTE(_xlpm.direccionCompleta, "1", ""), _xlpm.letraColumna )} -> R | Y93: {=_xlfn.LET( _xlpm.valor, INDEX(CostRate!I:I, MATCH(1, (CostRate!A:A=N93)*(CostRate!B:B=O93), 0)), _xlpm.posicion, MATCH(_xlpm.valor, FilterJP!$E$1:$FZ$1, 0), _xlpm.direccionCompleta, ADDRESS(1, _xlpm.posicion + 4, 4), _xlpm.letraColumna, SUBSTITUTE(_xlpm.direccionCompleta, "1", ""), _xlpm.letraColumna )} -> BO | AC93: =ROUNDUP($V93/(1-$AV$76),2) -> 66566.56 | AD93: =$T93*$AC93 -> 377432.4 | AE93: =IFERROR(1-($W93/$AD93),0) -> 0.30000003 | AG93: =IFERROR(IF(OR(ISBLANK(N93),N93=CustomerCountry,COUNTIF($N93,"*xDC*")),0,10%),0) -> 0 | AH93: =W93*AG93 -> 0 | AJ93: {=IFERROR(INDEX(WHT!$C$7:$W$18,MATCH( _xlfn.SWITCH(N93,"xDC Medellin","Colombia","xDC Belo Horizonte","Brazil","xDC Guadalajara","Mexico","xDC Gurugram","India","xDC Leon","Spain","xDC San Jose","Costa Rica","xDC Warsaw","Poland",N93), WHT!$B$7:$B$18,0),MATCH(CustomerCountry,WHT!$C$5:$W$5,0)),0)} -> 0 | AK93: =(W93+AH93)*AJ93 -> 0 | AM93: =SUM($AD93,$AH93,$AK93) -> 377432.4 | AN93: =AM93+IFERROR(SUM($AN$79:$AN$84)*AM93/$AM$88,0) -> 377432.4 | AO93: =IFERROR($AN93/$T93,0) -> 66566.56 | AS93: X | AT93: =IF(AS93="x",AM93+((SUM($AN$79:$AN$84)+SUMIF($AS$90:$AS$119,"<>x",$AM$90:$AM$119))*IFERROR(AM93/SUMIF($AS$90:$AS$119,"x",$AM$90:$AM$119),0)),0) -> 377432.4 | AV93: =IFERROR(AT93/T93,0) -> 66566.56 | AW93: =IFERROR(AV93/BusinessCurrencyTRM,"N/A") -> 17.068349
C94: Administrador Azure - 10% Horas Extras + 25% | G94: 0 | H94: 0 | I94: 0 | J94: =IFERROR(G94/(1-(H94+I94)),0) -> 0 | N94: xDC Medellin | O94: Other Services | P94: Expert Managed Operations | Q94: 1.23 | R94: {=$R$43*(1+(INDIRECT("CMSResumen!L"&(MAX(IF(INDIRECT("CMSResumen!B1:B"&ROW()-10)=B73,ROW(INDIRECT("CMSResumen!B1:B"&ROW()-10)),0)+18)))))} -> 0.078 | S94: =20*10% -> 2 | T94: =IF(ISBLANK($P94),0,IF(Approach="Team-Based",$Q94*$R94*$S94*HoursPerDayTeamBased,$J94)) -> 1.554228 | U94: 0 | V94: =ROUNDUP(IFERROR(INDEX(CostRateTbl[Cost Rate],MATCH(_xlfn.CONCAT(N94,O94,P94,"NA"),CostRateTbl[KeyCostRate],0)),0)*BillingCurrencyTRM*(1+U94),2) -> 0 | W94: =T94*V94 -> 0 | X94: {=_xlfn.LET( _xlpm.valor, INDEX(CostRate!H:H, MATCH(1, (CostRate!A:A=N94)*1, 0)), _xlpm.posicion, MATCH(_xlpm.valor, FilterSL!$F$1:$Z$1, 0), _xlpm.direccionCompleta, ADDRESS(1, _xlpm.posicion + 5, 4), _xlpm.letraColumna, SUBSTITUTE(_xlpm.direccionCompleta, "1", ""), _xlpm.letraColumna )} -> R | Y94: {=_xlfn.LET( _xlpm.valor, INDEX(CostRate!I:I, MATCH(1, (CostRate!A:A=N94)*(CostRate!B:B=O94), 0)), _xlpm.posicion, MATCH(_xlpm.valor, FilterJP!$E$1:$FZ$1, 0), _xlpm.direccionCompleta, ADDRESS(1, _xlpm.posicion + 4, 4), _xlpm.letraColumna, SUBSTITUTE(_xlpm.direccionCompleta, "1", ""), _xlpm.letraColumna )} -> BO | AC94: =ROUNDUP($V94/(1-$AV$76),2) -> 0 | AD94: =$T94*$AC94 -> 0 | AE94: =IFERROR(1-($W94/$AD94),0) -> 0 | AG94: =IFERROR(IF(OR(ISBLANK(N94),N94=CustomerCountry,COUNTIF($N94,"*xDC*")),0,10%),0) -> 0 | AH94: =W94*AG94 -> 0 | AJ94: {=IFERROR(INDEX(WHT!$C$7:$W$18,MATCH( _xlfn.SWITCH(N94,"xDC Medellin","Colombia","xDC Belo Horizonte","Brazil","xDC Guadalajara","Mexico","xDC Gurugram","India","xDC Leon","Spain","xDC San Jose","Costa Rica","xDC Warsaw","Poland",N94), WHT!$B$7:$B$18,0),MATCH(CustomerCountry,WHT!$C$5:$W$5,0)),0)} -> 0 | AK94: =(W94+AH94)*AJ94 -> 0 | AM94: =SUM($AD94,$AH94,$AK94) -> 0 | AN94: =AM94+IFERROR(SUM($AN$79:$AN$84)*AM94/$AM$88,0) -> 0 | AO94: =IFERROR($AN94/$T94,0) -> 0 | AS94: X | AT94: =IF(AS94="x",AM94+((SUM($AN$79:$AN$84)+SUMIF($AS$90:$AS$119,"<>x",$AM$90:$AM$119))*IFERROR(AM94/SUMIF($AS$90:$AS$119,"x",$AM$90:$AM$119),0)),0) -> 0 | AV94: =IFERROR(AT94/T94,0) -> 0 | AW94: =IFERROR(AV94/BusinessCurrencyTRM,"N/A") -> 0
C95: Monitoreo / operación - 10% Horas Extras + 25% | G95: 0 | H95: 0 | I95: 0 | J95: =IFERROR(G95/(1-(H95+I95)),0) -> 0 | N95: xDC Medellin | O95: Other Services | P95: Associate Expert Managed Operations | Q95: 1.23 | R95: {=$R$45*(1+(INDIRECT("CMSResumen!L"&(MAX(IF(INDIRECT("CMSResumen!B1:B"&ROW()-10)=B73,ROW(INDIRECT("CMSResumen!B1:B"&ROW()-10)),0)+20)))))} -> 0.035 | S95: =20*10% -> 2 | T95: =IF(ISBLANK($P95),0,IF(Approach="Team-Based",$Q95*$R95*$S95*HoursPerDayTeamBased,$J95)) -> 0.69741 | U95: 0 | V95: =ROUNDUP(IFERROR(INDEX(CostRateTbl[Cost Rate],MATCH(_xlfn.CONCAT(N95,O95,P95,"NA"),CostRateTbl[KeyCostRate],0)),0)*BillingCurrencyTRM*(1+U95),2) -> 46596.59 | W95: =T95*V95 -> 32496.928 | X95: {=_xlfn.LET( _xlpm.valor, INDEX(CostRate!H:H, MATCH(1, (CostRate!A:A=N95)*1, 0)), _xlpm.posicion, MATCH(_xlpm.valor, FilterSL!$F$1:$Z$1, 0), _xlpm.direccionCompleta, ADDRESS(1, _xlpm.posicion + 5, 4), _xlpm.letraColumna, SUBSTITUTE(_xlpm.direccionCompleta, "1", ""), _xlpm.letraColumna )} -> R | Y95: {=_xlfn.LET( _xlpm.valor, INDEX(CostRate!I:I, MATCH(1, (CostRate!A:A=N95)*(CostRate!B:B=O95), 0)), _xlpm.posicion, MATCH(_xlpm.valor, FilterJP!$E$1:$FZ$1, 0), _xlpm.direccionCompleta, ADDRESS(1, _xlpm.posicion + 4, 4), _xlpm.letraColumna, SUBSTITUTE(_xlpm.direccionCompleta, "1", ""), _xlpm.letraColumna )} -> BO | AC95: =ROUNDUP($V95/(1-$AV$76),2) -> 66566.56 | AD95: =$T95*$AC95 -> 46424.185 | AE95: =IFERROR(1-($W95/$AD95),0) -> 0.30000003 | AG95: =IFERROR(IF(OR(ISBLANK(N95),N95=CustomerCountry,COUNTIF($N95,"*xDC*")),0,10%),0) -> 0 | AH95: =W95*AG95 -> 0 | AJ95: {=IFERROR(INDEX(WHT!$C$7:$W$18,MATCH( _xlfn.SWITCH(N95,"xDC Medellin","Colombia","xDC Belo Horizonte","Brazil","xDC Guadalajara","Mexico","xDC Gurugram","India","xDC Leon","Spain","xDC San Jose","Costa Rica","xDC Warsaw","Poland",N95), WHT!$B$7:$B$18,0),MATCH(CustomerCountry,WHT!$C$5:$W$5,0)),0)} -> 0 | AK95: =(W95+AH95)*AJ95 -> 0 | AM95: =SUM($AD95,$AH95,$AK95) -> 46424.185 | AN95: =AM95+IFERROR(SUM($AN$79:$AN$84)*AM95/$AM$88,0) -> 46424.185 | AO95: =IFERROR($AN95/$T95,0) -> 66566.56 | AS95: X | AT95: =IF(AS95="x",AM95+((SUM($AN$79:$AN$84)+SUMIF($AS$90:$AS$119,"<>x",$AM$90:$AM$119))*IFERROR(AM95/SUMIF($AS$90:$AS$119,"x",$AM$90:$AM$119),0)),0) -> 46424.185 | AV95: =IFERROR(AT95/T95,0) -> 66566.56 | AW95: =IFERROR(AV95/BusinessCurrencyTRM,"N/A") -> 17.068349
C96: Administrador Azure - Disponibilidad - Incluir costo 200 USD x Mes | G96: 0 | H96: 0 | I96: 0 | J96: =IFERROR(G96/(1-(H96+I96)),0) -> 0 | S96: =IF(ISBLANK(P96),0,$O$82*20) -> 0 | T96: =IF(ISBLANK($P96),0,IF(Approach="Team-Based",$Q96*$R96*$S96*HoursPerDayTeamBased,$J96)) -> 0 | U96: 0 | V96: =ROUNDUP(IFERROR(INDEX(CostRateTbl[Cost Rate],MATCH(_xlfn.CONCAT(N96,O96,P96,"NA"),CostRateTbl[KeyCostRate],0)),0)*BillingCurrencyTRM*(1+U96),2) -> 0 | W96: =T96*V96 -> 0 | X96: {=_xlfn.LET( _xlpm.valor, INDEX(CostRate!H:H, MATCH(1, (CostRate!A:A=N96)*1, 0)), _xlpm.posicion, MATCH(_xlpm.valor, FilterSL!$F$1:$Z$1, 0), _xlpm.direccionCompleta, ADDRESS(1, _xlpm.posicion + 5, 4), _xlpm.letraColumna, SUBSTITUTE(_xlpm.direccionCompleta, "1", ""), _xlpm.letraColumna )} -> #N/A | Y96: {=_xlfn.LET( _xlpm.valor, INDEX(CostRate!I:I, MATCH(1, (CostRate!A:A=N96)*(CostRate!B:B=O96), 0)), _xlpm.posicion, MATCH(_xlpm.valor, FilterJP!$E$1:$FZ$1, 0), _xlpm.direccionCompleta, ADDRESS(1, _xlpm.posicion + 4, 4), _xlpm.letraColumna, SUBSTITUTE(_xlpm.direccionCompleta, "1", ""), _xlpm.letraColumna )} -> #N/A | AC96: =ROUNDUP($V96/(1-$AV$76),2) -> 0 | AD96: =$T96*$AC96 -> 0 | AE96: =IFERROR(1-($W96/$AD96),0) -> 0 | AG96: =IFERROR(IF(OR(ISBLANK(N96),N96=CustomerCountry,COUNTIF($N96,"*xDC*")),0,10%),0) -> 0 | AH96: =W96*AG96 -> 0 | AJ96: {=IFERROR(INDEX(WHT!$C$7:$W$18,MATCH( _xlfn.SWITCH(N96,"xDC Medellin","Colombia","xDC Belo Horizonte","Brazil","xDC Guadalajara","Mexico","xDC Gurugram","India","xDC Leon","Spain","xDC San Jose","Costa Rica","xDC Warsaw","Poland",N96), WHT!$B$7:$B$18,0),MATCH(CustomerCountry,WHT!$C$5:$W$5,0)),0)} -> 0 | AK96: =(W96+AH96)*AJ96 -> 0 | AM96: =SUM($AD96,$AH96,$AK96) -> 0 | AN96: =AM96+IFERROR(SUM($AN$79:$AN$84)*AM96/$AM$88,0) -> 0 | AO96: =IFERROR($AN96/$T96,0) -> 0 | AS96: X | AT96: =IF(AS96="x",AM96+((SUM($AN$79:$AN$84)+SUMIF($AS$90:$AS$119,"<>x",$AM$90:$AM$119))*IFERROR(AM96/SUMIF($AS$90:$AS$119,"x",$AM$90:$AM$119),0)),0) -> 0 | AV96: =IFERROR(AT96/T96,0) -> 0 | AW96: =IFERROR(AV96/BusinessCurrencyTRM,"N/A") -> 0
G97: 0 | H97: 0 | I97: 0 | J97: =IFERROR(G97/(1-(H97+I97)),0) -> 0 | S97: =IF(ISBLANK(P97),0,$O$82*20) -> 0 | T97: =IF(ISBLANK($P97),0,IF(Approach="Team-Based",$Q97*$R97*$S97*HoursPerDayTeamBased,$J97)) -> 0 | U97: 0 | V97: =ROUNDUP(IFERROR(INDEX(CostRateTbl[Cost Rate],MATCH(_xlfn.CONCAT(N97,O97,P97,"NA"),CostRateTbl[KeyCostRate],0)),0)*BillingCurrencyTRM*(1+U97),2) -> 0 | W97: =T97*V97 -> 0 | X97: {=_xlfn.LET( _xlpm.valor, INDEX(CostRate!H:H, MATCH(1, (CostRate!A:A=N97)*1, 0)), _xlpm.posicion, MATCH(_xlpm.valor, FilterSL!$F$1:$Z$1, 0), _xlpm.direccionCompleta, ADDRESS(1, _xlpm.posicion + 5, 4), _xlpm.letraColumna, SUBSTITUTE(_xlpm.direccionCompleta, "1", ""), _xlpm.letraColumna )} -> #N/A | Y97: {=_xlfn.LET( _xlpm.valor, INDEX(CostRate!I:I, MATCH(1, (CostRate!A:A=N97)*(CostRate!B:B=O97), 0)), _xlpm.posicion, MATCH(_xlpm.valor, FilterJP!$E$1:$FZ$1, 0), _xlpm.direccionCompleta, ADDRESS(1, _xlpm.posicion + 4, 4), _xlpm.letraColumna, SUBSTITUTE(_xlpm.direccionCompleta, "1", ""), _xlpm.letraColumna )} -> #N/A | AC97: =ROUNDUP($V97/(1-$AV$76),2) -> 0 | AD97: =$T97*$AC97 -> 0 | AE97: =IFERROR(1-($W97/$AD97),0) -> 0 | AG97: =IFERROR(IF(OR(ISBLANK(N97),N97=CustomerCountry,COUNTIF($N97,"*xDC*")),0,10%),0) -> 0 | AH97: =W97*AG97 -> 0 | AJ97: {=IFERROR(INDEX(WHT!$C$7:$W$18,MATCH( _xlfn.SWITCH(N97,"xDC Medellin","Colombia","xDC Belo Horizonte","Brazil","xDC Guadalajara","Mexico","xDC Gurugram","India","xDC Leon","Spain","xDC San Jose","Costa Rica","xDC Warsaw","Poland",N97), WHT!$B$7:$B$18,0),MATCH(CustomerCountry,WHT!$C$5:$W$5,0)),0)} -> 0 | AK97: =(W97+AH97)*AJ97 -> 0 | AM97: =SUM($AD97,$AH97,$AK97) -> 0 | AN97: =AM97+IFERROR(SUM($AN$79:$AN$84)*AM97/$AM$88,0) -> 0 | AO97: =IFERROR($AN97/$T97,0) -> 0 | AS97: X | AT97: =IF(AS97="x",AM97+((SUM($AN$79:$AN$84)+SUMIF($AS$90:$AS$119,"<>x",$AM$90:$AM$119))*IFERROR(AM97/SUMIF($AS$90:$AS$119,"x",$AM$90:$AM$119),0)),0) -> 0 | AV97: =IFERROR(AT97/T97,0) -> 0 | AW97: =IFERROR(AV97/BusinessCurrencyTRM,"N/A") -> 0
G98: 0 | H98: 0 | I98: 0 | J98: =IFERROR(G98/(1-(H98+I98)),0) -> 0 | S98: =IF(ISBLANK(P98),0,$O$82*20) -> 0 | T98: =IF(ISBLANK($P98),0,IF(Approach="Team-Based",$Q98*$R98*$S98*HoursPerDayTeamBased,$J98)) -> 0 | U98: 0 | V98: =ROUNDUP(IFERROR(INDEX(CostRateTbl[Cost Rate],MATCH(_xlfn.CONCAT(N98,O98,P98,"NA"),CostRateTbl[KeyCostRate],0)),0)*BillingCurrencyTRM*(1+U98),2) -> 0 | W98: =T98*V98 -> 0 | X98: {=_xlfn.LET( _xlpm.valor, INDEX(CostRate!H:H, MATCH(1, (CostRate!A:A=N98)*1, 0)), _xlpm.posicion, MATCH(_xlpm.valor, FilterSL!$F$1:$Z$1, 0), _xlpm.direccionCompleta, ADDRESS(1, _xlpm.posicion + 5, 4), _xlpm.letraColumna, SUBSTITUTE(_xlpm.direccionCompleta, "1", ""), _xlpm.letraColumna )} -> #N/A | Y98: {=_xlfn.LET( _xlpm.valor, INDEX(CostRate!I:I, MATCH(1, (CostRate!A:A=N98)*(CostRate!B:B=O98), 0)), _xlpm.posicion, MATCH(_xlpm.valor, FilterJP!$E$1:$FZ$1, 0), _xlpm.direccionCompleta, ADDRESS(1, _xlpm.posicion + 4, 4), _xlpm.letraColumna, SUBSTITUTE(_xlpm.direccionCompleta, "1", ""), _xlpm.letraColumna )} -> #N/A | AC98: =ROUNDUP($V98/(1-$AV$76),2) -> 0 | AD98: =$T98*$AC98 -> 0 | AE98: =IFERROR(1-($W98/$AD98),0) -> 0 | AG98: =IFERROR(IF(OR(ISBLANK(N98),N98=CustomerCountry,COUNTIF($N98,"*xDC*")),0,10%),0) -> 0 | AH98: =W98*AG98 -> 0 | AJ98: {=IFERROR(INDEX(WHT!$C$7:$W$18,MATCH( _xlfn.SWITCH(N98,"xDC Medellin","Colombia","xDC Belo Horizonte","Brazil","xDC Guadalajara","Mexico","xDC Gurugram","India","xDC Leon","Spain","xDC San Jose","Costa Rica","xDC Warsaw","Poland",N98), WHT!$B$7:$B$18,0),MATCH(CustomerCountry,WHT!$C$5:$W$5,0)),0)} -> 0 | AK98: =(W98+AH98)*AJ98 -> 0 | AM98: =SUM($AD98,$AH98,$AK98) -> 0 | AN98: =AM98+IFERROR(SUM($AN$79:$AN$84)*AM98/$AM$88,0) -> 0 | AO98: =IFERROR($AN98/$T98,0) -> 0 | AS98: X | AT98: =IF(AS98="x",AM98+((SUM($AN$79:$AN$84)+SUMIF($AS$90:$AS$119,"<>x",$AM$90:$AM$119))*IFERROR(AM98/SUMIF($AS$90:$AS$119,"x",$AM$90:$AM$119),0)),0) -> 0 | AV98: =IFERROR(AT98/T98,0) -> 0 | AW98: =IFERROR(AV98/BusinessCurrencyTRM,"N/A") -> 0
G99: 0 | H99: 0 | I99: 0 | J99: =IFERROR(G99/(1-(H99+I99)),0) -> 0 | S99: =IF(ISBLANK(P99),0,$O$82*20) -> 0 | T99: =IF(ISBLANK($P99),0,IF(Approach="Team-Based",$Q99*$R99*$S99*HoursPerDayTeamBased,$J99)) -> 0 | U99: 0 | V99: =ROUNDUP(IFERROR(INDEX(CostRateTbl[Cost Rate],MATCH(_xlfn.CONCAT(N99,O99,P99,"NA"),CostRateTbl[KeyCostRate],0)),0)*BillingCurrencyTRM*(1+U99),2) -> 0 | W99: =T99*V99 -> 0 | X99: {=_xlfn.LET( _xlpm.valor, INDEX(CostRate!H:H, MATCH(1, (CostRate!A:A=N99)*1, 0)), _xlpm.posicion, MATCH(_xlpm.valor, FilterSL!$F$1:$Z$1, 0), _xlpm.direccionCompleta, ADDRESS(1, _xlpm.posicion + 5, 4), _xlpm.letraColumna, SUBSTITUTE(_xlpm.direccionCompleta, "1", ""), _xlpm.letraColumna )} -> #N/A | Y99: {=_xlfn.LET( _xlpm.valor, INDEX(CostRate!I:I, MATCH(1, (CostRate!A:A=N99)*(CostRate!B:B=O99), 0)), _xlpm.posicion, MATCH(_xlpm.valor, FilterJP!$E$1:$FZ$1, 0), _xlpm.direccionCompleta, ADDRESS(1, _xlpm.posicion + 4, 4), _xlpm.letraColumna, SUBSTITUTE(_xlpm.direccionCompleta, "1", ""), _xlpm.letraColumna )} -> #N/A | AC99: =ROUNDUP($V99/(1-$AV$76),2) -> 0 | AD99: =$T99*$AC99 -> 0 | AE99: =IFERROR(1-($W99/$AD99),0) -> 0 | AG99: =IFERROR(IF(OR(ISBLANK(N99),N99=CustomerCountry,COUNTIF($N99,"*xDC*")),0,10%),0) -> 0 | AH99: =W99*AG99 -> 0 | AJ99: {=IFERROR(INDEX(WHT!$C$7:$W$18,MATCH( _xlfn.SWITCH(N99,"xDC Medellin","Colombia","xDC Belo Horizonte","Brazil","xDC Guadalajara","Mexico","xDC Gurugram","India","xDC Leon","Spain","xDC San Jose","Costa Rica","xDC Warsaw","Poland",N99), WHT!$B$7:$B$18,0),MATCH(CustomerCountry,WHT!$C$5:$W$5,0)),0)} -> 0 | AK99: =(W99+AH99)*AJ99 -> 0 | AM99: =SUM($AD99,$AH99,$AK99) -> 0 | AN99: =AM99+IFERROR(SUM($AN$79:$AN$84)*AM99/$AM$88,0) -> 0 | AO99: =IFERROR($AN99/$T99,0) -> 0 | AS99: X | AT99: =IF(AS99="x",AM99+((SUM($AN$79:$AN$84)+SUMIF($AS$90:$AS$119,"<>x",$AM$90:$AM$119))*IFERROR(AM99/SUMIF($AS$90:$AS$119,"x",$AM$90:$AM$119),0)),0) -> 0 | AV99: =IFERROR(AT99/T99,0) -> 0 | AW99: =IFERROR(AV99/BusinessCurrencyTRM,"N/A") -> 0
G100: 0 | H100: 0 | I100: 0 | J100: =IFERROR(G100/(1-(H100+I100)),0) -> 0 | S100: =IF(ISBLANK(P100),0,$O$82*20) -> 0 | T100: =IF(ISBLANK($P100),0,IF(Approach="Team-Based",$Q100*$R100*$S100*HoursPerDayTeamBased,$J100)) -> 0 | U100: 0 | V100: =ROUNDUP(IFERROR(INDEX(CostRateTbl[Cost Rate],MATCH(_xlfn.CONCAT(N100,O100,P100,"NA"),CostRateTbl[KeyCostRate],0)),0)*BillingCurrencyTRM*(1+U100),2) -> 0 | W100: =T100*V100 -> 0 | X100: {=_xlfn.LET( _xlpm.valor, INDEX(CostRate!H:H, MATCH(1, (CostRate!A:A=N100)*1, 0)), _xlpm.posicion, MATCH(_xlpm.valor, FilterSL!$F$1:$Z$1, 0), _xlpm.direccionCompleta, ADDRESS(1, _xlpm.posicion + 5, 4), _xlpm.letraColumna, SUBSTITUTE(_xlpm.direccionCompleta, "1", ""), _xlpm.letraColumna )} -> #N/A | Y100: {=_xlfn.LET( _xlpm.valor, INDEX(CostRate!I:I, MATCH(1, (CostRate!A:A=N100)*(CostRate!B:B=O100), 0)), _xlpm.posicion, MATCH(_xlpm.valor, FilterJP!$E$1:$FZ$1, 0), _xlpm.direccionCompleta, ADDRESS(1, _xlpm.posicion + 4, 4), _xlpm.letraColumna, SUBSTITUTE(_xlpm.direccionCompleta, "1", ""), _xlpm.letraColumna )} -> #N/A | AC100: =ROUNDUP($V100/(1-$AV$76),2) -> 0 | AD100: =$T100*$AC100 -> 0 | AE100: =IFERROR(1-($W100/$AD100),0) -> 0 | AG100: =IFERROR(IF(OR(ISBLANK(N100),N100=CustomerCountry,COUNTIF($N100,"*xDC*")),0,10%),0) -> 0 | AH100: =W100*AG100 -> 0 | AJ100: {=IFERROR(INDEX(WHT!$C$7:$W$18,MATCH( _xlfn.SWITCH(N100,"xDC Medellin","Colombia","xDC Belo Horizonte","Brazil","xDC Guadalajara","Mexico","xDC Gurugram","India","xDC Leon","Spain","xDC San Jose","Costa Rica","xDC Warsaw","Poland",N100), WHT!$B$7:$B$18,0),MATCH(CustomerCountry,WHT!$C$5:$W$5,0)),0)} -> 0 | AK100: =(W100+AH100)*AJ100 -> 0 | AM100: =SUM($AD100,$AH100,$AK100) -> 0 | AN100: =AM100+IFERROR(SUM($AN$79:$AN$84)*AM100/$AM$88,0) -> 0 | AO100: =IFERROR($AN100/$T100,0) -> 0 | AS100: X | AT100: =IF(AS100="x",AM100+((SUM($AN$79:$AN$84)+SUMIF($AS$90:$AS$119,"<>x",$AM$90:$AM$119))*IFERROR(AM100/SUMIF($AS$90:$AS$119,"x",$AM$90:$AM$119),0)),0) -> 0 | AV100: =IFERROR(AT100/T100,0) -> 0 | AW100: =IFERROR(AV100/BusinessCurrencyTRM,"N/A") -> 0
